Workbook

Sheet SEGUIMIENTO_PROYECTOS
A1: CONTROL DE PROYECTOS — ENTREGABLES Y CONFORMIDAD DEL SERVICIO
A2: Actualizado al: 29/05/2026 · VERDE=OK ROJO=PENDIENTE AMARILLO=Falta firma AZUL=En proceso GRIS=No aplica
A3: DATOS DEL PROYECTO | E3: GESTIÓN | H3: RESPONSABLES | J3: ENTREGABLES SIG | T3: COMENTARIOS | U3: ÚLT. SEGUIMIENTO | V3: % SIG | W3: ESTADO
A4: AÑO CIERRE | B4: N° PROYECTO | C4: NOMBRE DEL PROYECTO | D4: TIPO SGC | E4: ALCANCE DEL SERVICIO | F4: ETAPA ACTUAL | G4: FECHA CIERRE SERVICIO | H4: RESPONSABLE (JEFE) | I4: EQUIPO / JS (referencial) | J4: FICHA PROY. | K4: ACS | L4: SERVIDOR SIG | M4: EVAL. PROV. CCP | N4: DESEMPEÑO PROV. | O4: LECCIONES APRENDIDAS | P4: REPORTES (RA) | Q4: ACTAS REUNIÓN | R4: ESC / SOLICITUD CLIENTE | S4: DEBIDA DILIGENCIA | T4: COMENTARIOS | U4: ÚLT. SEGUIMIENTO | V4: % CUMPL. SIG | W4: ESTADO GENERAL | X4: APLICA (aux) | Y4: PTS (aux)
X5: =10-COUNTIF(J5:S5,"NO APLICA")-COUNTIF(J5:S5,"-")-COUNTIF(J5:S5,"") -> 0 | Y5: =COUNTIF(J5:S5,"OK")+COUNTIF(J5:S5,"EN PROCESO")*0.5 -> 0
A6: 2026 | B6: 23004 | C6: OBRAS INTERBANK | D6: D | E6: SUP | F6: POR INICIAR | H6: B. López | O6: NO APLICA | Q6: NO APLICA | S6: NO APLICA | T6: Inicio 08-06 | V6: =IFERROR((COUNTIF(J6:S6,"OK")+COUNTIF(J6:S6,"EN PROCESO")*0.5)/(10-COUNTIF(J6:S6,"NO APLICA")-COUNTIF(J6:S6,"DESCARTADA")-COUNTIF(J6:S6,"-")-COUNTIF(J6:S6,"")),"") | W6: =IF(ISNUMBER(V6),IF(V6>=0.9,"CONFORME",IF(V6>=0.5,"ALERTA","CRITICO")),IF(F6="CANCELADO","CANCELADO",IF(F6="STAND BY","STAND BY",IF(F6="DESCARTADO","DESCARTADO","S/D")))) -> S/D | X6: =10-COUNTIF(J6:S6,"NO APLICA")-COUNTIF(J6:S6,"-")-COUNTIF(J6:S6,"") -> 0 | Y6: =COUNTIF(J6:S6,"OK")+COUNTIF(J6:S6,"EN PROCESO")*0.5 -> 0
A7: 2026 | B7: 23003 | C7: ASCENSOR BCP HUANCAYO | D7: D | E7: SUP | F7: SUP | G7: 46189 | H7: F. Choque | I7: Nataly Muñante | J7: NO APLICA | L7: PENDIENTE | M7: NO APLICA | N7: NO APLICA | O7: NO APLICA | P7: OK | Q7: NO APLICA | S7: NO APLICA | V7: =IFERROR((COUNTIF(J7:S7,"OK")+COUNTIF(J7:S7,"EN PROCESO")*0.5)/(10-COUNTIF(J7:S7,"NO APLICA")-COUNTIF(J7:S7,"DESCARTADA")-COUNTIF(J7:S7,"-")-COUNTIF(J7:S7,"")),"") -> 0.5 | W7: =IF(ISNUMBER(V7),IF(V7>=0.9,"CONFORME",IF(V7>=0.5,"ALERTA","CRITICO")),IF(F7="CANCELADO","CANCELADO",IF(F7="STAND BY","STAND BY",IF(F7="DESCARTADO","DESCARTADO","S/D")))) -> ALERTA | X7: =10-COUNTIF(J7:S7,"NO APLICA")-COUNTIF(J7:S7,"-")-COUNTIF(J7:S7,"") -> 2 | Y7: =COUNTIF(J7:S7,"OK")+COUNTIF(J7:S7,"EN PROCESO")*0.5 -> 1
A8: 2026 | B8: 23002 | C8: SODIMAC SAN MIGUEL | D8: D | E8: SUP | F8: SUP | G8: 46203 | H8: B. López | J8: NO APLICA | K8: NO APLICA | M8: NO APLICA | N8: NO APLICA | O8: NO APLICA | P8: NO APLICA | Q8: NO APLICA | S8: NO APLICA | V8: =IFERROR((COUNTIF(J8:S8,"OK")+COUNTIF(J8:S8,"EN PROCESO")*0.5)/(10-COUNTIF(J8:S8,"NO APLICA")-COUNTIF(J8:S8,"DESCARTADA")-COUNTIF(J8:S8,"-")-COUNTIF(J8:S8,"")),"") | W8: =IF(ISNUMBER(V8),IF(V8>=0.9,"CONFORME",IF(V8>=0.5,"ALERTA","CRITICO")),IF(F8="CANCELADO","CANCELADO",IF(F8="STAND BY","STAND BY",IF(F8="DESCARTADO","DESCARTADO","S/D")))) -> S/D | X8: =10-COUNTIF(J8:S8,"NO APLICA")-COUNTIF(J8:S8,"-")-COUNTIF(J8:S8,"") -> 0 | Y8: =COUNTIF(J8:S8,"OK")+COUNTIF(J8:S8,"EN PROCESO")*0.5 -> 0
A9: 2026 | B9: 23001 | C9: AUDITORÍA HAYDUK | D9: D | E9: CONS | F9: POR INICIAR | H9: P. Lavado | J9: NO APLICA | O9: NO APLICA | Q9: NO APLICA | V9: =IFERROR((COUNTIF(J9:S9,"OK")+COUNTIF(J9:S9,"EN PROCESO")*0.5)/(10-COUNTIF(J9:S9,"NO APLICA")-COUNTIF(J9:S9,"DESCARTADA")-COUNTIF(J9:S9,"-")-COUNTIF(J9:S9,"")),"") | W9: =IF(ISNUMBER(V9),IF(V9>=0.9,"CONFORME",IF(V9>=0.5,"ALERTA","CRITICO")),IF(F9="CANCELADO","CANCELADO",IF(F9="STAND BY","STAND BY",IF(F9="DESCARTADO","DESCARTADO","S/D")))) -> S/D | X9: =10-COUNTIF(J9:S9,"NO APLICA")-COUNTIF(J9:S9,"-")-COUNTIF(J9:S9,"") -> 0 | Y9: =COUNTIF(J9:S9,"OK")+COUNTIF(J9:S9,"EN PROCESO")*0.5 -> 0
A10: 2026 | B10: 23000 | C10: AMPLIACIÓN CD FF&VV CENCOSUD | D10: A | E10: ING, LIC, SUP | F10: ING | H10: M. Becerra | J10: PENDIENTE | V10: =IFERROR((COUNTIF(J10:S10,"OK")+COUNTIF(J10:S10,"EN PROCESO")*0.5)/(10-COUNTIF(J10:S10,"NO APLICA")-COUNTIF(J10:S10,"DESCARTADA")-COUNTIF(J10:S10,"-")-COUNTIF(J10:S10,"")),"") -> 0 | W10: =IF(ISNUMBER(V10),IF(V10>=0.9,"CONFORME",IF(V10>=0.5,"ALERTA","CRITICO")),IF(F10="CANCELADO","CANCELADO",IF(F10="STAND BY","STAND BY",IF(F10="DESCARTADO","DESCARTADO","S/D")))) -> CRITICO | X10: =10-COUNTIF(J10:S10,"NO APLICA")-COUNTIF(J10:S10,"-")-COUNTIF(J10:S10,"") -> 1 | Y10: =COUNTIF(J10:S10,"OK")+COUNTIF(J10:S10,"EN PROCESO")*0.5 -> 0
A11: 2026 | B11: 22999 | C11: ESCALERA PISO 7 y 8 OFICINAS TMH | D11: D | E11: SUP | F11: SUP | G11: 46193 | H11: F. Choque | I11: José Cruz | J11: NO APLICA | L11: PENDIENTE | M11: NO APLICA | N11: NO APLICA | O11: NO APLICA | P11: OK | Q11: OK | S11: NO APLICA | V11: =IFERROR((COUNTIF(J11:S11,"OK")+COUNTIF(J11:S11,"EN PROCESO")*0.5)/(10-COUNTIF(J11:S11,"NO APLICA")-COUNTIF(J11:S11,"DESCARTADA")-COUNTIF(J11:S11,"-")-COUNTIF(J11:S11,"")),"") -> 0.66666667 | W11: =IF(ISNUMBER(V11),IF(V11>=0.9,"CONFORME",IF(V11>=0.5,"ALERTA","CRITICO")),IF(F11="CANCELADO","CANCELADO",IF(F11="STAND BY","STAND BY",IF(F11="DESCARTADO","DESCARTADO","S/D")))) -> ALERTA | X11: =10-COUNTIF(J11:S11,"NO APLICA")-COUNTIF(J11:S11,"-")-COUNTIF(J11:S11,"") -> 3 | Y11: =COUNTIF(J11:S11,"OK")+COUNTIF(J11:S11,"EN PROCESO")*0.5 -> 2
A12: 2026 | B12: 22998 | C12: MÓDULOS PUKAMANI MAXCO | D12: D | E12: ING | F12: ING | G12: 46188 | H12: M. Becerra | J12: NO APLICA | L12: PENDIENTE | M12: PENDIENTE | O12: NO APLICA | P12: NO APLICA | Q12: NO APLICA | S12: EN PROCESO | V12: =IFERROR((COUNTIF(J12:S12,"OK")+COUNTIF(J12:S12,"EN PROCESO")*0.5)/(10-COUNTIF(J12:S12,"NO APLICA")-COUNTIF(J12:S12,"DESCARTADA")-COUNTIF(J12:S12,"-")-COUNTIF(J12:S12,"")),"") -> 0.16666667 | W12: =IF(ISNUMBER(V12),IF(V12>=0.9,"CONFORME",IF(V12>=0.5,"ALERTA","CRITICO")),IF(F12="CANCELADO","CANCELADO",IF(F12="STAND BY","STAND BY",IF(F12="DESCARTADO","DESCARTADO","S/D")))) -> CRITICO | X12: =10-COUNTIF(J12:S12,"NO APLICA")-COUNTIF(J12:S12,"-")-COUNTIF(J12:S12,"") -> 3 | Y12: =COUNTIF(J12:S12,"OK")+COUNTIF(J12:S12,"EN PROCESO")*0.5 -> 0.5
A13: 2026 | B13: 22997 | C13: H.U. VELAMAR ETAPAS 2 Y 3 PISCO | D13: C | E13: SUP | F13: SUP | G13: 46260 | H13: B. López | I13: Augusto Quio | J13: PENDIENTE | L13: PENDIENTE | M13: NO APLICA | P13: OK | Q13: PENDIENTE | S13: NO APLICA | V13: =IFERROR((COUNTIF(J13:S13,"OK")+COUNTIF(J13:S13,"EN PROCESO")*0.5)/(10-COUNTIF(J13:S13,"NO APLICA")-COUNTIF(J13:S13,"DESCARTADA")-COUNTIF(J13:S13,"-")-COUNTIF(J13:S13,"")),"") -> 0.25 | W13: =IF(ISNUMBER(V13),IF(V13>=0.9,"CONFORME",IF(V13>=0.5,"ALERTA","CRITICO")),IF(F13="CANCELADO","CANCELADO",IF(F13="STAND BY","STAND BY",IF(F13="DESCARTADO","DESCARTADO","S/D")))) -> CRITICO | X13: =10-COUNTIF(J13:S13,"NO APLICA")-COUNTIF(J13:S13,"-")-COUNTIF(J13:S13,"") -> 4 | Y13: =COUNTIF(J13:S13,"OK")+COUNTIF(J13:S13,"EN PROCESO")*0.5 -> 1
A14: 2026 | B14: 22996 | C14: MEDICIÓN RUIDO METRO HUNTER 2026 | D14: D | E14: CONS | F14: CONS | H14: F. Choque | J14: NO APLICA | L14: PENDIENTE | M14: PENDIENTE | O14: NO APLICA | P14: NO APLICA | Q14: NO APLICA | T14: Servicio 02 días | V14: =IFERROR((COUNTIF(J14:S14,"OK")+COUNTIF(J14:S14,"EN PROCESO")*0.5)/(10-COUNTIF(J14:S14,"NO APLICA")-COUNTIF(J14:S14,"DESCARTADA")-COUNTIF(J14:S14,"-")-COUNTIF(J14:S14,"")),"") -> 0 | W14: =IF(ISNUMBER(V14),IF(V14>=0.9,"CONFORME",IF(V14>=0.5,"ALERTA","CRITICO")),IF(F14="CANCELADO","CANCELADO",IF(F14="STAND BY","STAND BY",IF(F14="DESCARTADO","DESCARTADO","S/D")))) -> CRITICO | X14: =10-COUNTIF(J14:S14,"NO APLICA")-COUNTIF(J14:S14,"-")-COUNTIF(J14:S14,"") -> 2 | Y14: =COUNTIF(J14:S14,"OK")+COUNTIF(J14:S14,"EN PROCESO")*0.5 -> 0
A15: 2026 | B15: 22995 | C15: FARMACIAS PERUANAS 2026-2028 | D15: D | E15: SUP | F15: SUP | G15: 46753 | H15: A. Ferrer | I15: César Menez | J15: NO APLICA | L15: PENDIENTE | M15: NO APLICA | O15: NO APLICA | P15: OK | Q15: NO APLICA | S15: OK | V15: =IFERROR((COUNTIF(J15:S15,"OK")+COUNTIF(J15:S15,"EN PROCESO")*0.5)/(10-COUNTIF(J15:S15,"NO APLICA")-COUNTIF(J15:S15,"DESCARTADA")-COUNTIF(J15:S15,"-")-COUNTIF(J15:S15,"")),"") -> 0.66666667 | W15: =IF(ISNUMBER(V15),IF(V15>=0.9,"CONFORME",IF(V15>=0.5,"ALERTA","CRITICO")),IF(F15="CANCELADO","CANCELADO",IF(F15="STAND BY","STAND BY",IF(F15="DESCARTADO","DESCARTADO","S/D")))) -> ALERTA | X15: =10-COUNTIF(J15:S15,"NO APLICA")-COUNTIF(J15:S15,"-")-COUNTIF(J15:S15,"") -> 3 | Y15: =COUNTIF(J15:S15,"OK")+COUNTIF(J15:S15,"EN PROCESO")*0.5 -> 2
A16: 2026 | B16: 22994 | C16: COORDINADORES REAL PLAZA | D16: D | E16: CONS | F16: CONS | G16: 46340 | H16: B. López | I16: Denis Bermudez | J16: NO APLICA | K16: NO APLICA | M16: NO APLICA | N16: NO APLICA | O16: NO APLICA | P16: NO APLICA | Q16: NO APLICA | S16: NO APLICA | V16: =IFERROR((COUNTIF(J16:S16,"OK")+COUNTIF(J16:S16,"EN PROCESO")*0.5)/(10-COUNTIF(J16:S16,"NO APLICA")-COUNTIF(J16:S16,"DESCARTADA")-COUNTIF(J16:S16,"-")-COUNTIF(J16:S16,"")),"") | W16: =IF(ISNUMBER(V16),IF(V16>=0.9,"CONFORME",IF(V16>=0.5,"ALERTA","CRITICO")),IF(F16="CANCELADO","CANCELADO",IF(F16="STAND BY","STAND BY",IF(F16="DESCARTADO","DESCARTADO","S/D")))) -> S/D | X16: =10-COUNTIF(J16:S16,"NO APLICA")-COUNTIF(J16:S16,"-")-COUNTIF(J16:S16,"") -> 0 | Y16: =COUNTIF(J16:S16,"OK")+COUNTIF(J16:S16,"EN PROCESO")*0.5 -> 0
A17: 2026 | B17: 22993 | C17: HVAC RP CAJAMARCA | D17: D | E17: SUP | F17: POR INICIAR | G17: 46223 | H17: M. Becerra | J17: NO APLICA | K17: NO APLICA | M17: NO APLICA | N17: NO APLICA | O17: NO APLICA | Q17: NO APLICA | T17: Fecha de inicio 22-06 | V17: =IFERROR((COUNTIF(J17:S17,"OK")+COUNTIF(J17:S17,"EN PROCESO")*0.5)/(10-COUNTIF(J17:S17,"NO APLICA")-COUNTIF(J17:S17,"DESCARTADA")-COUNTIF(J17:S17,"-")-COUNTIF(J17:S17,"")),"") | W17: =IF(ISNUMBER(V17),IF(V17>=0.9,"CONFORME",IF(V17>=0.5,"ALERTA","CRITICO")),IF(F17="CANCELADO","CANCELADO",IF(F17="STAND BY","STAND BY",IF(F17="DESCARTADO","DESCARTADO","S/D")))) -> S/D | X17: =10-COUNTIF(J17:S17,"NO APLICA")-COUNTIF(J17:S17,"-")-COUNTIF(J17:S17,"") -> 0 | Y17: =COUNTIF(J17:S17,"OK")+COUNTIF(J17:S17,"EN PROCESO")*0.5 -> 0
A18: 2026 | B18: 22992 | C18: 03 SEDES AREQUIPA UTP | D18: D | E18: SUP | F18: SUP | G18: 46195 | H18: B. López | I18: Dushan Ibarra / Juan Vizcarra | J18: NO APLICA | L18: PENDIENTE | M18: NO APLICA | N18: NO APLICA | O18: NO APLICA | P18: OK | Q18: NO APLICA | S18: NO APLICA | V18: =IFERROR((COUNTIF(J18:S18,"OK")+COUNTIF(J18:S18,"EN PROCESO")*0.5)/(10-COUNTIF(J18:S18,"NO APLICA")-COUNTIF(J18:S18,"DESCARTADA")-COUNTIF(J18:S18,"-")-COUNTIF(J18:S18,"")),"") -> 0.5 | W18: =IF(ISNUMBER(V18),IF(V18>=0.9,"CONFORME",IF(V18>=0.5,"ALERTA","CRITICO")),IF(F18="CANCELADO","CANCELADO",IF(F18="STAND BY","STAND BY",IF(F18="DESCARTADO","DESCARTADO","S/D")))) -> ALERTA | X18: =10-COUNTIF(J18:S18,"NO APLICA")-COUNTIF(J18:S18,"-")-COUNTIF(J18:S18,"") -> 2 | Y18: =COUNTIF(J18:S18,"OK")+COUNTIF(J18:S18,"EN PROCESO")*0.5 -> 1
A19: 2026 | B19: 22991 | C19: TALLERES CRC LA JOYA FESA | D19: C | E19: SUP | F19: SUP | G19: 46216 | H19: F. Choque | I19: Santiago Guzmán | J19: PENDIENTE | L19: PENDIENTE | M19: NO APLICA | N19: NO APLICA | P19: OK | Q19: OK | V19: =IFERROR((COUNTIF(J19:S19,"OK")+COUNTIF(J19:S19,"EN PROCESO")*0.5)/(10-COUNTIF(J19:S19,"NO APLICA")-COUNTIF(J19:S19,"DESCARTADA")-COUNTIF(J19:S19,"-")-COUNTIF(J19:S19,"")),"") -> 0.5 | W19: =IF(ISNUMBER(V19),IF(V19>=0.9,"CONFORME",IF(V19>=0.5,"ALERTA","CRITICO")),IF(F19="CANCELADO","CANCELADO",IF(F19="STAND BY","STAND BY",IF(F19="DESCARTADO","DESCARTADO","S/D")))) -> ALERTA | X19: =10-COUNTIF(J19:S19,"NO APLICA")-COUNTIF(J19:S19,"-")-COUNTIF(J19:S19,"") -> 4 | Y19: =COUNTIF(J19:S19,"OK")+COUNTIF(J19:S19,"EN PROCESO")*0.5 -> 2
A20: 2026 | B20: 22990 | C20: TRABAJOS MENORES TORRE IBK | D20: D | E20: SUP | F20: CERRADO | H20: B. López | J20: NO APLICA | K20: NO APLICA | L20: PENDIENTE | M20: NO APLICA | N20: NO APLICA | O20: NO APLICA | P20: OK | Q20: NO APLICA | R20: NO APLICA | S20: NO APLICA | T20: Alcance 02 visitas | U20: 46177 | V20: =IFERROR((COUNTIF(J20:S20,"OK")+COUNTIF(J20:S20,"EN PROCESO")*0.5)/(10-COUNTIF(J20:S20,"NO APLICA")-COUNTIF(J20:S20,"DESCARTADA")-COUNTIF(J20:S20,"-")-COUNTIF(J20:S20,"")),"") -> 0.5 | W20: =IF(ISNUMBER(V20),IF(V20>=0.9,"CONFORME",IF(V20>=0.5,"ALERTA","CRITICO")),IF(F20="CANCELADO","CANCELADO",IF(F20="STAND BY","STAND BY",IF(F20="DESCARTADO","DESCARTADO","S/D")))) -> ALERTA | X20: =10-COUNTIF(J20:S20,"NO APLICA")-COUNTIF(J20:S20,"-")-COUNTIF(J20:S20,"") -> 2 | Y20: =COUNTIF(J20:S20,"OK")+COUNTIF(J20:S20,"EN PROCESO")*0.5 -> 1
A21: 2026 | B21: 22989 | C21: REFORZAMIENTO EST PTAR SAN CLARA | D21: D | E21: SUP | F21: SUP | G21: 46188 | H21: B. López | I21: Pablo Duran | J21: NO APLICA | L21: PENDIENTE | M21: NO APLICA | N21: NO APLICA | O21: NO APLICA | P21: OK | Q21: NO APLICA | S21: NO APLICA | T21: Fin del servicio 16-05 | V21: =IFERROR((COUNTIF(J21:S21,"OK")+COUNTIF(J21:S21,"EN PROCESO")*0.5)/(10-COUNTIF(J21:S21,"NO APLICA")-COUNTIF(J21:S21,"DESCARTADA")-COUNTIF(J21:S21,"-")-COUNTIF(J21:S21,"")),"") -> 0.5 | W21: =IF(ISNUMBER(V21),IF(V21>=0.9,"CONFORME",IF(V21>=0.5,"ALERTA","CRITICO")),IF(F21="CANCELADO","CANCELADO",IF(F21="STAND BY","STAND BY",IF(F21="DESCARTADO","DESCARTADO","S/D")))) -> ALERTA | X21: =10-COUNTIF(J21:S21,"NO APLICA")-COUNTIF(J21:S21,"-")-COUNTIF(J21:S21,"") -> 2 | Y21: =COUNTIF(J21:S21,"OK")+COUNTIF(J21:S21,"EN PROCESO")*0.5 -> 1
A22: 2026 | B22: 22988 | C22: AUDITORIA ET MALL PLAZA TRUJILLO | D22: D | E22: RI | F22: CERRADO | H22: B. López | J22: NO APLICA | K22: PENDIENTE | L22: PENDIENTE | M22: PENDIENTE | N22: PENDIENTE | O22: NO APLICA | P22: NO APLICA | Q22: NO APLICA | R22: NO APLICA | S22: OK | T22: Proveedor Alfarero | U22: 46177 | V22: =IFERROR((COUNTIF(J22:S22,"OK")+COUNTIF(J22:S22,"EN PROCESO")*0.5)/(10-COUNTIF(J22:S22,"NO APLICA")-COUNTIF(J22:S22,"DESCARTADA")-COUNTIF(J22:S22,"-")-COUNTIF(J22:S22,"")),"") -> 0.2 | W22: =IF(ISNUMBER(V22),IF(V22>=0.9,"CONFORME",IF(V22>=0.5,"ALERTA","CRITICO")),IF(F22="CANCELADO","CANCELADO",IF(F22="STAND BY","STAND BY",IF(F22="DESCARTADO","DESCARTADO","S/D")))) -> CRITICO | X22: =10-COUNTIF(J22:S22,"NO APLICA")-COUNTIF(J22:S22,"-")-COUNTIF(J22:S22,"") -> 5 | Y22: =COUNTIF(J22:S22,"OK")+COUNTIF(J22:S22,"EN PROCESO")*0.5 -> 1
A23: 2026 | B23: 22987 | C23: DIRECTIVAS PROYECTOS AIJC LAP - FASE 03 | D23: A | E23: CONS | F23: CONS | G23: 46356 | H23: A. Ferrer | I23: Lorelay Dextre | J23: PENDIENTE | L23: PENDIENTE | M23: NO APLICA | P23: NO APLICA | Q23: OK | V23: =IFERROR((COUNTIF(J23:S23,"OK")+COUNTIF(J23:S23,"EN PROCESO")*0.5)/(10-COUNTIF(J23:S23,"NO APLICA")-COUNTIF(J23:S23,"DESCARTADA")-COUNTIF(J23:S23,"-")-COUNTIF(J23:S23,"")),"") -> 0.33333333 | W23: =IF(ISNUMBER(V23),IF(V23>=0.9,"CONFORME",IF(V23>=0.5,"ALERTA","CRITICO")),IF(F23="CANCELADO","CANCELADO",IF(F23="STAND BY","STAND BY",IF(F23="DESCARTADO","DESCARTADO","S/D")))) -> CRITICO | X23: =10-COUNTIF(J23:S23,"NO APLICA")-COUNTIF(J23:S23,"-")-COUNTIF(J23:S23,"") -> 3 | Y23: =COUNTIF(J23:S23,"OK")+COUNTIF(J23:S23,"EN PROCESO")*0.5 -> 1
A24: 2026 | B24: 22986 | C24: EXPEDIENTE ITSE PRECOR CHILCA | D24: D | E24: CONS | F24: CIERRE | H24: M. Becerra | J24: NO APLICA | K24: PENDIENTE | L24: PENDIENTE | M24: NO APLICA | N24: NO APLICA | O24: NO APLICA | P24: NO APLICA | Q24: NO APLICA | R24: NO APLICA | V24: =IFERROR((COUNTIF(J24:S24,"OK")+COUNTIF(J24:S24,"EN PROCESO")*0.5)/(10-COUNTIF(J24:S24,"NO APLICA")-COUNTIF(J24:S24,"DESCARTADA")-COUNTIF(J24:S24,"-")-COUNTIF(J24:S24,"")),"") -> 0 | W24: =IF(ISNUMBER(V24),IF(V24>=0.9,"CONFORME",IF(V24>=0.5,"ALERTA","CRITICO")),IF(F24="CANCELADO","CANCELADO",IF(F24="STAND BY","STAND BY",IF(F24="DESCARTADO","DESCARTADO","S/D")))) -> CRITICO | X24: =10-COUNTIF(J24:S24,"NO APLICA")-COUNTIF(J24:S24,"-")-COUNTIF(J24:S24,"") -> 2 | Y24: =COUNTIF(J24:S24,"OK")+COUNTIF(J24:S24,"EN PROCESO")*0.5 -> 0
A25: 2026 | B25: 22985 | C25: LICITACIÓN UPN ICA | D25: D | E25: LIC | F25: LIC | G25: 46173 | H25: F. Choque | J25: NO APLICA | L25: PENDIENTE | M25: NO APLICA | N25: NO APLICA | O25: NO APLICA | P25: NO APLICA | Q25: NO APLICA | V25: =IFERROR((COUNTIF(J25:S25,"OK")+COUNTIF(J25:S25,"EN PROCESO")*0.5)/(10-COUNTIF(J25:S25,"NO APLICA")-COUNTIF(J25:S25,"DESCARTADA")-COUNTIF(J25:S25,"-")-COUNTIF(J25:S25,"")),"") -> 0 | W25: =IF(ISNUMBER(V25),IF(V25>=0.9,"CONFORME",IF(V25>=0.5,"ALERTA","CRITICO")),IF(F25="CANCELADO","CANCELADO",IF(F25="STAND BY","STAND BY",IF(F25="DESCARTADO","DESCARTADO","S/D")))) -> CRITICO | X25: =10-COUNTIF(J25:S25,"NO APLICA")-COUNTIF(J25:S25,"-")-COUNTIF(J25:S25,"") -> 1 | Y25: =COUNTIF(J25:S25,"OK")+COUNTIF(J25:S25,"EN PROCESO")*0.5 -> 0
A26: 2026 | B26: 22984 | C26: IISS TORRE INTERBANK | D26: D | E26: SUP | F26: CIERRE | H26: B. López | J26: NO APLICA | K26: PENDIENTE | L26: PENDIENTE | M26: NO APLICA | N26: NO APLICA | O26: NO APLICA | P26: OK | Q26: NO APLICA | R26: PENDIENTE | S26: NO APLICA | T26: Fecha de inicio 24-02 Se realizó la recepción provisional Informes no se enviaron de manera formal por correo. | U26: 46177 | V26: =IFERROR((COUNTIF(J26:S26,"OK")+COUNTIF(J26:S26,"EN PROCESO")*0.5)/(10-COUNTIF(J26:S26,"NO APLICA")-COUNTIF(J26:S26,"DESCARTADA")-COUNTIF(J26:S26,"-")-COUNTIF(J26:S26,"")),"") -> 0.25 | W26: =IF(ISNUMBER(V26),IF(V26>=0.9,"CONFORME",IF(V26>=0.5,"ALERTA","CRITICO")),IF(F26="CANCELADO","CANCELADO",IF(F26="STAND BY","STAND BY",IF(F26="DESCARTADO","DESCARTADO","S/D")))) -> CRITICO | X26: =10-COUNTIF(J26:S26,"NO APLICA")-COUNTIF(J26:S26,"-")-COUNTIF(J26:S26,"") -> 4 | Y26: =COUNTIF(J26:S26,"OK")+COUNTIF(J26:S26,"EN PROCESO")*0.5 -> 1
A27: 2026 | B27: 22983 | C27: HU LAS HIGUERAS- REDES DE IMPULSIÓN | D27: D | E27: SUP | F27: SUP | G27: 46174 | H27: B. López | I27: Andrés Fernández | J27: NO APLICA | L27: PENDIENTE | M27: NO APLICA | N27: NO APLICA | O27: NO APLICA | P27: OK | Q27: OK | V27: =IFERROR((COUNTIF(J27:S27,"OK")+COUNTIF(J27:S27,"EN PROCESO")*0.5)/(10-COUNTIF(J27:S27,"NO APLICA")-COUNTIF(J27:S27,"DESCARTADA")-COUNTIF(J27:S27,"-")-COUNTIF(J27:S27,"")),"") -> 0.66666667 | W27: =IF(ISNUMBER(V27),IF(V27>=0.9,"CONFORME",IF(V27>=0.5,"ALERTA","CRITICO")),IF(F27="CANCELADO","CANCELADO",IF(F27="STAND BY","STAND BY",IF(F27="DESCARTADO","DESCARTADO","S/D")))) -> ALERTA | X27: =10-COUNTIF(J27:S27,"NO APLICA")-COUNTIF(J27:S27,"-")-COUNTIF(J27:S27,"") -> 3 | Y27: =COUNTIF(J27:S27,"OK")+COUNTIF(J27:S27,"EN PROCESO")*0.5 -> 2
A28: 2026 | B28: 22982 | C28: PAVIMENTACIÓN ENRIQUE MEIGSS - PLANTA DUEÑAS | D28: D | E28: SUP | F28: CANCELADO | H28: B. López | J28: NO APLICA | K28: NO APLICA | L28: NO APLICA | M28: NO APLICA | N28: NO APLICA | O28: NO APLICA | P28: NO APLICA | Q28: NO APLICA | R28: NO APLICA | S28: NO APLICA | T28: Solo visitas. Proveedor externo Proyecto cancelado, no se inició servicio. | V28: =IFERROR((COUNTIF(J28:S28,"OK")+COUNTIF(J28:S28,"EN PROCESO")*0.5)/(10-COUNTIF(J28:S28,"NO APLICA")-COUNTIF(J28:S28,"DESCARTADA")-COUNTIF(J28:S28,"-")-COUNTIF(J28:S28,"")),"") | W28: =IF(ISNUMBER(V28),IF(V28>=0.9,"CONFORME",IF(V28>=0.5,"ALERTA","CRITICO")),IF(F28="CANCELADO","CANCELADO",IF(F28="STAND BY","STAND BY",IF(F28="DESCARTADO","DESCARTADO","S/D")))) -> CANCELADO | X28: =10-COUNTIF(J28:S28,"NO APLICA")-COUNTIF(J28:S28,"-")-COUNTIF(J28:S28,"") -> 0 | Y28: =COUNTIF(J28:S28,"OK")+COUNTIF(J28:S28,"EN PROCESO")*0.5 -> 0
A29: 2026 | B29: 22981 | C29: UTP TACNA | D29: D | E29: CONS | F29: CERRADO | H29: B. López | J29: NO APLICA | K29: NO APLICA | L29: PENDIENTE | M29: NO APLICA | N29: NO APLICA | O29: NO APLICA | P29: NO APLICA | Q29: NO APLICA | R29: NO APLICA | S29: NO APLICA | T29: Visita 01 día. | U29: 46177 | V29: =IFERROR((COUNTIF(J29:S29,"OK")+COUNTIF(J29:S29,"EN PROCESO")*0.5)/(10-COUNTIF(J29:S29,"NO APLICA")-COUNTIF(J29:S29,"DESCARTADA")-COUNTIF(J29:S29,"-")-COUNTIF(J29:S29,"")),"") -> 0 | W29: =IF(ISNUMBER(V29),IF(V29>=0.9,"CONFORME",IF(V29>=0.5,"ALERTA","CRITICO")),IF(F29="CANCELADO","CANCELADO",IF(F29="STAND BY","STAND BY",IF(F29="DESCARTADO","DESCARTADO","S/D")))) -> CRITICO | X29: =10-COUNTIF(J29:S29,"NO APLICA")-COUNTIF(J29:S29,"-")-COUNTIF(J29:S29,"") -> 1 | Y29: =COUNTIF(J29:S29,"OK")+COUNTIF(J29:S29,"EN PROCESO")*0.5 -> 0
A30: 2026 | B30: 22980 | C30: REFORZAMIENTO ESTRUCTURAL ALAMEDA PLAZA | D30: D | E30: ING | F30: CERRADO | H30: F. Choque | J30: NO APLICA | K30: OK | L30: PENDIENTE | M30: NO APLICA | N30: NO APLICA | O30: NO APLICA | P30: NO APLICA | Q30: NO APLICA | R30: PENDIENTE | S30: NO APLICA | T30: La ingeniería se desarolla con personal de casa Fecha fin aprox 15-03 | V30: =IFERROR((COUNTIF(J30:S30,"OK")+COUNTIF(J30:S30,"EN PROCESO")*0.5)/(10-COUNTIF(J30:S30,"NO APLICA")-COUNTIF(J30:S30,"DESCARTADA")-COUNTIF(J30:S30,"-")-COUNTIF(J30:S30,"")),"") -> 0.33333333 | W30: =IF(ISNUMBER(V30),IF(V30>=0.9,"CONFORME",IF(V30>=0.5,"ALERTA","CRITICO")),IF(F30="CANCELADO","CANCELADO",IF(F30="STAND BY","STAND BY",IF(F30="DESCARTADO","DESCARTADO","S/D")))) -> CRITICO | X30: =10-COUNTIF(J30:S30,"NO APLICA")-COUNTIF(J30:S30,"-")-COUNTIF(J30:S30,"") -> 3 | Y30: =COUNTIF(J30:S30,"OK")+COUNTIF(J30:S30,"EN PROCESO")*0.5 -> 1
A31: 2026 | B31: 22979 | C31: NUEVO PABELLÓN UMA SJL | D31: A | E31: RI, LIC, SUP | F31: RI | G31: 46538 | H31: B. López | J31: PENDIENTE | L31: PENDIENTE | M31: NO APLICA | S31: NO APLICA | T31: RI: evaluación de costos de las soluciones de ingeniería que propone la gerencia VITAL. | V31: =IFERROR((COUNTIF(J31:S31,"OK")+COUNTIF(J31:S31,"EN PROCESO")*0.5)/(10-COUNTIF(J31:S31,"NO APLICA")-COUNTIF(J31:S31,"DESCARTADA")-COUNTIF(J31:S31,"-")-COUNTIF(J31:S31,"")),"") -> 0 | W31: =IF(ISNUMBER(V31),IF(V31>=0.9,"CONFORME",IF(V31>=0.5,"ALERTA","CRITICO")),IF(F31="CANCELADO","CANCELADO",IF(F31="STAND BY","STAND BY",IF(F31="DESCARTADO","DESCARTADO","S/D")))) -> CRITICO | X31: =10-COUNTIF(J31:S31,"NO APLICA")-COUNTIF(J31:S31,"-")-COUNTIF(J31:S31,"") -> 2 | Y31: =COUNTIF(J31:S31,"OK")+COUNTIF(J31:S31,"EN PROCESO")*0.5 -> 0
A32: 2026 | B32: 22978 | C32: AGENCIA BCP TOTTUS PUENTE PIEDRA | D32: D | E32: SUP | F32: CERRADO | H32: F. Choque | I32: Edith Gutierrez | J32: NO APLICA | K32: PENDIENTE | L32: PENDIENTE | M32: NO APLICA | N32: NO APLICA | O32: NO APLICA | P32: OK | Q32: NO APLICA | R32: OK | S32: NO APLICA | V32: =IFERROR((COUNTIF(J32:S32,"OK")+COUNTIF(J32:S32,"EN PROCESO")*0.5)/(10-COUNTIF(J32:S32,"NO APLICA")-COUNTIF(J32:S32,"DESCARTADA")-COUNTIF(J32:S32,"-")-COUNTIF(J32:S32,"")),"") -> 0.5 | W32: =IF(ISNUMBER(V32),IF(V32>=0.9,"CONFORME",IF(V32>=0.5,"ALERTA","CRITICO")),IF(F32="CANCELADO","CANCELADO",IF(F32="STAND BY","STAND BY",IF(F32="DESCARTADO","DESCARTADO","S/D")))) -> ALERTA | X32: =10-COUNTIF(J32:S32,"NO APLICA")-COUNTIF(J32:S32,"-")-COUNTIF(J32:S32,"") -> 4 | Y32: =COUNTIF(J32:S32,"OK")+COUNTIF(J32:S32,"EN PROCESO")*0.5 -> 2
A33: 2025 | B33: 22977 | C33: ASCENSORES 15 SEDES INNOVA SCHOOL | D33: D | E33: ING | F33: CERRADO | H33: F. Choque | J33: NO APLICA | K33: OK | L33: PENDIENTE | M33: PENDIENTE | N33: PENDIENTE | O33: NO APLICA | P33: NO APLICA | Q33: NO APLICA | R33: OK | V33: =IFERROR((COUNTIF(J33:S33,"OK")+COUNTIF(J33:S33,"EN PROCESO")*0.5)/(10-COUNTIF(J33:S33,"NO APLICA")-COUNTIF(J33:S33,"DESCARTADA")-COUNTIF(J33:S33,"-")-COUNTIF(J33:S33,"")),"") -> 0.4 | W33: =IF(ISNUMBER(V33),IF(V33>=0.9,"CONFORME",IF(V33>=0.5,"ALERTA","CRITICO")),IF(F33="CANCELADO","CANCELADO",IF(F33="STAND BY","STAND BY",IF(F33="DESCARTADO","DESCARTADO","S/D")))) -> CRITICO | X33: =10-COUNTIF(J33:S33,"NO APLICA")-COUNTIF(J33:S33,"-")-COUNTIF(J33:S33,"") -> 5 | Y33: =COUNTIF(J33:S33,"OK")+COUNTIF(J33:S33,"EN PROCESO")*0.5 -> 2
A34: 2025 | B34: 22976 | C34: AMPLIACIÓN OFICINA FERREYROS TOQUEPALA CUAJONE | D34: C | E34: LIC, SUP | F34: CANCELADO | H34: F. Choque | J34: NO APLICA | K34: NO APLICA | L34: NO APLICA | M34: NO APLICA | N34: NO APLICA | O34: NO APLICA | P34: NO APLICA | Q34: NO APLICA | R34: NO APLICA | S34: NO APLICA | T34: Proyecto stand by | V34: =IFERROR((COUNTIF(J34:S34,"OK")+COUNTIF(J34:S34,"EN PROCESO")*0.5)/(10-COUNTIF(J34:S34,"NO APLICA")-COUNTIF(J34:S34,"DESCARTADA")-COUNTIF(J34:S34,"-")-COUNTIF(J34:S34,"")),"") | W34: =IF(ISNUMBER(V34),IF(V34>=0.9,"CONFORME",IF(V34>=0.5,"ALERTA","CRITICO")),IF(F34="CANCELADO","CANCELADO",IF(F34="STAND BY","STAND BY",IF(F34="DESCARTADO","DESCARTADO","S/D")))) -> CANCELADO | X34: =10-COUNTIF(J34:S34,"NO APLICA")-COUNTIF(J34:S34,"-")-COUNTIF(J34:S34,"") -> 0 | Y34: =COUNTIF(J34:S34,"OK")+COUNTIF(J34:S34,"EN PROCESO")*0.5 -> 0
A35: 2026 | B35: 22975 | C35: REVISIÓN EXPEDIENTES MIFARMA CENCO | D35: D | E35: RI | F35: RI | G35: 46203 | H35: M. Becerra | J35: NO APLICA | L35: PENDIENTE | O35: NO APLICA | P35: NO APLICA | Q35: NO APLICA | U35: 45978 | V35: =IFERROR((COUNTIF(J35:S35,"OK")+COUNTIF(J35:S35,"EN PROCESO")*0.5)/(10-COUNTIF(J35:S35,"NO APLICA")-COUNTIF(J35:S35,"DESCARTADA")-COUNTIF(J35:S35,"-")-COUNTIF(J35:S35,"")),"") -> 0 | W35: =IF(ISNUMBER(V35),IF(V35>=0.9,"CONFORME",IF(V35>=0.5,"ALERTA","CRITICO")),IF(F35="CANCELADO","CANCELADO",IF(F35="STAND BY","STAND BY",IF(F35="DESCARTADO","DESCARTADO","S/D")))) -> CRITICO | X35: =10-COUNTIF(J35:S35,"NO APLICA")-COUNTIF(J35:S35,"-")-COUNTIF(J35:S35,"") -> 1 | Y35: =COUNTIF(J35:S35,"OK")+COUNTIF(J35:S35,"EN PROCESO")*0.5 -> 0
A36: 2025 | B36: 22974 | C36: CAMBIO TECNOLOGÍA HVAC PAB. I UPC MONTERRICO | D36: D | E36: SUP | F36: CERRADO | H36: M. Becerra | J36: NO APLICA | K36: PENDIENTE | L36: PENDIENTE | M36: NO APLICA | N36: NO APLICA | O36: NO APLICA | P36: OK | Q36: NO APLICA | R36: OK | T36: Inicio obra 06-11-25 | U36: 45978 | V36: =IFERROR((COUNTIF(J36:S36,"OK")+COUNTIF(J36:S36,"EN PROCESO")*0.5)/(10-COUNTIF(J36:S36,"NO APLICA")-COUNTIF(J36:S36,"DESCARTADA")-COUNTIF(J36:S36,"-")-COUNTIF(J36:S36,"")),"") -> 0.5 | W36: =IF(ISNUMBER(V36),IF(V36>=0.9,"CONFORME",IF(V36>=0.5,"ALERTA","CRITICO")),IF(F36="CANCELADO","CANCELADO",IF(F36="STAND BY","STAND BY",IF(F36="DESCARTADO","DESCARTADO","S/D")))) -> ALERTA | X36: =10-COUNTIF(J36:S36,"NO APLICA")-COUNTIF(J36:S36,"-")-COUNTIF(J36:S36,"") -> 4 | Y36: =COUNTIF(J36:S36,"OK")+COUNTIF(J36:S36,"EN PROCESO")*0.5 -> 2
A37: 2026 | B37: 22973 | C37: OUTLET JOCKEY PLAZA LOTE H | D37: A | E37: GP, SUP | F37: SUP | G37: 46356 | H37: A. Ferrer | I37: Raúl Ávalos | J37: PENDIENTE | L37: PENDIENTE | M37: NO APLICA | P37: OK | Q37: OK | S37: NO APLICA | T37: GP: considera la revisión del expediente técnico y el soporte en el proceso de licitación, ambos ejecutados por el cliente. Servidor sin información Obra inicia en febrero 26 aprox. | V37: =IFERROR((COUNTIF(J37:S37,"OK")+COUNTIF(J37:S37,"EN PROCESO")*0.5)/(10-COUNTIF(J37:S37,"NO APLICA")-COUNTIF(J37:S37,"DESCARTADA")-COUNTIF(J37:S37,"-")-COUNTIF(J37:S37,"")),"") -> 0.5 | W37: =IF(ISNUMBER(V37),IF(V37>=0.9,"CONFORME",IF(V37>=0.5,"ALERTA","CRITICO")),IF(F37="CANCELADO","CANCELADO",IF(F37="STAND BY","STAND BY",IF(F37="DESCARTADO","DESCARTADO","S/D")))) -> ALERTA | X37: =10-COUNTIF(J37:S37,"NO APLICA")-COUNTIF(J37:S37,"-")-COUNTIF(J37:S37,"") -> 4 | Y37: =COUNTIF(J37:S37,"OK")+COUNTIF(J37:S37,"EN PROCESO")*0.5 -> 2
A38: 2026 | B38: 22972 | C38: PACKING ARÁNDANOS PISCO VANGUARD - INGENIERIA | D38: A | E38: ING | F38: ING | H38: M. Becerra | J38: PENDIENTE | L38: PENDIENTE | M38: PENDIENTE | P38: NO APLICA | Q38: PENDIENTE | T38: Supendido | U38: 45978 | V38: =IFERROR((COUNTIF(J38:S38,"OK")+COUNTIF(J38:S38,"EN PROCESO")*0.5)/(10-COUNTIF(J38:S38,"NO APLICA")-COUNTIF(J38:S38,"DESCARTADA")-COUNTIF(J38:S38,"-")-COUNTIF(J38:S38,"")),"") -> 0 | W38: =IF(ISNUMBER(V38),IF(V38>=0.9,"CONFORME",IF(V38>=0.5,"ALERTA","CRITICO")),IF(F38="CANCELADO","CANCELADO",IF(F38="STAND BY","STAND BY",IF(F38="DESCARTADO","DESCARTADO","S/D")))) -> CRITICO | X38: =10-COUNTIF(J38:S38,"NO APLICA")-COUNTIF(J38:S38,"-")-COUNTIF(J38:S38,"") -> 4 | Y38: =COUNTIF(J38:S38,"OK")+COUNTIF(J38:S38,"EN PROCESO")*0.5 -> 0
A39: 2025 | B39: 22971 | C39: RIEGO PACKING PISCO VANGUARD | D39: D | E39: SUP | F39: CERRADO | H39: P. Lavado | I39: Eloy Meza | J39: NO APLICA | K39: PENDIENTE | L39: PENDIENTE | M39: NO APLICA | N39: NO APLICA | O39: NO APLICA | P39: PENDIENTE | Q39: NO APLICA | R39: NO APLICA | V39: =IFERROR((COUNTIF(J39:S39,"OK")+COUNTIF(J39:S39,"EN PROCESO")*0.5)/(10-COUNTIF(J39:S39,"NO APLICA")-COUNTIF(J39:S39,"DESCARTADA")-COUNTIF(J39:S39,"-")-COUNTIF(J39:S39,"")),"") -> 0 | W39: =IF(ISNUMBER(V39),IF(V39>=0.9,"CONFORME",IF(V39>=0.5,"ALERTA","CRITICO")),IF(F39="CANCELADO","CANCELADO",IF(F39="STAND BY","STAND BY",IF(F39="DESCARTADO","DESCARTADO","S/D")))) -> CRITICO | X39: =10-COUNTIF(J39:S39,"NO APLICA")-COUNTIF(J39:S39,"-")-COUNTIF(J39:S39,"") -> 3 | Y39: =COUNTIF(J39:S39,"OK")+COUNTIF(J39:S39,"EN PROCESO")*0.5 -> 0
A40: 2025 | B40: 22970 | C40: AGENCIA BCP PEDRO RUIZ CHICLAYO | D40: D | E40: SUP | F40: CERRADO | H40: F. Choque | J40: NO APLICA | K40: PENDIENTE | L40: PENDIENTE | M40: NO APLICA | N40: NO APLICA | O40: NO APLICA | P40: OK | Q40: NO APLICA | R40: OK | S40: NO APLICA | U40: 45975 | V40: =IFERROR((COUNTIF(J40:S40,"OK")+COUNTIF(J40:S40,"EN PROCESO")*0.5)/(10-COUNTIF(J40:S40,"NO APLICA")-COUNTIF(J40:S40,"DESCARTADA")-COUNTIF(J40:S40,"-")-COUNTIF(J40:S40,"")),"") -> 0.5 | W40: =IF(ISNUMBER(V40),IF(V40>=0.9,"CONFORME",IF(V40>=0.5,"ALERTA","CRITICO")),IF(F40="CANCELADO","CANCELADO",IF(F40="STAND BY","STAND BY",IF(F40="DESCARTADO","DESCARTADO","S/D")))) -> ALERTA | X40: =10-COUNTIF(J40:S40,"NO APLICA")-COUNTIF(J40:S40,"-")-COUNTIF(J40:S40,"") -> 4 | Y40: =COUNTIF(J40:S40,"OK")+COUNTIF(J40:S40,"EN PROCESO")*0.5 -> 2
A41: 2026 | B41: 22969 | C41: INSPECCIÓN ESTRUCTURAL 06 COLEGIOS INNOVA | D41: D | E41: CONS | F41: CERRADO | H41: F. Choque | J41: NO APLICA | K41: OK | L41: PENDIENTE | M41: PENDIENTE | N41: PENDIENTE | O41: NO APLICA | P41: NO APLICA | Q41: NO APLICA | R41: OK | V41: =IFERROR((COUNTIF(J41:S41,"OK")+COUNTIF(J41:S41,"EN PROCESO")*0.5)/(10-COUNTIF(J41:S41,"NO APLICA")-COUNTIF(J41:S41,"DESCARTADA")-COUNTIF(J41:S41,"-")-COUNTIF(J41:S41,"")),"") -> 0.4 | W41: =IF(ISNUMBER(V41),IF(V41>=0.9,"CONFORME",IF(V41>=0.5,"ALERTA","CRITICO")),IF(F41="CANCELADO","CANCELADO",IF(F41="STAND BY","STAND BY",IF(F41="DESCARTADO","DESCARTADO","S/D")))) -> CRITICO | X41: =10-COUNTIF(J41:S41,"NO APLICA")-COUNTIF(J41:S41,"-")-COUNTIF(J41:S41,"") -> 5 | Y41: =COUNTIF(J41:S41,"OK")+COUNTIF(J41:S41,"EN PROCESO")*0.5 -> 2
A42: 2026 | B42: 22968 | C42: TIENDAS MASS 2025-2027 | D42: D | E42: ING, SUP | F42: SUP | G42: 46408 | H42: A. Ferrer | I42: César Menez | J42: NO APLICA | L42: PENDIENTE | M42: NO APLICA | N42: PENDIENTE | O42: NO APLICA | P42: OK | Q42: NO APLICA | S42: PENDIENTE | V42: =IFERROR((COUNTIF(J42:S42,"OK")+COUNTIF(J42:S42,"EN PROCESO")*0.5)/(10-COUNTIF(J42:S42,"NO APLICA")-COUNTIF(J42:S42,"DESCARTADA")-COUNTIF(J42:S42,"-")-COUNTIF(J42:S42,"")),"") -> 0.25 | W42: =IF(ISNUMBER(V42),IF(V42>=0.9,"CONFORME",IF(V42>=0.5,"ALERTA","CRITICO")),IF(F42="CANCELADO","CANCELADO",IF(F42="STAND BY","STAND BY",IF(F42="DESCARTADO","DESCARTADO","S/D")))) -> CRITICO | X42: =10-COUNTIF(J42:S42,"NO APLICA")-COUNTIF(J42:S42,"-")-COUNTIF(J42:S42,"") -> 4 | Y42: =COUNTIF(J42:S42,"OK")+COUNTIF(J42:S42,"EN PROCESO")*0.5 -> 1
A43: 2025 | B43: 22967 | C43: IMPLEMENTACIÓN DESIGUAL JOCKEY PLAZA | D43: D | E43: SUP | F43: CERRADO | H43: F. Choque | J43: NO APLICA | K43: PENDIENTE | L43: PENDIENTE | M43: NO APLICA | N43: NO APLICA | O43: NO APLICA | P43: PENDIENTE | Q43: NO APLICA | R43: OK | S43: NO APLICA | T43: Surge como un adicional del proyecto 22948 (desde el 08-09-25) | U43: 45975 | V43: =IFERROR((COUNTIF(J43:S43,"OK")+COUNTIF(J43:S43,"EN PROCESO")*0.5)/(10-COUNTIF(J43:S43,"NO APLICA")-COUNTIF(J43:S43,"DESCARTADA")-COUNTIF(J43:S43,"-")-COUNTIF(J43:S43,"")),"") -> 0.25 | W43: =IF(ISNUMBER(V43),IF(V43>=0.9,"CONFORME",IF(V43>=0.5,"ALERTA","CRITICO")),IF(F43="CANCELADO","CANCELADO",IF(F43="STAND BY","STAND BY",IF(F43="DESCARTADO","DESCARTADO","S/D")))) -> CRITICO | X43: =10-COUNTIF(J43:S43,"NO APLICA")-COUNTIF(J43:S43,"-")-COUNTIF(J43:S43,"") -> 4 | Y43: =COUNTIF(J43:S43,"OK")+COUNTIF(J43:S43,"EN PROCESO")*0.5 -> 1
A44: 2025 | B44: 22966 | C44: RENOVACIÓN 53 LETREROS IBK | D44: D | E44: SUP | F44: SUP | G44: 46239 | H44: B. López | J44: NO APLICA | L44: PENDIENTE | M44: NO APLICA | N44: NO APLICA | O44: NO APLICA | P44: PENDIENTE | Q44: NO APLICA | S44: NO APLICA | T44: Inicio 26-12-25 Son aprox. 100 tiendas, se van liberando por paquetes. Los reportes se codifican por cada sede | U44: 45980 | V44: =IFERROR((COUNTIF(J44:S44,"OK")+COUNTIF(J44:S44,"EN PROCESO")*0.5)/(10-COUNTIF(J44:S44,"NO APLICA")-COUNTIF(J44:S44,"DESCARTADA")-COUNTIF(J44:S44,"-")-COUNTIF(J44:S44,"")),"") -> 0 | W44: =IF(ISNUMBER(V44),IF(V44>=0.9,"CONFORME",IF(V44>=0.5,"ALERTA","CRITICO")),IF(F44="CANCELADO","CANCELADO",IF(F44="STAND BY","STAND BY",IF(F44="DESCARTADO","DESCARTADO","S/D")))) -> CRITICO | X44: =10-COUNTIF(J44:S44,"NO APLICA")-COUNTIF(J44:S44,"-")-COUNTIF(J44:S44,"") -> 2 | Y44: =COUNTIF(J44:S44,"OK")+COUNTIF(J44:S44,"EN PROCESO")*0.5 -> 0
A45: 2026 | B45: 22965 | C45: AMPLIACIÓN PABELLÓN D UPC SAN MIGUEL | D45: B | E45: SUP | F45: CERRADO | H45: B. López | I45: Samuel Castillo | J45: PENDIENTE | K45: PENDIENTE | L45: PENDIENTE | M45: NO APLICA | N45: PENDIENTE | O45: PENDIENTE | P45: PENDIENTE | Q45: PENDIENTE | R45: OK | T45: Fin del servicio 25-04 | U45: 45980 | V45: =IFERROR((COUNTIF(J45:S45,"OK")+COUNTIF(J45:S45,"EN PROCESO")*0.5)/(10-COUNTIF(J45:S45,"NO APLICA")-COUNTIF(J45:S45,"DESCARTADA")-COUNTIF(J45:S45,"-")-COUNTIF(J45:S45,"")),"") -> 0.125 | W45: =IF(ISNUMBER(V45),IF(V45>=0.9,"CONFORME",IF(V45>=0.5,"ALERTA","CRITICO")),IF(F45="CANCELADO","CANCELADO",IF(F45="STAND BY","STAND BY",IF(F45="DESCARTADO","DESCARTADO","S/D")))) -> CRITICO | X45: =10-COUNTIF(J45:S45,"NO APLICA")-COUNTIF(J45:S45,"-")-COUNTIF(J45:S45,"") -> 8 | Y45: =COUNTIF(J45:S45,"OK")+COUNTIF(J45:S45,"EN PROCESO")*0.5 -> 1
A46: 2025 | B46: 22964 | C46: AGENCIA BCP HUANCAYO | D46: D | E46: SUP | F46: CERRADO | H46: F. Choque | I46: Nataly Muñante | J46: NO APLICA | K46: PENDIENTE | L46: PENDIENTE | M46: NO APLICA | N46: NO APLICA | O46: NO APLICA | P46: OK | Q46: NO APLICA | R46: OK | V46: =IFERROR((COUNTIF(J46:S46,"OK")+COUNTIF(J46:S46,"EN PROCESO")*0.5)/(10-COUNTIF(J46:S46,"NO APLICA")-COUNTIF(J46:S46,"DESCARTADA")-COUNTIF(J46:S46,"-")-COUNTIF(J46:S46,"")),"") -> 0.5 | W46: =IF(ISNUMBER(V46),IF(V46>=0.9,"CONFORME",IF(V46>=0.5,"ALERTA","CRITICO")),IF(F46="CANCELADO","CANCELADO",IF(F46="STAND BY","STAND BY",IF(F46="DESCARTADO","DESCARTADO","S/D")))) -> ALERTA | X46: =10-COUNTIF(J46:S46,"NO APLICA")-COUNTIF(J46:S46,"-")-COUNTIF(J46:S46,"") -> 4 | Y46: =COUNTIF(J46:S46,"OK")+COUNTIF(J46:S46,"EN PROCESO")*0.5 -> 2
A47: 2025 | B47: 22963 | C47: METRO HACIENDA SJL | D47: D | E47: SUP | F47: CERRADO | H47: P. Lavado | J47: NO APLICA | K47: PENDIENTE | L47: PENDIENTE | M47: NO APLICA | N47: NO APLICA | O47: NO APLICA | P47: PENDIENTE | Q47: NO APLICA | R47: DESCARTADA | T47: Duración 1 mes. | U47: 45980 | V47: =IFERROR((COUNTIF(J47:S47,"OK")+COUNTIF(J47:S47,"EN PROCESO")*0.5)/(10-COUNTIF(J47:S47,"NO APLICA")-COUNTIF(J47:S47,"DESCARTADA")-COUNTIF(J47:S47,"-")-COUNTIF(J47:S47,"")),"") -> 0 | W47: =IF(ISNUMBER(V47),IF(V47>=0.9,"CONFORME",IF(V47>=0.5,"ALERTA","CRITICO")),IF(F47="CANCELADO","CANCELADO",IF(F47="STAND BY","STAND BY",IF(F47="DESCARTADO","DESCARTADO","S/D")))) -> CRITICO | X47: =10-COUNTIF(J47:S47,"NO APLICA")-COUNTIF(J47:S47,"-")-COUNTIF(J47:S47,"") -> 4 | Y47: =COUNTIF(J47:S47,"OK")+COUNTIF(J47:S47,"EN PROCESO")*0.5 -> 0
A48: 2025 | B48: 22962 | C48: TF PLAZA SAN MIGUEL IBK | D48: D | E48: LIC, SUP | F48: CERRADO | H48: B. López | I48: Samuel Castillo | J48: NO APLICA | K48: OK | L48: PENDIENTE | M48: NO APLICA | N48: NO APLICA | O48: NO APLICA | P48: OK | Q48: OK | R48: OK | S48: NO APLICA | T48: Servidor sin información Obra concluye a fines de nov25 | U48: 45980 | V48: =IFERROR((COUNTIF(J48:S48,"OK")+COUNTIF(J48:S48,"EN PROCESO")*0.5)/(10-COUNTIF(J48:S48,"NO APLICA")-COUNTIF(J48:S48,"DESCARTADA")-COUNTIF(J48:S48,"-")-COUNTIF(J48:S48,"")),"") -> 0.8 | W48: =IF(ISNUMBER(V48),IF(V48>=0.9,"CONFORME",IF(V48>=0.5,"ALERTA","CRITICO")),IF(F48="CANCELADO","CANCELADO",IF(F48="STAND BY","STAND BY",IF(F48="DESCARTADO","DESCARTADO","S/D")))) -> ALERTA | X48: =10-COUNTIF(J48:S48,"NO APLICA")-COUNTIF(J48:S48,"-")-COUNTIF(J48:S48,"") -> 5 | Y48: =COUNTIF(J48:S48,"OK")+COUNTIF(J48:S48,"EN PROCESO")*0.5 -> 4
A49: 2025 | B49: 22961-03 | C49: REFORZAMIENTO BARANDAS PIURA | D49: D | E49: SUP | F49: CERRADO | H49: F. Choque | J49: NO APLICA | K49: OK | L49: PENDIENTE | M49: NO APLICA | N49: NO APLICA | O49: NO APLICA | P49: OK | Q49: NO APLICA | R49: - | S49: NO APLICA | T49: ACS: formato cliente | U49: 45975 | V49: =IFERROR((COUNTIF(J49:S49,"OK")+COUNTIF(J49:S49,"EN PROCESO")*0.5)/(10-COUNTIF(J49:S49,"NO APLICA")-COUNTIF(J49:S49,"DESCARTADA")-COUNTIF(J49:S49,"-")-COUNTIF(J49:S49,"")),"") -> 0.66666667 | W49: =IF(ISNUMBER(V49),IF(V49>=0.9,"CONFORME",IF(V49>=0.5,"ALERTA","CRITICO")),IF(F49="CANCELADO","CANCELADO",IF(F49="STAND BY","STAND BY",IF(F49="DESCARTADO","DESCARTADO","S/D")))) -> ALERTA | X49: =10-COUNTIF(J49:S49,"NO APLICA")-COUNTIF(J49:S49,"-")-COUNTIF(J49:S49,"") -> 3 | Y49: =COUNTIF(J49:S49,"OK")+COUNTIF(J49:S49,"EN PROCESO")*0.5 -> 2
A50: 2025 | B50: 22961-02 | C50: REFORZAMIENTO BARANDAS CHICLAYO | D50: D | E50: SUP | F50: CERRADO | H50: F. Choque | J50: NO APLICA | K50: OK | L50: PENDIENTE | M50: NO APLICA | N50: NO APLICA | O50: NO APLICA | P50: OK | Q50: NO APLICA | R50: - | S50: NO APLICA | T50: ACS: formato cliente | U50: 45975 | V50: =IFERROR((COUNTIF(J50:S50,"OK")+COUNTIF(J50:S50,"EN PROCESO")*0.5)/(10-COUNTIF(J50:S50,"NO APLICA")-COUNTIF(J50:S50,"DESCARTADA")-COUNTIF(J50:S50,"-")-COUNTIF(J50:S50,"")),"") -> 0.66666667 | W50: =IF(ISNUMBER(V50),IF(V50>=0.9,"CONFORME",IF(V50>=0.5,"ALERTA","CRITICO")),IF(F50="CANCELADO","CANCELADO",IF(F50="STAND BY","STAND BY",IF(F50="DESCARTADO","DESCARTADO","S/D")))) -> ALERTA | X50: =10-COUNTIF(J50:S50,"NO APLICA")-COUNTIF(J50:S50,"-")-COUNTIF(J50:S50,"") -> 3 | Y50: =COUNTIF(J50:S50,"OK")+COUNTIF(J50:S50,"EN PROCESO")*0.5 -> 2
A51: 2025 | B51: 22961-01 | C51: REFORZAMIENTO BARANDAS TRUJILLO | D51: D | E51: SUP | F51: CERRADO | H51: F. Choque | J51: NO APLICA | K51: OK | L51: PENDIENTE | M51: NO APLICA | N51: NO APLICA | O51: NO APLICA | P51: OK | Q51: NO APLICA | R51: OK | S51: NO APLICA | T51: ACS: formato cliente | U51: 45975 | V51: =IFERROR((COUNTIF(J51:S51,"OK")+COUNTIF(J51:S51,"EN PROCESO")*0.5)/(10-COUNTIF(J51:S51,"NO APLICA")-COUNTIF(J51:S51,"DESCARTADA")-COUNTIF(J51:S51,"-")-COUNTIF(J51:S51,"")),"") -> 0.75 | W51: =IF(ISNUMBER(V51),IF(V51>=0.9,"CONFORME",IF(V51>=0.5,"ALERTA","CRITICO")),IF(F51="CANCELADO","CANCELADO",IF(F51="STAND BY","STAND BY",IF(F51="DESCARTADO","DESCARTADO","S/D")))) -> ALERTA | X51: =10-COUNTIF(J51:S51,"NO APLICA")-COUNTIF(J51:S51,"-")-COUNTIF(J51:S51,"") -> 4 | Y51: =COUNTIF(J51:S51,"OK")+COUNTIF(J51:S51,"EN PROCESO")*0.5 -> 3
A52: 2025 | B52: 22960 | C52: DIAGNÓSTICO ESTRUCTURAS 05 LOCALES CENCOSUD – INGENIERÍA | D52: D | E52: CONS | F52: CERRADO | H52: P. Lavado | I52: Victor Ramírez | J52: NO APLICA | K52: PENDIENTE | L52: PENDIENTE | M52: NO APLICA | N52: PENDIENTE | O52: NO APLICA | P52: PENDIENTE | Q52: NO APLICA | R52: OK | T52: CCP: No aplica. El cliente seleccionó a los proveedores, esto fue comunicado desde la etapa comercial. | V52: =IFERROR((COUNTIF(J52:S52,"OK")+COUNTIF(J52:S52,"EN PROCESO")*0.5)/(10-COUNTIF(J52:S52,"NO APLICA")-COUNTIF(J52:S52,"DESCARTADA")-COUNTIF(J52:S52,"-")-COUNTIF(J52:S52,"")),"") -> 0.2 | W52: =IF(ISNUMBER(V52),IF(V52>=0.9,"CONFORME",IF(V52>=0.5,"ALERTA","CRITICO")),IF(F52="CANCELADO","CANCELADO",IF(F52="STAND BY","STAND BY",IF(F52="DESCARTADO","DESCARTADO","S/D")))) -> CRITICO | X52: =10-COUNTIF(J52:S52,"NO APLICA")-COUNTIF(J52:S52,"-")-COUNTIF(J52:S52,"") -> 5 | Y52: =COUNTIF(J52:S52,"OK")+COUNTIF(J52:S52,"EN PROCESO")*0.5 -> 1
A53: 2025 | B53: 22959 | C53: DIAGNÓSTICO ESTRUCTURAS 08 LOCALES CENCOSUD - INGENIERÍA | D53: D | E53: CONS | F53: CERRADO | H53: P. Lavado | I53: Victor Ramírez | J53: NO APLICA | K53: PENDIENTE | L53: PENDIENTE | M53: NO APLICA | N53: PENDIENTE | O53: NO APLICA | P53: PENDIENTE | Q53: NO APLICA | R53: OK | T53: CCP: No aplica. El cliente seleccionó a los proveedores, esto fue comunicado desde la etapa comercial. | V53: =IFERROR((COUNTIF(J53:S53,"OK")+COUNTIF(J53:S53,"EN PROCESO")*0.5)/(10-COUNTIF(J53:S53,"NO APLICA")-COUNTIF(J53:S53,"DESCARTADA")-COUNTIF(J53:S53,"-")-COUNTIF(J53:S53,"")),"") -> 0.2 | W53: =IF(ISNUMBER(V53),IF(V53>=0.9,"CONFORME",IF(V53>=0.5,"ALERTA","CRITICO")),IF(F53="CANCELADO","CANCELADO",IF(F53="STAND BY","STAND BY",IF(F53="DESCARTADO","DESCARTADO","S/D")))) -> CRITICO | X53: =10-COUNTIF(J53:S53,"NO APLICA")-COUNTIF(J53:S53,"-")-COUNTIF(J53:S53,"") -> 5 | Y53: =COUNTIF(J53:S53,"OK")+COUNTIF(J53:S53,"EN PROCESO")*0.5 -> 1
A54: 2026 | B54: 22958 | C54: AMPLIACIÓN PAB. F UPN CAJAMARCA | D54: B | E54: LIC, SUP | F54: CIERRE | H54: F. Choque | J54: PENDIENTE | K54: PENDIENTE | L54: PENDIENTE | M54: NO APLICA | N54: NO APLICA | O54: PENDIENTE | P54: OK | Q54: OK | R54: PENDIENTE | T54: Inicio de obra estimado dic25 Juan Lara concluyó licitación. | V54: =IFERROR((COUNTIF(J54:S54,"OK")+COUNTIF(J54:S54,"EN PROCESO")*0.5)/(10-COUNTIF(J54:S54,"NO APLICA")-COUNTIF(J54:S54,"DESCARTADA")-COUNTIF(J54:S54,"-")-COUNTIF(J54:S54,"")),"") -> 0.28571429 | W54: =IF(ISNUMBER(V54),IF(V54>=0.9,"CONFORME",IF(V54>=0.5,"ALERTA","CRITICO")),IF(F54="CANCELADO","CANCELADO",IF(F54="STAND BY","STAND BY",IF(F54="DESCARTADO","DESCARTADO","S/D")))) -> CRITICO | X54: =10-COUNTIF(J54:S54,"NO APLICA")-COUNTIF(J54:S54,"-")-COUNTIF(J54:S54,"") -> 7 | Y54: =COUNTIF(J54:S54,"OK")+COUNTIF(J54:S54,"EN PROCESO")*0.5 -> 2
A55: 2025 | B55: 22957 | C55: CAMBIO ALIMENTADORES RP CHICLAYO - 2da ETAPA | D55: D | E55: SUP | F55: CERRADO | H55: M. Becerra | I55: Nicolas Espinoza | J55: NO APLICA | K55: OK | L55: PENDIENTE | M55: NO APLICA | N55: NO APLICA | O55: NO APLICA | P55: OK | Q55: OK | R55: OK | T55: Inició obra 01-08, fin 20-11 | U55: 45978 | V55: =IFERROR((COUNTIF(J55:S55,"OK")+COUNTIF(J55:S55,"EN PROCESO")*0.5)/(10-COUNTIF(J55:S55,"NO APLICA")-COUNTIF(J55:S55,"DESCARTADA")-COUNTIF(J55:S55,"-")-COUNTIF(J55:S55,"")),"") -> 0.8 | W55: =IF(ISNUMBER(V55),IF(V55>=0.9,"CONFORME",IF(V55>=0.5,"ALERTA","CRITICO")),IF(F55="CANCELADO","CANCELADO",IF(F55="STAND BY","STAND BY",IF(F55="DESCARTADO","DESCARTADO","S/D")))) -> ALERTA | X55: =10-COUNTIF(J55:S55,"NO APLICA")-COUNTIF(J55:S55,"-")-COUNTIF(J55:S55,"") -> 5 | Y55: =COUNTIF(J55:S55,"OK")+COUNTIF(J55:S55,"EN PROCESO")*0.5 -> 4
A56: 2025 | B56: 22956 | C56: IISS MONTEMAR 3 CENTENARIO | D56: D | E56: SUP | F56: CERRADO | H56: B. López | I56: Supervisor externo | J56: NO APLICA | K56: NO APLICA | L56: PENDIENTE | M56: NO APLICA | N56: NO APLICA | O56: NO APLICA | P56: OK | Q56: NO APLICA | R56: OK | S56: NO APLICA | T56: Solo supervisión IISS, solo visitas. | U56: 46177 | V56: =IFERROR((COUNTIF(J56:S56,"OK")+COUNTIF(J56:S56,"EN PROCESO")*0.5)/(10-COUNTIF(J56:S56,"NO APLICA")-COUNTIF(J56:S56,"DESCARTADA")-COUNTIF(J56:S56,"-")-COUNTIF(J56:S56,"")),"") -> 0.66666667 | W56: =IF(ISNUMBER(V56),IF(V56>=0.9,"CONFORME",IF(V56>=0.5,"ALERTA","CRITICO")),IF(F56="CANCELADO","CANCELADO",IF(F56="STAND BY","STAND BY",IF(F56="DESCARTADO","DESCARTADO","S/D")))) -> ALERTA | X56: =10-COUNTIF(J56:S56,"NO APLICA")-COUNTIF(J56:S56,"-")-COUNTIF(J56:S56,"") -> 3 | Y56: =COUNTIF(J56:S56,"OK")+COUNTIF(J56:S56,"EN PROCESO")*0.5 -> 2
A57: 2026 | B57: 22955 | C57: PACKING PISCO VANGUARD PERÚ | D57: A | E57: SUP | F57: SUP | G57: 46177 | H57: P. Lavado | I57: César Adrianzen | J57: PENDIENTE | L57: PENDIENTE | M57: NO APLICA | N57: NO APLICA | O57: PENDIENTE | P57: OK | Q57: OK | S57: NO APLICA | V57: =IFERROR((COUNTIF(J57:S57,"OK")+COUNTIF(J57:S57,"EN PROCESO")*0.5)/(10-COUNTIF(J57:S57,"NO APLICA")-COUNTIF(J57:S57,"DESCARTADA")-COUNTIF(J57:S57,"-")-COUNTIF(J57:S57,"")),"") -> 0.4 | W57: =IF(ISNUMBER(V57),IF(V57>=0.9,"CONFORME",IF(V57>=0.5,"ALERTA","CRITICO")),IF(F57="CANCELADO","CANCELADO",IF(F57="STAND BY","STAND BY",IF(F57="DESCARTADO","DESCARTADO","S/D")))) -> CRITICO | X57: =10-COUNTIF(J57:S57,"NO APLICA")-COUNTIF(J57:S57,"-")-COUNTIF(J57:S57,"") -> 5 | Y57: =COUNTIF(J57:S57,"OK")+COUNTIF(J57:S57,"EN PROCESO")*0.5 -> 2
A58: 2026 | B58: 22954 | C58: OFICINAS CENCOSUD MIRAFLORES | D58: A | E58: SUP | F58: SUP | G58: 46188 | H58: B. López | I58: Michael Gómez | J58: PENDIENTE | L58: PENDIENTE | M58: NO APLICA | P58: OK | Q58: OK | S58: NO APLICA | T58: Inicio obra 11-08 Obra concluye a fines de abr26 | U58: 45980 | V58: =IFERROR((COUNTIF(J58:S58,"OK")+COUNTIF(J58:S58,"EN PROCESO")*0.5)/(10-COUNTIF(J58:S58,"NO APLICA")-COUNTIF(J58:S58,"DESCARTADA")-COUNTIF(J58:S58,"-")-COUNTIF(J58:S58,"")),"") -> 0.5 | W58: =IF(ISNUMBER(V58),IF(V58>=0.9,"CONFORME",IF(V58>=0.5,"ALERTA","CRITICO")),IF(F58="CANCELADO","CANCELADO",IF(F58="STAND BY","STAND BY",IF(F58="DESCARTADO","DESCARTADO","S/D")))) -> ALERTA | X58: =10-COUNTIF(J58:S58,"NO APLICA")-COUNTIF(J58:S58,"-")-COUNTIF(J58:S58,"") -> 4 | Y58: =COUNTIF(J58:S58,"OK")+COUNTIF(J58:S58,"EN PROCESO")*0.5 -> 2
A59: 2025 | B59: 22953 | C59: CAJA AREQUIPA VILLA MARÍA DEL TRIUNFO | D59: D | E59: RI, SUP | F59: CERRADO | H59: F. Choque | I59: Daniel Guevara | J59: NO APLICA | K59: PENDIENTE | L59: PENDIENTE | M59: NO APLICA | N59: NO APLICA | O59: NO APLICA | P59: OK | Q59: NO APLICA | R59: OK | S59: NO APLICA | T59: Inicio obra 31-07 | V59: =IFERROR((COUNTIF(J59:S59,"OK")+COUNTIF(J59:S59,"EN PROCESO")*0.5)/(10-COUNTIF(J59:S59,"NO APLICA")-COUNTIF(J59:S59,"DESCARTADA")-COUNTIF(J59:S59,"-")-COUNTIF(J59:S59,"")),"") -> 0.5 | W59: =IF(ISNUMBER(V59),IF(V59>=0.9,"CONFORME",IF(V59>=0.5,"ALERTA","CRITICO")),IF(F59="CANCELADO","CANCELADO",IF(F59="STAND BY","STAND BY",IF(F59="DESCARTADO","DESCARTADO","S/D")))) -> ALERTA | X59: =10-COUNTIF(J59:S59,"NO APLICA")-COUNTIF(J59:S59,"-")-COUNTIF(J59:S59,"") -> 4 | Y59: =COUNTIF(J59:S59,"OK")+COUNTIF(J59:S59,"EN PROCESO")*0.5 -> 2
A60: 2026 | B60: 22952 | C60: REVISIÓN EXPEDIENTES LOCATARIOS CENCOSUD | D60: D | E60: RI | F60: RI | H60: M. Becerra | J60: NO APLICA | L60: PENDIENTE | M60: NO APLICA | N60: NO APLICA | O60: NO APLICA | P60: NO APLICA | Q60: NO APLICA | S60: NO APLICA | T60: Suspendido | U60: 45978 | V60: =IFERROR((COUNTIF(J60:S60,"OK")+COUNTIF(J60:S60,"EN PROCESO")*0.5)/(10-COUNTIF(J60:S60,"NO APLICA")-COUNTIF(J60:S60,"DESCARTADA")-COUNTIF(J60:S60,"-")-COUNTIF(J60:S60,"")),"") -> 0 | W60: =IF(ISNUMBER(V60),IF(V60>=0.9,"CONFORME",IF(V60>=0.5,"ALERTA","CRITICO")),IF(F60="CANCELADO","CANCELADO",IF(F60="STAND BY","STAND BY",IF(F60="DESCARTADO","DESCARTADO","S/D")))) -> CRITICO | X60: =10-COUNTIF(J60:S60,"NO APLICA")-COUNTIF(J60:S60,"-")-COUNTIF(J60:S60,"") -> 1 | Y60: =COUNTIF(J60:S60,"OK")+COUNTIF(J60:S60,"EN PROCESO")*0.5 -> 0
A61: 2025 | B61: 22951 | C61: REMODELACIÓN MALL PLAZA HUANCAYO | D61: C | E61: SUP | F61: CERRADO | H61: B. López | I61: Luis Castañeda | J61: PENDIENTE | K61: PENDIENTE | L61: PENDIENTE | M61: NO APLICA | N61: PENDIENTE | O61: PENDIENTE | P61: PENDIENTE | Q61: PENDIENTE | R61: OK | T61: Inicio obra 25-08 ACS: Pendiente la última OC | U61: 45980 | V61: =IFERROR((COUNTIF(J61:S61,"OK")+COUNTIF(J61:S61,"EN PROCESO")*0.5)/(10-COUNTIF(J61:S61,"NO APLICA")-COUNTIF(J61:S61,"DESCARTADA")-COUNTIF(J61:S61,"-")-COUNTIF(J61:S61,"")),"") -> 0.125 | W61: =IF(ISNUMBER(V61),IF(V61>=0.9,"CONFORME",IF(V61>=0.5,"ALERTA","CRITICO")),IF(F61="CANCELADO","CANCELADO",IF(F61="STAND BY","STAND BY",IF(F61="DESCARTADO","DESCARTADO","S/D")))) -> CRITICO | X61: =10-COUNTIF(J61:S61,"NO APLICA")-COUNTIF(J61:S61,"-")-COUNTIF(J61:S61,"") -> 8 | Y61: =COUNTIF(J61:S61,"OK")+COUNTIF(J61:S61,"EN PROCESO")*0.5 -> 1
A62: 2025 | B62: 22950 | C62: REVISIÓN EXPEDIENTE IE DIVINO MAESTRO OXI BCP CAÑETE | D62: D | E62: RI | F62: CERRADO | H62: F. Choque | J62: NO APLICA | K62: PENDIENTE | L62: PENDIENTE | M62: NO APLICA | N62: NO APLICA | O62: NO APLICA | P62: NO APLICA | Q62: NO APLICA | R62: OK | S62: NO APLICA | V62: =IFERROR((COUNTIF(J62:S62,"OK")+COUNTIF(J62:S62,"EN PROCESO")*0.5)/(10-COUNTIF(J62:S62,"NO APLICA")-COUNTIF(J62:S62,"DESCARTADA")-COUNTIF(J62:S62,"-")-COUNTIF(J62:S62,"")),"") -> 0.33333333 | W62: =IF(ISNUMBER(V62),IF(V62>=0.9,"CONFORME",IF(V62>=0.5,"ALERTA","CRITICO")),IF(F62="CANCELADO","CANCELADO",IF(F62="STAND BY","STAND BY",IF(F62="DESCARTADO","DESCARTADO","S/D")))) -> CRITICO | X62: =10-COUNTIF(J62:S62,"NO APLICA")-COUNTIF(J62:S62,"-")-COUNTIF(J62:S62,"") -> 3 | Y62: =COUNTIF(J62:S62,"OK")+COUNTIF(J62:S62,"EN PROCESO")*0.5 -> 1
A63: 2026 | B63: 22949 | C63: REFORZAMIENTO BARANDAS UTP AREQUIPA | D63: D | E63: SUP | F63: CERRADO | H63: B. López | J63: NO APLICA | K63: OK | L63: PENDIENTE | M63: NO APLICA | N63: NO APLICA | O63: NO APLICA | P63: OK | Q63: NO APLICA | R63: OK | S63: NO APLICA | T63: Supervisión nocturna. | U63: 46177 | V63: =IFERROR((COUNTIF(J63:S63,"OK")+COUNTIF(J63:S63,"EN PROCESO")*0.5)/(10-COUNTIF(J63:S63,"NO APLICA")-COUNTIF(J63:S63,"DESCARTADA")-COUNTIF(J63:S63,"-")-COUNTIF(J63:S63,"")),"") -> 0.75 | W63: =IF(ISNUMBER(V63),IF(V63>=0.9,"CONFORME",IF(V63>=0.5,"ALERTA","CRITICO")),IF(F63="CANCELADO","CANCELADO",IF(F63="STAND BY","STAND BY",IF(F63="DESCARTADO","DESCARTADO","S/D")))) -> ALERTA | X63: =10-COUNTIF(J63:S63,"NO APLICA")-COUNTIF(J63:S63,"-")-COUNTIF(J63:S63,"") -> 4 | Y63: =COUNTIF(J63:S63,"OK")+COUNTIF(J63:S63,"EN PROCESO")*0.5 -> 3
A64: 2025 | B64: 22948 | C64: REFORZAMIENTO TIENDA D&G JP | D64: D | E64: SUP | F64: CERRADO | H64: F. Choque | I64: Juan Tupayachi | J64: NO APLICA | K64: OK | L64: PENDIENTE | M64: NO APLICA | N64: NO APLICA | O64: NO APLICA | P64: OK | Q64: NO APLICA | R64: OK | S64: NO APLICA | T64: Supervisión nocturna Fin de obra 07-10 | U64: 45975 | V64: =IFERROR((COUNTIF(J64:S64,"OK")+COUNTIF(J64:S64,"EN PROCESO")*0.5)/(10-COUNTIF(J64:S64,"NO APLICA")-COUNTIF(J64:S64,"DESCARTADA")-COUNTIF(J64:S64,"-")-COUNTIF(J64:S64,"")),"") -> 0.75 | W64: =IF(ISNUMBER(V64),IF(V64>=0.9,"CONFORME",IF(V64>=0.5,"ALERTA","CRITICO")),IF(F64="CANCELADO","CANCELADO",IF(F64="STAND BY","STAND BY",IF(F64="DESCARTADO","DESCARTADO","S/D")))) -> ALERTA | X64: =10-COUNTIF(J64:S64,"NO APLICA")-COUNTIF(J64:S64,"-")-COUNTIF(J64:S64,"") -> 4 | Y64: =COUNTIF(J64:S64,"OK")+COUNTIF(J64:S64,"EN PROCESO")*0.5 -> 3
A65: 2025 | B65: 22947 | C65: TF REAL PLAZA CUSCO IBK | D65: D | E65: LIC, SUP | F65: CERRADO | H65: B. López | J65: NO APLICA | K65: OK | L65: OK | M65: NO APLICA | N65: NO APLICA | O65: NO APLICA | P65: OK | Q65: NO APLICA | R65: OK | S65: NO APLICA | T65: ARD: Cliente realizó la recepción. | U65: 45980 | V65: =IFERROR((COUNTIF(J65:S65,"OK")+COUNTIF(J65:S65,"EN PROCESO")*0.5)/(10-COUNTIF(J65:S65,"NO APLICA")-COUNTIF(J65:S65,"DESCARTADA")-COUNTIF(J65:S65,"-")-COUNTIF(J65:S65,"")),"") -> 1 | W65: =IF(ISNUMBER(V65),IF(V65>=0.9,"CONFORME",IF(V65>=0.5,"ALERTA","CRITICO")),IF(F65="CANCELADO","CANCELADO",IF(F65="STAND BY","STAND BY",IF(F65="DESCARTADO","DESCARTADO","S/D")))) -> CONFORME | X65: =10-COUNTIF(J65:S65,"NO APLICA")-COUNTIF(J65:S65,"-")-COUNTIF(J65:S65,"") -> 4 | Y65: =COUNTIF(J65:S65,"OK")+COUNTIF(J65:S65,"EN PROCESO")*0.5 -> 4
A66: 2025 | B66: 22946 | C66: TF REAL PLAZA PRO IBK | D66: D | E66: LIC, SUP | F66: CERRADO | H66: B. López | J66: NO APLICA | K66: OK | L66: PENDIENTE | M66: NO APLICA | N66: NO APLICA | O66: NO APLICA | P66: OK | Q66: OK | R66: OK | S66: NO APLICA | T66: Inicio obra estimado 28-08 | V66: =IFERROR((COUNTIF(J66:S66,"OK")+COUNTIF(J66:S66,"EN PROCESO")*0.5)/(10-COUNTIF(J66:S66,"NO APLICA")-COUNTIF(J66:S66,"DESCARTADA")-COUNTIF(J66:S66,"-")-COUNTIF(J66:S66,"")),"") -> 0.8 | W66: =IF(ISNUMBER(V66),IF(V66>=0.9,"CONFORME",IF(V66>=0.5,"ALERTA","CRITICO")),IF(F66="CANCELADO","CANCELADO",IF(F66="STAND BY","STAND BY",IF(F66="DESCARTADO","DESCARTADO","S/D")))) -> ALERTA | X66: =10-COUNTIF(J66:S66,"NO APLICA")-COUNTIF(J66:S66,"-")-COUNTIF(J66:S66,"") -> 5 | Y66: =COUNTIF(J66:S66,"OK")+COUNTIF(J66:S66,"EN PROCESO")*0.5 -> 4
A67: 2025 | B67: 22945 | C67: HABILITACIÓN URBANA MONTEMAR CENTENARIO | D67: D | E67: SUP | F67: CERRADO | H67: B. López | I67: Joseph Anthony Zevallos Armestar | J67: NO APLICA | K67: PENDIENTE | L67: EN PROCESO | M67: NO APLICA | N67: NO APLICA | O67: NO APLICA | P67: OK | Q67: NO APLICA | R67: OK | S67: NO APLICA | T67: Los reportes de avance de obra se cargan en un carpeta compartida con el cliente. Servidor: pendiente verificar entregables: actas de recepción definitiva, planos redes sanitarias, otros | U67: 46177 | V67: =IFERROR((COUNTIF(J67:S67,"OK")+COUNTIF(J67:S67,"EN PROCESO")*0.5)/(10-COUNTIF(J67:S67,"NO APLICA")-COUNTIF(J67:S67,"DESCARTADA")-COUNTIF(J67:S67,"-")-COUNTIF(J67:S67,"")),"") -> 0.625 | W67: =IF(ISNUMBER(V67),IF(V67>=0.9,"CONFORME",IF(V67>=0.5,"ALERTA","CRITICO")),IF(F67="CANCELADO","CANCELADO",IF(F67="STAND BY","STAND BY",IF(F67="DESCARTADO","DESCARTADO","S/D")))) -> ALERTA | X67: =10-COUNTIF(J67:S67,"NO APLICA")-COUNTIF(J67:S67,"-")-COUNTIF(J67:S67,"") -> 4 | Y67: =COUNTIF(J67:S67,"OK")+COUNTIF(J67:S67,"EN PROCESO")*0.5 -> 2.5
A68: 2025 | B68: 22944 | C68: TF RICARDO PALMA IBK | D68: D | E68: SUP | F68: CERRADO | H68: M. Gómez | J68: NO APLICA | K68: PENDIENTE | L68: PENDIENTE | M68: NO APLICA | N68: NO APLICA | O68: NO APLICA | P68: OK | Q68: NO APLICA | R68: OK | S68: NO APLICA | T68: FP: 17-06 Se solicitó acceso | U68: 45980 | V68: =IFERROR((COUNTIF(J68:S68,"OK")+COUNTIF(J68:S68,"EN PROCESO")*0.5)/(10-COUNTIF(J68:S68,"NO APLICA")-COUNTIF(J68:S68,"DESCARTADA")-COUNTIF(J68:S68,"-")-COUNTIF(J68:S68,"")),"") -> 0.5 | W68: =IF(ISNUMBER(V68),IF(V68>=0.9,"CONFORME",IF(V68>=0.5,"ALERTA","CRITICO")),IF(F68="CANCELADO","CANCELADO",IF(F68="STAND BY","STAND BY",IF(F68="DESCARTADO","DESCARTADO","S/D")))) -> ALERTA | X68: =10-COUNTIF(J68:S68,"NO APLICA")-COUNTIF(J68:S68,"-")-COUNTIF(J68:S68,"") -> 4 | Y68: =COUNTIF(J68:S68,"OK")+COUNTIF(J68:S68,"EN PROCESO")*0.5 -> 2
A69: 2025 | B69: 22943 | C69: TF MALL DEL SUR IBK | D69: D | E69: LIC, SUP | F69: CERRADO | H69: B. López | J69: NO APLICA | K69: OK | L69: PENDIENTE | M69: NO APLICA | N69: NO APLICA | O69: NO APLICA | P69: OK | Q69: OK | R69: OK | S69: NO APLICA | T69: FP: 17-06 Se solicitó acceso Supervisión nocturna de manera parcial. Inicio obra 18-08 | U69: 45798 | V69: =IFERROR((COUNTIF(J69:S69,"OK")+COUNTIF(J69:S69,"EN PROCESO")*0.5)/(10-COUNTIF(J69:S69,"NO APLICA")-COUNTIF(J69:S69,"DESCARTADA")-COUNTIF(J69:S69,"-")-COUNTIF(J69:S69,"")),"") -> 0.8 | W69: =IF(ISNUMBER(V69),IF(V69>=0.9,"CONFORME",IF(V69>=0.5,"ALERTA","CRITICO")),IF(F69="CANCELADO","CANCELADO",IF(F69="STAND BY","STAND BY",IF(F69="DESCARTADO","DESCARTADO","S/D")))) -> ALERTA | X69: =10-COUNTIF(J69:S69,"NO APLICA")-COUNTIF(J69:S69,"-")-COUNTIF(J69:S69,"") -> 5 | Y69: =COUNTIF(J69:S69,"OK")+COUNTIF(J69:S69,"EN PROCESO")*0.5 -> 4
A70: 2026 | B70: 22942 | C70: TF EXPRESS AREQUIPA 1 IBK - MALL AVENTURA | D70: D | E70: LIC, SUP | F70: CANCELADO | H70: B. López | J70: NO APLICA | K70: NO APLICA | L70: PENDIENTE | M70: NO APLICA | N70: NO APLICA | O70: NO APLICA | P70: NO APLICA | Q70: NO APLICA | R70: NO APLICA | S70: NO APLICA | T70: FP: 17-06 /Se solicitó acceso Concluída la etapa de licitación. Proyecto en stand by | U70: 45980 | V70: =IFERROR((COUNTIF(J70:S70,"OK")+COUNTIF(J70:S70,"EN PROCESO")*0.5)/(10-COUNTIF(J70:S70,"NO APLICA")-COUNTIF(J70:S70,"DESCARTADA")-COUNTIF(J70:S70,"-")-COUNTIF(J70:S70,"")),"") -> 0 | W70: =IF(ISNUMBER(V70),IF(V70>=0.9,"CONFORME",IF(V70>=0.5,"ALERTA","CRITICO")),IF(F70="CANCELADO","CANCELADO",IF(F70="STAND BY","STAND BY",IF(F70="DESCARTADO","DESCARTADO","S/D")))) -> CRITICO | X70: =10-COUNTIF(J70:S70,"NO APLICA")-COUNTIF(J70:S70,"-")-COUNTIF(J70:S70,"") -> 1 | Y70: =COUNTIF(J70:S70,"OK")+COUNTIF(J70:S70,"EN PROCESO")*0.5 -> 0
A71: 2026 | B71: 22941 | C71: PARQUE LOGÍSTICO ADN GERENCIA ETAPA 2 | D71: D | E71: GP | F71: CERRADO | H71: P. Lavado | J71: NO APLICA | K71: PENDIENTE | L71: PENDIENTE | M71: NO APLICA | N71: NO APLICA | O71: NO APLICA | P71: PENDIENTE | Q71: OK | S71: NO APLICA | T71: Ficha: 15-06-25 Servidor: Solicitar acceso | U71: 45807 | V71: =IFERROR((COUNTIF(J71:S71,"OK")+COUNTIF(J71:S71,"EN PROCESO")*0.5)/(10-COUNTIF(J71:S71,"NO APLICA")-COUNTIF(J71:S71,"DESCARTADA")-COUNTIF(J71:S71,"-")-COUNTIF(J71:S71,"")),"") -> 0.25 | W71: =IF(ISNUMBER(V71),IF(V71>=0.9,"CONFORME",IF(V71>=0.5,"ALERTA","CRITICO")),IF(F71="CANCELADO","CANCELADO",IF(F71="STAND BY","STAND BY",IF(F71="DESCARTADO","DESCARTADO","S/D")))) -> CRITICO | X71: =10-COUNTIF(J71:S71,"NO APLICA")-COUNTIF(J71:S71,"-")-COUNTIF(J71:S71,"") -> 4 | Y71: =COUNTIF(J71:S71,"OK")+COUNTIF(J71:S71,"EN PROCESO")*0.5 -> 1
A72: 2025 | B72: 22940 | C72: INTERVENCIONES ESTRUCTURALES JOCKEY PLAZA (04 proyectos) | D72: D | E72: SUP | F72: CERRADO | H72: F. Choque | I72: Julio Cruz | J72: NO APLICA | K72: OK | L72: PENDIENTE | M72: NO APLICA | N72: NO APLICA | O72: NO APLICA | P72: OK | Q72: NO APLICA | R72: OK | S72: NO APLICA | U72: 45975 | V72: =IFERROR((COUNTIF(J72:S72,"OK")+COUNTIF(J72:S72,"EN PROCESO")*0.5)/(10-COUNTIF(J72:S72,"NO APLICA")-COUNTIF(J72:S72,"DESCARTADA")-COUNTIF(J72:S72,"-")-COUNTIF(J72:S72,"")),"") -> 0.75 | W72: =IF(ISNUMBER(V72),IF(V72>=0.9,"CONFORME",IF(V72>=0.5,"ALERTA","CRITICO")),IF(F72="CANCELADO","CANCELADO",IF(F72="STAND BY","STAND BY",IF(F72="DESCARTADO","DESCARTADO","S/D")))) -> ALERTA | X72: =10-COUNTIF(J72:S72,"NO APLICA")-COUNTIF(J72:S72,"-")-COUNTIF(J72:S72,"") -> 4 | Y72: =COUNTIF(J72:S72,"OK")+COUNTIF(J72:S72,"EN PROCESO")*0.5 -> 3
A73: 2025 | B73: 22939 | C73: DESMONTAJE WONG PANORAMA | D73: D | E73: SUP | F73: CERRADO | H73: J. Lara | J73: NO APLICA | K73: NO APLICA | L73: PENDIENTE | M73: NO APLICA | N73: NO APLICA | O73: NO APLICA | P73: PENDIENTE | Q73: NO APLICA | R73: NO APLICA | S73: NO APLICA | T73: Servidor sin información Trabajos menores | U73: 45840 | V73: =IFERROR((COUNTIF(J73:S73,"OK")+COUNTIF(J73:S73,"EN PROCESO")*0.5)/(10-COUNTIF(J73:S73,"NO APLICA")-COUNTIF(J73:S73,"DESCARTADA")-COUNTIF(J73:S73,"-")-COUNTIF(J73:S73,"")),"") -> 0 | W73: =IF(ISNUMBER(V73),IF(V73>=0.9,"CONFORME",IF(V73>=0.5,"ALERTA","CRITICO")),IF(F73="CANCELADO","CANCELADO",IF(F73="STAND BY","STAND BY",IF(F73="DESCARTADO","DESCARTADO","S/D")))) -> CRITICO | X73: =10-COUNTIF(J73:S73,"NO APLICA")-COUNTIF(J73:S73,"-")-COUNTIF(J73:S73,"") -> 2 | Y73: =COUNTIF(J73:S73,"OK")+COUNTIF(J73:S73,"EN PROCESO")*0.5 -> 0
A74: 2026 | B74: 22938 | C74: REFORZAMIENTO IE DIVINO MAESTRO OXI BCP CAÑETE | D74: A | E74: SUP | F74: SUP | G74: 46203 | H74: F. Choque | I74: Juan Tupayachi | J74: PENDIENTE | L74: PENDIENTE | M74: NO APLICA | P74: OK | Q74: PENDIENTE | S74: NO APLICA | U74: 45819 | V74: =IFERROR((COUNTIF(J74:S74,"OK")+COUNTIF(J74:S74,"EN PROCESO")*0.5)/(10-COUNTIF(J74:S74,"NO APLICA")-COUNTIF(J74:S74,"DESCARTADA")-COUNTIF(J74:S74,"-")-COUNTIF(J74:S74,"")),"") -> 0.25 | W74: =IF(ISNUMBER(V74),IF(V74>=0.9,"CONFORME",IF(V74>=0.5,"ALERTA","CRITICO")),IF(F74="CANCELADO","CANCELADO",IF(F74="STAND BY","STAND BY",IF(F74="DESCARTADO","DESCARTADO","S/D")))) -> CRITICO | X74: =10-COUNTIF(J74:S74,"NO APLICA")-COUNTIF(J74:S74,"-")-COUNTIF(J74:S74,"") -> 4 | Y74: =COUNTIF(J74:S74,"OK")+COUNTIF(J74:S74,"EN PROCESO")*0.5 -> 1
A75: 2025 | B75: 22937 | C75: REFORZAMIENTO IE MANUEL TOVAR OXI BCP SAYÁN | D75: D | E75: SUP | F75: CERRADO | H75: F. Choque | I75: Julio Cruz | J75: NO APLICA | K75: DESCARTADA | L75: OK | M75: NO APLICA | N75: NO APLICA | O75: NO APLICA | P75: OK | Q75: NO APLICA | R75: OK | S75: NO APLICA | T75: ESC: Pilar Cáceres ACS: Responsable indica que BCP no quiere firmar, solo por correo indicó conformidad | U75: 45975 | V75: =IFERROR((COUNTIF(J75:S75,"OK")+COUNTIF(J75:S75,"EN PROCESO")*0.5)/(10-COUNTIF(J75:S75,"NO APLICA")-COUNTIF(J75:S75,"DESCARTADA")-COUNTIF(J75:S75,"-")-COUNTIF(J75:S75,"")),"") -> 1 | W75: =IF(ISNUMBER(V75),IF(V75>=0.9,"CONFORME",IF(V75>=0.5,"ALERTA","CRITICO")),IF(F75="CANCELADO","CANCELADO",IF(F75="STAND BY","STAND BY",IF(F75="DESCARTADO","DESCARTADO","S/D")))) -> CONFORME | X75: =10-COUNTIF(J75:S75,"NO APLICA")-COUNTIF(J75:S75,"-")-COUNTIF(J75:S75,"") -> 4 | Y75: =COUNTIF(J75:S75,"OK")+COUNTIF(J75:S75,"EN PROCESO")*0.5 -> 3
A76: 2026 | B76: 22936 | C76: TIENDAS MASS 2025 | D76: D | E76: ING, SUP | F76: CIERRE | H76: A. Ferrer | J76: NO APLICA | K76: PENDIENTE | L76: PENDIENTE | M76: PENDIENTE | N76: PENDIENTE | O76: NO APLICA | P76: OK | Q76: NO APLICA | R76: PENDIENTE | S76: PENDIENTE | T76: Servidor sin información | U76: 45798 | V76: =IFERROR((COUNTIF(J76:S76,"OK")+COUNTIF(J76:S76,"EN PROCESO")*0.5)/(10-COUNTIF(J76:S76,"NO APLICA")-COUNTIF(J76:S76,"DESCARTADA")-COUNTIF(J76:S76,"-")-COUNTIF(J76:S76,"")),"") -> 0.14285714 | W76: =IF(ISNUMBER(V76),IF(V76>=0.9,"CONFORME",IF(V76>=0.5,"ALERTA","CRITICO")),IF(F76="CANCELADO","CANCELADO",IF(F76="STAND BY","STAND BY",IF(F76="DESCARTADO","DESCARTADO","S/D")))) -> CRITICO | X76: =10-COUNTIF(J76:S76,"NO APLICA")-COUNTIF(J76:S76,"-")-COUNTIF(J76:S76,"") -> 7 | Y76: =COUNTIF(J76:S76,"OK")+COUNTIF(J76:S76,"EN PROCESO")*0.5 -> 1
A77: 2026 | B77: 22935 | C77: UPN LIMA SUR | D77: A | E77: LIC, SUP | F77: SUP | G77: 46432 | H77: F. Choque | I77: Aldo Bendezú | J77: EN PROCESO | L77: PENDIENTE | M77: NO APLICA | P77: OK | Q77: OK | S77: NO APLICA | T77: Fin de obra fines de noviembre25. | U77: 45819 | V77: =IFERROR((COUNTIF(J77:S77,"OK")+COUNTIF(J77:S77,"EN PROCESO")*0.5)/(10-COUNTIF(J77:S77,"NO APLICA")-COUNTIF(J77:S77,"DESCARTADA")-COUNTIF(J77:S77,"-")-COUNTIF(J77:S77,"")),"") -> 0.625 | W77: =IF(ISNUMBER(V77),IF(V77>=0.9,"CONFORME",IF(V77>=0.5,"ALERTA","CRITICO")),IF(F77="CANCELADO","CANCELADO",IF(F77="STAND BY","STAND BY",IF(F77="DESCARTADO","DESCARTADO","S/D")))) -> ALERTA | X77: =10-COUNTIF(J77:S77,"NO APLICA")-COUNTIF(J77:S77,"-")-COUNTIF(J77:S77,"") -> 4 | Y77: =COUNTIF(J77:S77,"OK")+COUNTIF(J77:S77,"EN PROCESO")*0.5 -> 2.5
A78: 2025 | B78: 22934 | C78: IE MARÍA CLARET OXI BCP AQP | D78: D | E78: SUP | F78: CERRADO | H78: F. Choque | I78: Carlos Chambilla | J78: NO APLICA | K78: DESCARTADA | L78: OK | M78: NO APLICA | N78: NO APLICA | O78: NO APLICA | P78: OK | Q78: NO APLICA | R78: OK | S78: NO APLICA | T78: ACS: Responsable indica que BCP no quiere firmar | U78: 45975 | V78: =IFERROR((COUNTIF(J78:S78,"OK")+COUNTIF(J78:S78,"EN PROCESO")*0.5)/(10-COUNTIF(J78:S78,"NO APLICA")-COUNTIF(J78:S78,"DESCARTADA")-COUNTIF(J78:S78,"-")-COUNTIF(J78:S78,"")),"") -> 1 | W78: =IF(ISNUMBER(V78),IF(V78>=0.9,"CONFORME",IF(V78>=0.5,"ALERTA","CRITICO")),IF(F78="CANCELADO","CANCELADO",IF(F78="STAND BY","STAND BY",IF(F78="DESCARTADO","DESCARTADO","S/D")))) -> CONFORME | X78: =10-COUNTIF(J78:S78,"NO APLICA")-COUNTIF(J78:S78,"-")-COUNTIF(J78:S78,"") -> 4 | Y78: =COUNTIF(J78:S78,"OK")+COUNTIF(J78:S78,"EN PROCESO")*0.5 -> 3
A79: 2025 | B79: 22933 | C79: LICORERÍA WONG DOS DE MAYO | D79: D | E79: CONS | F79: CERRADO | H79: F. Choque | J79: NO APLICA | K79: NO APLICA | L79: PENDIENTE | M79: NO APLICA | N79: NO APLICA | O79: NO APLICA | P79: NO APLICA | Q79: NO APLICA | R79: OK | S79: NO APLICA | T79: Servidor sin información ING: Se realizó con personal planilla | U79: 45975 | V79: =IFERROR((COUNTIF(J79:S79,"OK")+COUNTIF(J79:S79,"EN PROCESO")*0.5)/(10-COUNTIF(J79:S79,"NO APLICA")-COUNTIF(J79:S79,"DESCARTADA")-COUNTIF(J79:S79,"-")-COUNTIF(J79:S79,"")),"") -> 0.5 | W79: =IF(ISNUMBER(V79),IF(V79>=0.9,"CONFORME",IF(V79>=0.5,"ALERTA","CRITICO")),IF(F79="CANCELADO","CANCELADO",IF(F79="STAND BY","STAND BY",IF(F79="DESCARTADO","DESCARTADO","S/D")))) -> ALERTA | X79: =10-COUNTIF(J79:S79,"NO APLICA")-COUNTIF(J79:S79,"-")-COUNTIF(J79:S79,"") -> 2 | Y79: =COUNTIF(J79:S79,"OK")+COUNTIF(J79:S79,"EN PROCESO")*0.5 -> 1
A80: 2026 | B80: 22932 | C80: FARMACIAS PERUANAS 2025 | D80: D | E80: SUP | F80: CIERRE | H80: A. Ferrer | J80: NO APLICA | K80: PENDIENTE | L80: PENDIENTE | M80: NO APLICA | N80: NO APLICA | O80: NO APLICA | P80: PENDIENTE | Q80: NO APLICA | R80: PENDIENTE | S80: PENDIENTE | T80: Servidor sin información | U80: 45798 | V80: =IFERROR((COUNTIF(J80:S80,"OK")+COUNTIF(J80:S80,"EN PROCESO")*0.5)/(10-COUNTIF(J80:S80,"NO APLICA")-COUNTIF(J80:S80,"DESCARTADA")-COUNTIF(J80:S80,"-")-COUNTIF(J80:S80,"")),"") -> 0 | W80: =IF(ISNUMBER(V80),IF(V80>=0.9,"CONFORME",IF(V80>=0.5,"ALERTA","CRITICO")),IF(F80="CANCELADO","CANCELADO",IF(F80="STAND BY","STAND BY",IF(F80="DESCARTADO","DESCARTADO","S/D")))) -> CRITICO | X80: =10-COUNTIF(J80:S80,"NO APLICA")-COUNTIF(J80:S80,"-")-COUNTIF(J80:S80,"") -> 5 | Y80: =COUNTIF(J80:S80,"OK")+COUNTIF(J80:S80,"EN PROCESO")*0.5 -> 0
A81: 2025 | B81: 22931 | C81: PLANTA DUEÑAS OESTE ARVUM - ING | D81: D | E81: ING | F81: CERRADO | H81: F. Corvera | J81: NO APLICA | K81: NO APLICA | L81: PENDIENTE | M81: PENDIENTE | N81: PENDIENTE | O81: NO APLICA | P81: NO APLICA | Q81: NO APLICA | R81: NO APLICA | S81: PENDIENTE | T81: Servidor sin información Se cerró seguimiento con pendientes | U81: 45729 | V81: =IFERROR((COUNTIF(J81:S81,"OK")+COUNTIF(J81:S81,"EN PROCESO")*0.5)/(10-COUNTIF(J81:S81,"NO APLICA")-COUNTIF(J81:S81,"DESCARTADA")-COUNTIF(J81:S81,"-")-COUNTIF(J81:S81,"")),"") -> 0 | W81: =IF(ISNUMBER(V81),IF(V81>=0.9,"CONFORME",IF(V81>=0.5,"ALERTA","CRITICO")),IF(F81="CANCELADO","CANCELADO",IF(F81="STAND BY","STAND BY",IF(F81="DESCARTADO","DESCARTADO","S/D")))) -> CRITICO | X81: =10-COUNTIF(J81:S81,"NO APLICA")-COUNTIF(J81:S81,"-")-COUNTIF(J81:S81,"") -> 4 | Y81: =COUNTIF(J81:S81,"OK")+COUNTIF(J81:S81,"EN PROCESO")*0.5 -> 0
A82: 2025 | B82: 22930 | C82: REMODELACIÓN MP HUANCAYO - ING | D82: B | E82: ING | F82: CERRADO | H82: B. López | I82: Michael Gómez | J82: PENDIENTE | K82: OK | L82: PENDIENTE | M82: PENDIENTE | N82: OK | O82: PENDIENTE | P82: NO APLICA | Q82: OK | R82: OK | S82: PENDIENTE | T82: Servidor sin información: 13-06 Ingeniería entregada al cliente. Solicitar encuesta | U82: 45980 | V82: =IFERROR((COUNTIF(J82:S82,"OK")+COUNTIF(J82:S82,"EN PROCESO")*0.5)/(10-COUNTIF(J82:S82,"NO APLICA")-COUNTIF(J82:S82,"DESCARTADA")-COUNTIF(J82:S82,"-")-COUNTIF(J82:S82,"")),"") -> 0.44444444 | W82: =IF(ISNUMBER(V82),IF(V82>=0.9,"CONFORME",IF(V82>=0.5,"ALERTA","CRITICO")),IF(F82="CANCELADO","CANCELADO",IF(F82="STAND BY","STAND BY",IF(F82="DESCARTADO","DESCARTADO","S/D")))) -> CRITICO | X82: =10-COUNTIF(J82:S82,"NO APLICA")-COUNTIF(J82:S82,"-")-COUNTIF(J82:S82,"") -> 9 | Y82: =COUNTIF(J82:S82,"OK")+COUNTIF(J82:S82,"EN PROCESO")*0.5 -> 4
A83: 2025 | B83: 22929 | C83: AGENCIA CELENDÍN CAJA AREQUIPA | D83: D | E83: SUP | F83: CERRADO | H83: F. Choque | I83: Daniel Guevara | J83: NO APLICA | K83: PENDIENTE | L83: PENDIENTE | M83: NO APLICA | N83: NO APLICA | O83: NO APLICA | P83: OK | Q83: NO APLICA | R83: OK | S83: NO APLICA | T83: Servidor: completar y ordenar la información. ACS: En proceso | U83: 45975 | V83: =IFERROR((COUNTIF(J83:S83,"OK")+COUNTIF(J83:S83,"EN PROCESO")*0.5)/(10-COUNTIF(J83:S83,"NO APLICA")-COUNTIF(J83:S83,"DESCARTADA")-COUNTIF(J83:S83,"-")-COUNTIF(J83:S83,"")),"") -> 0.5 | W83: =IF(ISNUMBER(V83),IF(V83>=0.9,"CONFORME",IF(V83>=0.5,"ALERTA","CRITICO")),IF(F83="CANCELADO","CANCELADO",IF(F83="STAND BY","STAND BY",IF(F83="DESCARTADO","DESCARTADO","S/D")))) -> ALERTA | X83: =10-COUNTIF(J83:S83,"NO APLICA")-COUNTIF(J83:S83,"-")-COUNTIF(J83:S83,"") -> 4 | Y83: =COUNTIF(J83:S83,"OK")+COUNTIF(J83:S83,"EN PROCESO")*0.5 -> 2
A84: 2026 | B84: 22928 | C84: AMPLIACIÓN OPEN PLAZA ANGAMOS - ING | D84: A | E84: ING | F84: ING | G84: 46173 | H84: B. López | I84: Michael Gómez | J84: PENDIENTE | L84: PENDIENTE | M84: PENDIENTE | N84: PENDIENTE | O84: PENDIENTE | P84: NO APLICA | Q84: OK | R84: PENDIENTE | S84: PENDIENTE | T84: Fin de servicio 27-04 | U84: 45980 | V84: =IFERROR((COUNTIF(J84:S84,"OK")+COUNTIF(J84:S84,"EN PROCESO")*0.5)/(10-COUNTIF(J84:S84,"NO APLICA")-COUNTIF(J84:S84,"DESCARTADA")-COUNTIF(J84:S84,"-")-COUNTIF(J84:S84,"")),"") -> 0.125 | W84: =IF(ISNUMBER(V84),IF(V84>=0.9,"CONFORME",IF(V84>=0.5,"ALERTA","CRITICO")),IF(F84="CANCELADO","CANCELADO",IF(F84="STAND BY","STAND BY",IF(F84="DESCARTADO","DESCARTADO","S/D")))) -> CRITICO | X84: =10-COUNTIF(J84:S84,"NO APLICA")-COUNTIF(J84:S84,"-")-COUNTIF(J84:S84,"") -> 8 | Y84: =COUNTIF(J84:S84,"OK")+COUNTIF(J84:S84,"EN PROCESO")*0.5 -> 1
A85: 2025 | B85: 22927 | C85: 05 COLEGIOS GORE OXI BCP | D85: D | E85: CONS | F85: CERRADO | H85: F. Choque | J85: NO APLICA | K85: DESCARTADA | L85: EN PROCESO | M85: NO APLICA | N85: NO APLICA | O85: NO APLICA | P85: NO APLICA | Q85: NO APLICA | R85: OK | S85: PENDIENTE | T85: Servicio metrados Servidor: completar y ordenar la información. ACS: Responsable indica que BCP no quiere firmar, solo por correo indicó conformidad | U85: 45975 | V85: =IFERROR((COUNTIF(J85:S85,"OK")+COUNTIF(J85:S85,"EN PROCESO")*0.5)/(10-COUNTIF(J85:S85,"NO APLICA")-COUNTIF(J85:S85,"DESCARTADA")-COUNTIF(J85:S85,"-")-COUNTIF(J85:S85,"")),"") -> 0.5 | W85: =IF(ISNUMBER(V85),IF(V85>=0.9,"CONFORME",IF(V85>=0.5,"ALERTA","CRITICO")),IF(F85="CANCELADO","CANCELADO",IF(F85="STAND BY","STAND BY",IF(F85="DESCARTADO","DESCARTADO","S/D")))) -> ALERTA | X85: =10-COUNTIF(J85:S85,"NO APLICA")-COUNTIF(J85:S85,"-")-COUNTIF(J85:S85,"") -> 4 | Y85: =COUNTIF(J85:S85,"OK")+COUNTIF(J85:S85,"EN PROCESO")*0.5 -> 1.5
A86: 2025 | B86: 22926 | C86: 03 TIENDAS METRO LIMA | D86: D | E86: SUP | F86: CANCELADO | H86: M. Becerra | J86: NO APLICA | K86: NO APLICA | L86: NO APLICA | M86: NO APLICA | N86: NO APLICA | O86: NO APLICA | P86: NO APLICA | Q86: NO APLICA | R86: NO APLICA | S86: NO APLICA | T86: Trabajos de Aire Acondicionado en Independencia, Breña y Barranco. Fecha estimada inicio julio 25. La órden de compra fue anulada. | U86: 45978 | V86: =IFERROR((COUNTIF(J86:S86,"OK")+COUNTIF(J86:S86,"EN PROCESO")*0.5)/(10-COUNTIF(J86:S86,"NO APLICA")-COUNTIF(J86:S86,"DESCARTADA")-COUNTIF(J86:S86,"-")-COUNTIF(J86:S86,"")),"") | W86: =IF(ISNUMBER(V86),IF(V86>=0.9,"CONFORME",IF(V86>=0.5,"ALERTA","CRITICO")),IF(F86="CANCELADO","CANCELADO",IF(F86="STAND BY","STAND BY",IF(F86="DESCARTADO","DESCARTADO","S/D")))) -> CANCELADO | X86: =10-COUNTIF(J86:S86,"NO APLICA")-COUNTIF(J86:S86,"-")-COUNTIF(J86:S86,"") -> 0 | Y86: =COUNTIF(J86:S86,"OK")+COUNTIF(J86:S86,"EN PROCESO")*0.5 -> 0
A87: 2025 | B87: 22925 | C87: 04 TIENDAS METRO ZONA NORTE | D87: D | E87: SUP | F87: CERRADO | H87: M. Becerra | I87: Luis Chuquilin | J87: NO APLICA | K87: OK | L87: PENDIENTE | M87: NO APLICA | N87: NO APLICA | O87: NO APLICA | P87: OK | Q87: NO APLICA | R87: OK | S87: NO APLICA | T87: Inicio febrero25. Trabajos de Aire Acondcionado en Trujillo, Chiclayo y Lambayeque. GRAU, PIZARRO, LAMBAYEQUE, SANTA VICTORIA. Reportes de obra: han copiado a calidad recién desde el 20.05. La obra inicio en febrero. Pizarro, Grau y Lambayeque en proceso de cierre El servicio de SIGRAL cierra 04-06. Servidor: falta adicionales, dossier, control del servicio, valorizaciones, control del servicio, otros aplicables. | U87: 45978 | V87: =IFERROR((COUNTIF(J87:S87,"OK")+COUNTIF(J87:S87,"EN PROCESO")*0.5)/(10-COUNTIF(J87:S87,"NO APLICA")-COUNTIF(J87:S87,"DESCARTADA")-COUNTIF(J87:S87,"-")-COUNTIF(J87:S87,"")),"") -> 0.75 | W87: =IF(ISNUMBER(V87),IF(V87>=0.9,"CONFORME",IF(V87>=0.5,"ALERTA","CRITICO")),IF(F87="CANCELADO","CANCELADO",IF(F87="STAND BY","STAND BY",IF(F87="DESCARTADO","DESCARTADO","S/D")))) -> ALERTA | X87: =10-COUNTIF(J87:S87,"NO APLICA")-COUNTIF(J87:S87,"-")-COUNTIF(J87:S87,"") -> 4 | Y87: =COUNTIF(J87:S87,"OK")+COUNTIF(J87:S87,"EN PROCESO")*0.5 -> 3
A88: 2025 | B88: 22924 | C88: 03 PROYECTOS UPN CAJAMARCA | D88: D | E88: SUP | F88: CERRADO | H88: J. Lara | I88: Dany Tacilla | J88: NO APLICA | K88: PENDIENTE | L88: OK | M88: NO APLICA | N88: NO APLICA | O88: NO APLICA | P88: OK | Q88: OK | R88: OK | S88: NO APLICA | T88: Valorizaciones, liquidación por parte del cliente. Dossier: solo calidad. ACS: 15-06-25 | U88: 45840 | V88: =IFERROR((COUNTIF(J88:S88,"OK")+COUNTIF(J88:S88,"EN PROCESO")*0.5)/(10-COUNTIF(J88:S88,"NO APLICA")-COUNTIF(J88:S88,"DESCARTADA")-COUNTIF(J88:S88,"-")-COUNTIF(J88:S88,"")),"") -> 0.8 | W88: =IF(ISNUMBER(V88),IF(V88>=0.9,"CONFORME",IF(V88>=0.5,"ALERTA","CRITICO")),IF(F88="CANCELADO","CANCELADO",IF(F88="STAND BY","STAND BY",IF(F88="DESCARTADO","DESCARTADO","S/D")))) -> ALERTA | X88: =10-COUNTIF(J88:S88,"NO APLICA")-COUNTIF(J88:S88,"-")-COUNTIF(J88:S88,"") -> 5 | Y88: =COUNTIF(J88:S88,"OK")+COUNTIF(J88:S88,"EN PROCESO")*0.5 -> 4
A89: 2024 | B89: 22923 | C89: AUDITORÍA DE COSTOS CLUB DE REGATAS LA CANTUTA | D89: D | E89: CONS | F89: CERRADO | H89: R. Nuñez | I89: Moises Becerra / Eddy P | J89: NO APLICA | K89: NO APLICA | L89: PENDIENTE | M89: NO APLICA | N89: NO APLICA | O89: NO APLICA | P89: NO APLICA | Q89: NO APLICA | R89: NO APLICA | S89: PENDIENTE | T89: Personal no labora en la empresa | U89: 45798 | V89: =IFERROR((COUNTIF(J89:S89,"OK")+COUNTIF(J89:S89,"EN PROCESO")*0.5)/(10-COUNTIF(J89:S89,"NO APLICA")-COUNTIF(J89:S89,"DESCARTADA")-COUNTIF(J89:S89,"-")-COUNTIF(J89:S89,"")),"") -> 0 | W89: =IF(ISNUMBER(V89),IF(V89>=0.9,"CONFORME",IF(V89>=0.5,"ALERTA","CRITICO")),IF(F89="CANCELADO","CANCELADO",IF(F89="STAND BY","STAND BY",IF(F89="DESCARTADO","DESCARTADO","S/D")))) -> CRITICO | X89: =10-COUNTIF(J89:S89,"NO APLICA")-COUNTIF(J89:S89,"-")-COUNTIF(J89:S89,"") -> 2 | Y89: =COUNTIF(J89:S89,"OK")+COUNTIF(J89:S89,"EN PROCESO")*0.5 -> 0
A90: 2024 | B90: 22922 | C90: IISS Y CLIMA CLUB DE REGATAS CHORRILLOS | D90: D | E90: CONS | F90: CERRADO | H90: R. Nuñez | J90: NO APLICA | K90: NO APLICA | L90: PENDIENTE | M90: NO APLICA | N90: NO APLICA | O90: NO APLICA | P90: NO APLICA | Q90: NO APLICA | R90: NO APLICA | S90: PENDIENTE | T90: Personal no labora en la empresa | U90: 45798 | V90: =IFERROR((COUNTIF(J90:S90,"OK")+COUNTIF(J90:S90,"EN PROCESO")*0.5)/(10-COUNTIF(J90:S90,"NO APLICA")-COUNTIF(J90:S90,"DESCARTADA")-COUNTIF(J90:S90,"-")-COUNTIF(J90:S90,"")),"") -> 0 | W90: =IF(ISNUMBER(V90),IF(V90>=0.9,"CONFORME",IF(V90>=0.5,"ALERTA","CRITICO")),IF(F90="CANCELADO","CANCELADO",IF(F90="STAND BY","STAND BY",IF(F90="DESCARTADO","DESCARTADO","S/D")))) -> CRITICO | X90: =10-COUNTIF(J90:S90,"NO APLICA")-COUNTIF(J90:S90,"-")-COUNTIF(J90:S90,"") -> 2 | Y90: =COUNTIF(J90:S90,"OK")+COUNTIF(J90:S90,"EN PROCESO")*0.5 -> 0
A91: 2025 | B91: 22921 | C91: COLEGIO LUIS ALBERTO SÁNCHEZ BCP | D91: D | E91: SUP | F91: CERRADO | H91: F. Choque | I91: Julio Cruz | J91: NO APLICA | K91: DESCARTADA | L91: OK | M91: NO APLICA | N91: NO APLICA | O91: NO APLICA | P91: OK | Q91: NO APLICA | R91: OK | S91: NO APLICA | T91: Dossier QA/SSTMA entregado directamente por el contratista. Conformidad solo por correo. | U91: 45975 | V91: =IFERROR((COUNTIF(J91:S91,"OK")+COUNTIF(J91:S91,"EN PROCESO")*0.5)/(10-COUNTIF(J91:S91,"NO APLICA")-COUNTIF(J91:S91,"DESCARTADA")-COUNTIF(J91:S91,"-")-COUNTIF(J91:S91,"")),"") -> 1 | W91: =IF(ISNUMBER(V91),IF(V91>=0.9,"CONFORME",IF(V91>=0.5,"ALERTA","CRITICO")),IF(F91="CANCELADO","CANCELADO",IF(F91="STAND BY","STAND BY",IF(F91="DESCARTADO","DESCARTADO","S/D")))) -> CONFORME | X91: =10-COUNTIF(J91:S91,"NO APLICA")-COUNTIF(J91:S91,"-")-COUNTIF(J91:S91,"") -> 4 | Y91: =COUNTIF(J91:S91,"OK")+COUNTIF(J91:S91,"EN PROCESO")*0.5 -> 3
A92: 2026 | B92: 22920 | C92: TF JIRÓN DE LA UNIÓN IBK | D92: D | E92: LIC, SUP | F92: STAND BY | H92: B. López | J92: NO APLICA | L92: OK | M92: NO APLICA | N92: NO APLICA | O92: NO APLICA | P92: NO APLICA | Q92: NO APLICA | S92: NO APLICA | T92: Proyecto en stand by, en proceso de trámite de licencia. Licitación cerrada. Servidor actualizado a mayo25. | U92: 45980 | V92: =IFERROR((COUNTIF(J92:S92,"OK")+COUNTIF(J92:S92,"EN PROCESO")*0.5)/(10-COUNTIF(J92:S92,"NO APLICA")-COUNTIF(J92:S92,"DESCARTADA")-COUNTIF(J92:S92,"-")-COUNTIF(J92:S92,"")),"") -> 1 | W92: =IF(ISNUMBER(V92),IF(V92>=0.9,"CONFORME",IF(V92>=0.5,"ALERTA","CRITICO")),IF(F92="CANCELADO","CANCELADO",IF(F92="STAND BY","STAND BY",IF(F92="DESCARTADO","DESCARTADO","S/D")))) -> CONFORME | X92: =10-COUNTIF(J92:S92,"NO APLICA")-COUNTIF(J92:S92,"-")-COUNTIF(J92:S92,"") -> 1 | Y92: =COUNTIF(J92:S92,"OK")+COUNTIF(J92:S92,"EN PROCESO")*0.5 -> 1
A93: 2024 | B93: 22919 | C93: PREVENTORIO DE SALUD UPN PUENTE PIEDRA | D93: D | E93: SUP | F93: CERRADO | H93: J. Lara | I93: Eddy Portocarrero | J93: NO APLICA | K93: PENDIENTE | L93: OK | M93: NO APLICA | N93: NO APLICA | O93: NO APLICA | P93: OK | Q93: OK | R93: NO APLICA | S93: NO APLICA | T93: Dossier: se cargo dossier con observaciones. El seguimiento no fue parte de nuestro servicio, el plazo termino. ACS: 14-06-25. Conformidad de pago valorización 01 no se firma por parte de SIGRAL, se facturo. Proyecto menor | U93: 45840 | V93: =IFERROR((COUNTIF(J93:S93,"OK")+COUNTIF(J93:S93,"EN PROCESO")*0.5)/(10-COUNTIF(J93:S93,"NO APLICA")-COUNTIF(J93:S93,"DESCARTADA")-COUNTIF(J93:S93,"-")-COUNTIF(J93:S93,"")),"") -> 0.75 | W93: =IF(ISNUMBER(V93),IF(V93>=0.9,"CONFORME",IF(V93>=0.5,"ALERTA","CRITICO")),IF(F93="CANCELADO","CANCELADO",IF(F93="STAND BY","STAND BY",IF(F93="DESCARTADO","DESCARTADO","S/D")))) -> ALERTA | X93: =10-COUNTIF(J93:S93,"NO APLICA")-COUNTIF(J93:S93,"-")-COUNTIF(J93:S93,"") -> 4 | Y93: =COUNTIF(J93:S93,"OK")+COUNTIF(J93:S93,"EN PROCESO")*0.5 -> 3
A94: 2024 | B94: 22918 | C94: REPARACIÓN FISURAS RP CUSCO | D94: D | E94: SUP | F94: CERRADO | H94: M. Gómez | J94: NO APLICA | K94: NO APLICA | L94: PENDIENTE | M94: NO APLICA | N94: NO APLICA | O94: NO APLICA | P94: PENDIENTE | Q94: NO APLICA | R94: NO APLICA | S94: NO APLICA | T94: Servidor sin información MG solicitará acceso al servidor y cargar los entregables. | U94: 45980 | V94: =IFERROR((COUNTIF(J94:S94,"OK")+COUNTIF(J94:S94,"EN PROCESO")*0.5)/(10-COUNTIF(J94:S94,"NO APLICA")-COUNTIF(J94:S94,"DESCARTADA")-COUNTIF(J94:S94,"-")-COUNTIF(J94:S94,"")),"") -> 0 | W94: =IF(ISNUMBER(V94),IF(V94>=0.9,"CONFORME",IF(V94>=0.5,"ALERTA","CRITICO")),IF(F94="CANCELADO","CANCELADO",IF(F94="STAND BY","STAND BY",IF(F94="DESCARTADO","DESCARTADO","S/D")))) -> CRITICO | X94: =10-COUNTIF(J94:S94,"NO APLICA")-COUNTIF(J94:S94,"-")-COUNTIF(J94:S94,"") -> 2 | Y94: =COUNTIF(J94:S94,"OK")+COUNTIF(J94:S94,"EN PROCESO")*0.5 -> 0
A95: 2024 | B95: 22917 | C95: ACTUALIZACIÓN OFICINA QUBO | D95: D | E95: CONS | F95: CERRADO | H95: C. Valdizán | J95: NO APLICA | K95: NO APLICA | L95: PENDIENTE | M95: PENDIENTE | N95: NO APLICA | O95: NO APLICA | P95: NO APLICA | Q95: NO APLICA | R95: NO APLICA | S95: NO APLICA | T95: No considerar dentro del SIG | V95: =IFERROR((COUNTIF(J95:S95,"OK")+COUNTIF(J95:S95,"EN PROCESO")*0.5)/(10-COUNTIF(J95:S95,"NO APLICA")-COUNTIF(J95:S95,"DESCARTADA")-COUNTIF(J95:S95,"-")-COUNTIF(J95:S95,"")),"") -> 0 | W95: =IF(ISNUMBER(V95),IF(V95>=0.9,"CONFORME",IF(V95>=0.5,"ALERTA","CRITICO")),IF(F95="CANCELADO","CANCELADO",IF(F95="STAND BY","STAND BY",IF(F95="DESCARTADO","DESCARTADO","S/D")))) -> CRITICO | X95: =10-COUNTIF(J95:S95,"NO APLICA")-COUNTIF(J95:S95,"-")-COUNTIF(J95:S95,"") -> 2 | Y95: =COUNTIF(J95:S95,"OK")+COUNTIF(J95:S95,"EN PROCESO")*0.5 -> 0
A96: 2024 | B96: 22916 | C96: MM PAITA IBK | D96: D | E96: SUP | F96: CERRADO | H96: M. Gómez | J96: NO APLICA | K96: PENDIENTE | L96: OK | M96: NO APLICA | N96: NO APLICA | O96: NO APLICA | P96: OK | Q96: NO APLICA | R96: NO APLICA | S96: NO APLICA | T96: ACS: 13-06 | U96: 45980 | V96: =IFERROR((COUNTIF(J96:S96,"OK")+COUNTIF(J96:S96,"EN PROCESO")*0.5)/(10-COUNTIF(J96:S96,"NO APLICA")-COUNTIF(J96:S96,"DESCARTADA")-COUNTIF(J96:S96,"-")-COUNTIF(J96:S96,"")),"") -> 0.66666667 | W96: =IF(ISNUMBER(V96),IF(V96>=0.9,"CONFORME",IF(V96>=0.5,"ALERTA","CRITICO")),IF(F96="CANCELADO","CANCELADO",IF(F96="STAND BY","STAND BY",IF(F96="DESCARTADO","DESCARTADO","S/D")))) -> ALERTA | X96: =10-COUNTIF(J96:S96,"NO APLICA")-COUNTIF(J96:S96,"-")-COUNTIF(J96:S96,"") -> 3 | Y96: =COUNTIF(J96:S96,"OK")+COUNTIF(J96:S96,"EN PROCESO")*0.5 -> 2
A97: 2024 | B97: 22915 | C97: AGENCIA NEX GEN BCP CAYMA | D97: D | E97: SUP | F97: CERRADO | H97: F. Choque | J97: NO APLICA | K97: DESCARTADA | L97: OK | M97: NO APLICA | N97: NO APLICA | O97: NO APLICA | P97: OK | Q97: NO APLICA | R97: OK | S97: NO APLICA | T97: Dossier QA/SSTMA. Sigral no ha validado la versión final, el servicio ya había concluido. La contratista entrego directamente al cliente. Se indica el estatus en el informe final. ACS: Responsable indica que BCP no quiere firmar | U97: 45975 | V97: =IFERROR((COUNTIF(J97:S97,"OK")+COUNTIF(J97:S97,"EN PROCESO")*0.5)/(10-COUNTIF(J97:S97,"NO APLICA")-COUNTIF(J97:S97,"DESCARTADA")-COUNTIF(J97:S97,"-")-COUNTIF(J97:S97,"")),"") -> 1 | W97: =IF(ISNUMBER(V97),IF(V97>=0.9,"CONFORME",IF(V97>=0.5,"ALERTA","CRITICO")),IF(F97="CANCELADO","CANCELADO",IF(F97="STAND BY","STAND BY",IF(F97="DESCARTADO","DESCARTADO","S/D")))) -> CONFORME | X97: =10-COUNTIF(J97:S97,"NO APLICA")-COUNTIF(J97:S97,"-")-COUNTIF(J97:S97,"") -> 4 | Y97: =COUNTIF(J97:S97,"OK")+COUNTIF(J97:S97,"EN PROCESO")*0.5 -> 3
A98: 2024 | B98: 22914 | C98: INSTALACIÓN PANTALLAS RP PURUCHUCO | D98: D | E98: SUP | F98: CERRADO | H98: C. Castillo | I98: Julio Cruz | J98: NO APLICA | K98: NO APLICA | L98: OK | M98: NO APLICA | N98: OK | O98: NO APLICA | P98: PENDIENTE | Q98: NO APLICA | R98: NO APLICA | S98: NO APLICA | T98: Servidor actualizado al 11-11 por Carlos Castillo. No se evidencian reportes de obra | V98: =IFERROR((COUNTIF(J98:S98,"OK")+COUNTIF(J98:S98,"EN PROCESO")*0.5)/(10-COUNTIF(J98:S98,"NO APLICA")-COUNTIF(J98:S98,"DESCARTADA")-COUNTIF(J98:S98,"-")-COUNTIF(J98:S98,"")),"") -> 0.66666667 | W98: =IF(ISNUMBER(V98),IF(V98>=0.9,"CONFORME",IF(V98>=0.5,"ALERTA","CRITICO")),IF(F98="CANCELADO","CANCELADO",IF(F98="STAND BY","STAND BY",IF(F98="DESCARTADO","DESCARTADO","S/D")))) -> ALERTA | X98: =10-COUNTIF(J98:S98,"NO APLICA")-COUNTIF(J98:S98,"-")-COUNTIF(J98:S98,"") -> 3 | Y98: =COUNTIF(J98:S98,"OK")+COUNTIF(J98:S98,"EN PROCESO")*0.5 -> 2
A99: 2024 | B99: 22913 | C99: PLATAFORMA MANTENIMIENTO LATAM | D99: D | E99: CONS | F99: CERRADO | H99: Giancarlo G | J99: NO APLICA | K99: NO APLICA | L99: PENDIENTE | M99: NO APLICA | N99: NO APLICA | O99: NO APLICA | P99: NO APLICA | Q99: NO APLICA | R99: NO APLICA | S99: NO APLICA | T99: DD: Pendiente firma de Pedro Lavado Sevidor: cerrado con observaciones. El responsable ya no labora en SIGRAL. | U99: 45721 | V99: =IFERROR((COUNTIF(J99:S99,"OK")+COUNTIF(J99:S99,"EN PROCESO")*0.5)/(10-COUNTIF(J99:S99,"NO APLICA")-COUNTIF(J99:S99,"DESCARTADA")-COUNTIF(J99:S99,"-")-COUNTIF(J99:S99,"")),"") -> 0 | W99: =IF(ISNUMBER(V99),IF(V99>=0.9,"CONFORME",IF(V99>=0.5,"ALERTA","CRITICO")),IF(F99="CANCELADO","CANCELADO",IF(F99="STAND BY","STAND BY",IF(F99="DESCARTADO","DESCARTADO","S/D")))) -> CRITICO | X99: =10-COUNTIF(J99:S99,"NO APLICA")-COUNTIF(J99:S99,"-")-COUNTIF(J99:S99,"") -> 1 | Y99: =COUNTIF(J99:S99,"OK")+COUNTIF(J99:S99,"EN PROCESO")*0.5 -> 0
A100: 2025 | B100: 22912 | C100: UTP AREQUIPA IV ETAPA 3 | D100: A | E100: SUP | F100: CERRADO | H100: P. Lavado | I100: Delia Garcia | J100: PENDIENTE | K100: PENDIENTE | L100: PENDIENTE | M100: NO APLICA | N100: OK | O100: PENDIENTE | P100: PENDIENTE | Q100: PENDIENTE | R100: OK | S100: NO APLICA | T100: Continuación del 22864 Servidor sin información. PL indicó que se maneja en SHAREPOINT. | U100: 45980 | V100: =IFERROR((COUNTIF(J100:S100,"OK")+COUNTIF(J100:S100,"EN PROCESO")*0.5)/(10-COUNTIF(J100:S100,"NO APLICA")-COUNTIF(J100:S100,"DESCARTADA")-COUNTIF(J100:S100,"-")-COUNTIF(J100:S100,"")),"") -> 0.25 | W100: =IF(ISNUMBER(V100),IF(V100>=0.9,"CONFORME",IF(V100>=0.5,"ALERTA","CRITICO")),IF(F100="CANCELADO","CANCELADO",IF(F100="STAND BY","STAND BY",IF(F100="DESCARTADO","DESCARTADO","S/D")))) -> CRITICO | X100: =10-COUNTIF(J100:S100,"NO APLICA")-COUNTIF(J100:S100,"-")-COUNTIF(J100:S100,"") -> 8 | Y100: =COUNTIF(J100:S100,"OK")+COUNTIF(J100:S100,"EN PROCESO")*0.5 -> 2
...

Sheet DASHBOARD_KPIs
A1: DASHBOARD DE SEGUIMIENTO DE PROYECTOS
A2: Actualizado 29/05/2026 · CONFORME ≥ 90% | EN RIESGO 50–89% | CRÍTICO < 50%
B3: 🔍 FILTRAR POR AÑO DE CIERRE: | D3: 0 | E3: =IF(D3=0,">0","="&D3) -> >0 | F3: ← Escribir: 0=TODOS / 2024 / 2025 / 2026
B5: 📊 RESUMEN GENERAL DE PROYECTOS
B6: TOTAL PROYECTOS | C6: PROYECTOS ACTIVOS | D6: CERRADOS | E6: CANCELADOS | F6: STAND BY | G6: % SIG PROM.
B7: =COUNTIFS(SEGUIMIENTO_PROYECTOS!$A$5:$A$185,DASHBOARD_KPIs!$E$3) -> 180 | C7: =COUNTIFS(SEGUIMIENTO_PROYECTOS!$A$5:$A$185,DASHBOARD_KPIs!$E$3)-COUNTIFS(SEGUIMIENTO_PROYECTOS!$A$5:$A$185,DASHBOARD_KPIs!$E$3,SEGUIMIENTO_PROYECTOS!$F$5:$F$185,"CERRADO")-COUNTIFS(SEGUIMIENTO_PROYECTOS!$A$5:$A$185,DASHBOARD_KPIs!$E$3,SEGUIMIENTO_PROYECTOS!$F$5:$F$185,"CANCELADO")-COUNTIFS(SEGUIMIENTO_PROYECTOS!$A$5:$A$185,DASHBOARD_KPIs!$E$3,SEGUIMIENTO_PROYECTOS!$F$5:$F$185,"DESCARTADO") -> 46 | D7: =COUNTIFS(SEGUIMIENTO_PROYECTOS!$A$5:$A$185,DASHBOARD_KPIs!$E$3,SEGUIMIENTO_PROYECTOS!$F$5:$F$185,"CERRADO") -> 130 | E7: =COUNTIFS(SEGUIMIENTO_PROYECTOS!$A$5:$A$185,DASHBOARD_KPIs!$E$3,SEGUIMIENTO_PROYECTOS!$F$5:$F$185,"CANCELADO") -> 4 | F7: =COUNTIFS(SEGUIMIENTO_PROYECTOS!$A$5:$A$185,DASHBOARD_KPIs!$E$3,SEGUIMIENTO_PROYECTOS!$F$5:$F$185,"STAND BY") -> 4 | G7: =IFERROR(SUMIFS(SEGUIMIENTO_PROYECTOS!$Y$5:$Y$185,SEGUIMIENTO_PROYECTOS!$A$5:$A$185,DASHBOARD_KPIs!$E$3)/SUMIFS(SEGUIMIENTO_PROYECTOS!$X$5:$X$185,SEGUIMIENTO_PROYECTOS!$A$5:$A$185,DASHBOARD_KPIs!$E$3),"—") -> 0.55511811
B8: En base de datos | C8: Excluye cerrados | D8: Etapa CERRADO | E8: Etapa CANCELADO | F8: Suspendidos | G8: Acumulado todos los proyectos
B11: 🚦 ESTADO GENERAL — DISTRIBUCIÓN
B12: CONFORME | C12: ALERTA | D12: CRITICO | E12: CANCELADO | F12: STAND BY | G12: S/D
B13: =COUNTIFS(SEGUIMIENTO_PROYECTOS!$A$5:$A$185,DASHBOARD_KPIs!$E$3,SEGUIMIENTO_PROYECTOS!$W$5:$W$185,"CONFORME") -> 33 | C13: =COUNTIFS(SEGUIMIENTO_PROYECTOS!$A$5:$A$185,DASHBOARD_KPIs!$E$3,SEGUIMIENTO_PROYECTOS!$W$5:$W$185,"ALERTA") -> 74 | D13: =COUNTIFS(SEGUIMIENTO_PROYECTOS!$A$5:$A$185,DASHBOARD_KPIs!$E$3,SEGUIMIENTO_PROYECTOS!$W$5:$W$185,"CRITICO") -> 62 | E13: =COUNTIFS(SEGUIMIENTO_PROYECTOS!$A$5:$A$185,DASHBOARD_KPIs!$E$3,SEGUIMIENTO_PROYECTOS!$W$5:$W$185,"CANCELADO") -> 3 | F13: =COUNTIFS(SEGUIMIENTO_PROYECTOS!$A$5:$A$185,DASHBOARD_KPIs!$E$3,SEGUIMIENTO_PROYECTOS!$W$5:$W$185,"STAND BY") -> 2 | G13: =COUNTIFS(SEGUIMIENTO_PROYECTOS!$A$5:$A$185,DASHBOARD_KPIs!$E$3,SEGUIMIENTO_PROYECTOS!$W$5:$W$185,"S/D") -> 6
B14: ≥ 90% SIG | C14: 50–89% SIG | D14: < 50% SIG | E14: Etapa CANCELADO | F14: Suspendidos | G14: Sin datos
B17: 📋 SEGUIMIENTO POR ENTREGABLE SIG
B18: ENTREGABLE | C18: APLICA | D18: OK | E18: OK (falta firma) | F18: EN PROCESO | G18: PENDIENTE | H18: NO APLICA | I18: % CUMPL. | J18: ESTADO
B19: FICHA DE PROYECTO | C19: =COUNTIFS(SEGUIMIENTO_PROYECTOS!$A$5:$A$185,DASHBOARD_KPIs!$E$3)-COUNTIFS(SEGUIMIENTO_PROYECTOS!$A$5:$A$185,DASHBOARD_KPIs!$E$3,SEGUIMIENTO_PROYECTOS!$J$5:$J$185,"NO APLICA")-COUNTIFS(SEGUIMIENTO_PROYECTOS!$A$5:$A$185,DASHBOARD_KPIs!$E$3,SEGUIMIENTO_PROYECTOS!$J$5:$J$185,"-")-COUNTIFS(SEGUIMIENTO_PROYECTOS!$A$5:$A$185,DASHBOARD_KPIs!$E$3,SEGUIMIENTO_PROYECTOS!$J$5:$J$185,"") -> 51 | D19: =COUNTIFS(SEGUIMIENTO_PROYECTOS!$A$5:$A$185,DASHBOARD_KPIs!$E$3,SEGUIMIENTO_PROYECTOS!$J$5:$J$185,"OK") -> 18 | E19: =COUNTIFS(SEGUIMIENTO_PROYECTOS!$A$5:$A$185,DASHBOARD_KPIs!$E$3,SEGUIMIENTO_PROYECTOS!$J$5:$J$185,"OK (falta firma)") -> 0 | F19: =COUNTIFS(SEGUIMIENTO_PROYECTOS!$A$5:$A$185,DASHBOARD_KPIs!$E$3,SEGUIMIENTO_PROYECTOS!$J$5:$J$185,"EN PROCESO") -> 4 | G19: =COUNTIFS(SEGUIMIENTO_PROYECTOS!$A$5:$A$185,DASHBOARD_KPIs!$E$3,SEGUIMIENTO_PROYECTOS!$J$5:$J$185,"PENDIENTE") -> 29 | H19: =COUNTIFS(SEGUIMIENTO_PROYECTOS!$A$5:$A$185,DASHBOARD_KPIs!$E$3,SEGUIMIENTO_PROYECTOS!$J$5:$J$185,"NO APLICA") -> 122 | I19: =IFERROR((COUNTIFS(SEGUIMIENTO_PROYECTOS!$A$5:$A$185,DASHBOARD_KPIs!$E$3,SEGUIMIENTO_PROYECTOS!$J$5:$J$185,"OK")+COUNTIFS(SEGUIMIENTO_PROYECTOS!$A$5:$A$185,DASHBOARD_KPIs!$E$3,SEGUIMIENTO_PROYECTOS!$J$5:$J$185,"OK (falta firma)")*0.75+COUNTIFS(SEGUIMIENTO_PROYECTOS!$A$5:$A$185,DASHBOARD_KPIs!$E$3,SEGUIMIENTO_PROYECTOS!$J$5:$J$185,"EN PROCESO")*0.5)/(COUNTIFS(SEGUIMIENTO_PROYECTOS!$A$5:$A$185,DASHBOARD_KPIs!$E$3)-COUNTIFS(SEGUIMIENTO_PROYECTOS!$A$5:$A$185,DASHBOARD_KPIs!$E$3,SEGUIMIENTO_PROYECTOS!$J$5:$J$185,"NO APLICA")-COUNTIFS(SEGUIMIENTO_PROYECTOS!$A$5:$A$185,DASHBOARD_KPIs!$E$3,SEGUIMIENTO_PROYECTOS!$J$5:$J$185,"-")-COUNTIFS(SEGUIMIENTO_PROYECTOS!$A$5:$A$185,DASHBOARD_KPIs!$E$3,SEGUIMIENTO_PROYECTOS!$J$5:$J$185,"")),"") -> 0.39215686 | J19: =IFERROR(IF(I19>=0.9,"CONFORME",IF(I19>=0.5,"ALERTA","CRITICO")),"S/D") -> CRITICO
B20: ACTA DE CONFORMIDAD (ACS) | C20: =COUNTIFS(SEGUIMIENTO_PROYECTOS!$A$5:$A$185,DASHBOARD_KPIs!$E$3)-COUNTIFS(SEGUIMIENTO_PROYECTOS!$A$5:$A$185,DASHBOARD_KPIs!$E$3,SEGUIMIENTO_PROYECTOS!$K$5:$K$185,"NO APLICA")-COUNTIFS(SEGUIMIENTO_PROYECTOS!$A$5:$A$185,DASHBOARD_KPIs!$E$3,SEGUIMIENTO_PROYECTOS!$K$5:$K$185,"-")-COUNTIFS(SEGUIMIENTO_PROYECTOS!$A$5:$A$185,DASHBOARD_KPIs!$E$3,SEGUIMIENTO_PROYECTOS!$K$5:$K$185,"") -> 110 | D20: =COUNTIFS(SEGUIMIENTO_PROYECTOS!$A$5:$A$185,DASHBOARD_KPIs!$E$3,SEGUIMIENTO_PROYECTOS!$K$5:$K$185,"OK") -> 51 | E20: =COUNTIFS(SEGUIMIENTO_PROYECTOS!$A$5:$A$185,DASHBOARD_KPIs!$E$3,SEGUIMIENTO_PROYECTOS!$K$5:$K$185,"OK (falta firma)") -> 0 | F20: =COUNTIFS(SEGUIMIENTO_PROYECTOS!$A$5:$A$185,DASHBOARD_KPIs!$E$3,SEGUIMIENTO_PROYECTOS!$K$5:$K$185,"EN PROCESO") -> 0 | G20: =COUNTIFS(SEGUIMIENTO_PROYECTOS!$A$5:$A$185,DASHBOARD_KPIs!$E$3,SEGUIMIENTO_PROYECTOS!$K$5:$K$185,"PENDIENTE") -> 52 | H20: =COUNTIFS(SEGUIMIENTO_PROYECTOS!$A$5:$A$185,DASHBOARD_KPIs!$E$3,SEGUIMIENTO_PROYECTOS!$K$5:$K$185,"NO APLICA") -> 25 | I20: =IFERROR((COUNTIFS(SEGUIMIENTO_PROYECTOS!$A$5:$A$185,DASHBOARD_KPIs!$E$3,SEGUIMIENTO_PROYECTOS!$K$5:$K$185,"OK")+COUNTIFS(SEGUIMIENTO_PROYECTOS!$A$5:$A$185,DASHBOARD_KPIs!$E$3,SEGUIMIENTO_PROYECTOS!$K$5:$K$185,"OK (falta firma)")*0.75+COUNTIFS(SEGUIMIENTO_PROYECTOS!$A$5:$A$185,DASHBOARD_KPIs!$E$3,SEGUIMIENTO_PROYECTOS!$K$5:$K$185,"EN PROCESO")*0.5)/(COUNTIFS(SEGUIMIENTO_PROYECTOS!$A$5:$A$185,DASHBOARD_KPIs!$E$3)-COUNTIFS(SEGUIMIENTO_PROYECTOS!$A$5:$A$185,DASHBOARD_KPIs!$E$3,SEGUIMIENTO_PROYECTOS!$K$5:$K$185,"NO APLICA")-COUNTIFS(SEGUIMIENTO_PROYECTOS!$A$5:$A$185,DASHBOARD_KPIs!$E$3,SEGUIMIENTO_PROYECTOS!$K$5:$K$185,"-")-COUNTIFS(SEGUIMIENTO_PROYECTOS!$A$5:$A$185,DASHBOARD_KPIs!$E$3,SEGUIMIENTO_PROYECTOS!$K$5:$K$185,"")),"") -> 0.46363636 | J20: =IFERROR(IF(I20>=0.9,"CONFORME",IF(I20>=0.5,"ALERTA","CRITICO")),"S/D") -> CRITICO
B21: ACTUALIZACIÓN SERVIDOR | C21: =COUNTIFS(SEGUIMIENTO_PROYECTOS!$A$5:$A$185,DASHBOARD_KPIs!$E$3)-COUNTIFS(SEGUIMIENTO_PROYECTOS!$A$5:$A$185,DASHBOARD_KPIs!$E$3,SEGUIMIENTO_PROYECTOS!$L$5:$L$185,"NO APLICA")-COUNTIFS(SEGUIMIENTO_PROYECTOS!$A$5:$A$185,DASHBOARD_KPIs!$E$3,SEGUIMIENTO_PROYECTOS!$L$5:$L$185,"-")-COUNTIFS(SEGUIMIENTO_PROYECTOS!$A$5:$A$185,DASHBOARD_KPIs!$E$3,SEGUIMIENTO_PROYECTOS!$L$5:$L$185,"") -> 165 | D21: =COUNTIFS(SEGUIMIENTO_PROYECTOS!$A$5:$A$185,DASHBOARD_KPIs!$E$3,SEGUIMIENTO_PROYECTOS!$L$5:$L$185,"OK") -> 56 | E21: =COUNTIFS(SEGUIMIENTO_PROYECTOS!$A$5:$A$185,DASHBOARD_KPIs!$E$3,SEGUIMIENTO_PROYECTOS!$L$5:$L$185,"OK (falta firma)") -> 0 | F21: =COUNTIFS(SEGUIMIENTO_PROYECTOS!$A$5:$A$185,DASHBOARD_KPIs!$E$3,SEGUIMIENTO_PROYECTOS!$L$5:$L$185,"EN PROCESO") -> 8 | G21: =COUNTIFS(SEGUIMIENTO_PROYECTOS!$A$5:$A$185,DASHBOARD_KPIs!$E$3,SEGUIMIENTO_PROYECTOS!$L$5:$L$185,"PENDIENTE") -> 101 | H21: =COUNTIFS(SEGUIMIENTO_PROYECTOS!$A$5:$A$185,DASHBOARD_KPIs!$E$3,SEGUIMIENTO_PROYECTOS!$L$5:$L$185,"NO APLICA") -> 4 | I21: =IFERROR((COUNTIFS(SEGUIMIENTO_PROYECTOS!$A$5:$A$185,DASHBOARD_KPIs!$E$3,SEGUIMIENTO_PROYECTOS!$L$5:$L$185,"OK")+COUNTIFS(SEGUIMIENTO_PROYECTOS!$A$5:$A$185,DASHBOARD_KPIs!$E$3,SEGUIMIENTO_PROYECTOS!$L$5:$L$185,"OK (falta firma)")*0.75+COUNTIFS(SEGUIMIENTO_PROYECTOS!$A$5:$A$185,DASHBOARD_KPIs!$E$3,SEGUIMIENTO_PROYECTOS!$L$5:$L$185,"EN PROCESO")*0.5)/(COUNTIFS(SEGUIMIENTO_PROYECTOS!$A$5:$A$185,DASHBOARD_KPIs!$E$3)-COUNTIFS(SEGUIMIENTO_PROYECTOS!$A$5:$A$185,DASHBOARD_KPIs!$E$3,SEGUIMIENTO_PROYECTOS!$L$5:$L$185,"NO APLICA")-COUNTIFS(SEGUIMIENTO_PROYECTOS!$A$5:$A$185,DASHBOARD_KPIs!$E$3,SEGUIMIENTO_PROYECTOS!$L$5:$L$185,"-")-COUNTIFS(SEGUIMIENTO_PROYECTOS!$A$5:$A$185,DASHBOARD_KPIs!$E$3,SEGUIMIENTO_PROYECTOS!$L$5:$L$185,"")),"") -> 0.36363636 | J21: =IFERROR(IF(I21>=0.9,"CONFORME",IF(I21>=0.5,"ALERTA","CRITICO")),"S/D") -> CRITICO
B22: EVAL. SELECCIÓN PROV. / CCP | C22: =COUNTIFS(SEGUIMIENTO_PROYECTOS!$A$5:$A$185,DASHBOARD_KPIs!$E$3)-COUNTIFS(SEGUIMIENTO_PROYECTOS!$A$5:$A$185,DASHBOARD_KPIs!$E$3,SEGUIMIENTO_PROYECTOS!$M$5:$M$185,"NO APLICA")-COUNTIFS(SEGUIMIENTO_PROYECTOS!$A$5:$A$185,DASHBOARD_KPIs!$E$3,SEGUIMIENTO_PROYECTOS!$M$5:$M$185,"-")-COUNTIFS(SEGUIMIENTO_PROYECTOS!$A$5:$A$185,DASHBOARD_KPIs!$E$3,SEGUIMIENTO_PROYECTOS!$M$5:$M$185,"") -> 29 | D22: =COUNTIFS(SEGUIMIENTO_PROYECTOS!$A$5:$A$185,DASHBOARD_KPIs!$E$3,SEGUIMIENTO_PROYECTOS!$M$5:$M$185,"OK") -> 8 | E22: =COUNTIFS(SEGUIMIENTO_PROYECTOS!$A$5:$A$185,DASHBOARD_KPIs!$E$3,SEGUIMIENTO_PROYECTOS!$M$5:$M$185,"OK (falta firma)") -> 0 | F22: =COUNTIFS(SEGUIMIENTO_PROYECTOS!$A$5:$A$185,DASHBOARD_KPIs!$E$3,SEGUIMIENTO_PROYECTOS!$M$5:$M$185,"EN PROCESO") -> 1 | G22: =COUNTIFS(SEGUIMIENTO_PROYECTOS!$A$5:$A$185,DASHBOARD_KPIs!$E$3,SEGUIMIENTO_PROYECTOS!$M$5:$M$185,"PENDIENTE") -> 20 | H22: =COUNTIFS(SEGUIMIENTO_PROYECTOS!$A$5:$A$185,DASHBOARD_KPIs!$E$3,SEGUIMIENTO_PROYECTOS!$M$5:$M$185,"NO APLICA") -> 140 | I22: =IFERROR((COUNTIFS(SEGUIMIENTO_PROYECTOS!$A$5:$A$185,DASHBOARD_KPIs!$E$3,SEGUIMIENTO_PROYECTOS!$M$5:$M$185,"OK")+COUNTIFS(SEGUIMIENTO_PROYECTOS!$A$5:$A$185,DASHBOARD_KPIs!$E$3,SEGUIMIENTO_PROYECTOS!$M$5:$M$185,"OK (falta firma)")*0.75+COUNTIFS(SEGUIMIENTO_PROYECTOS!$A$5:$A$185,DASHBOARD_KPIs!$E$3,SEGUIMIENTO_PROYECTOS!$M$5:$M$185,"EN PROCESO")*0.5)/(COUNTIFS(SEGUIMIENTO_PROYECTOS!$A$5:$A$185,DASHBOARD_KPIs!$E$3)-COUNTIFS(SEGUIMIENTO_PROYECTOS!$A$5:$A$185,DASHBOARD_KPIs!$E$3,SEGUIMIENTO_PROYECTOS!$M$5:$M$185,"NO APLICA")-COUNTIFS(SEGUIMIENTO_PROYECTOS!$A$5:$A$185,DASHBOARD_KPIs!$E$3,SEGUIMIENTO_PROYECTOS!$M$5:$M$185,"-")-COUNTIFS(SEGUIMIENTO_PROYECTOS!$A$5:$A$185,DASHBOARD_KPIs!$E$3,SEGUIMIENTO_PROYECTOS!$M$5:$M$185,"")),"") -> 0.29310345 | J22: =IFERROR(IF(I22>=0.9,"CONFORME",IF(I22>=0.5,"ALERTA","CRITICO")),"S/D") -> CRITICO
B23: DESEMPEÑO PROV. (EPSP) | C23: =COUNTIFS(SEGUIMIENTO_PROYECTOS!$A$5:$A$185,DASHBOARD_KPIs!$E$3)-COUNTIFS(SEGUIMIENTO_PROYECTOS!$A$5:$A$185,DASHBOARD_KPIs!$E$3,SEGUIMIENTO_PROYECTOS!$N$5:$N$185,"NO APLICA")-COUNTIFS(SEGUIMIENTO_PROYECTOS!$A$5:$A$185,DASHBOARD_KPIs!$E$3,SEGUIMIENTO_PROYECTOS!$N$5:$N$185,"-")-COUNTIFS(SEGUIMIENTO_PROYECTOS!$A$5:$A$185,DASHBOARD_KPIs!$E$3,SEGUIMIENTO_PROYECTOS!$N$5:$N$185,"") -> 53 | D23: =COUNTIFS(SEGUIMIENTO_PROYECTOS!$A$5:$A$185,DASHBOARD_KPIs!$E$3,SEGUIMIENTO_PROYECTOS!$N$5:$N$185,"OK") -> 35 | E23: =COUNTIFS(SEGUIMIENTO_PROYECTOS!$A$5:$A$185,DASHBOARD_KPIs!$E$3,SEGUIMIENTO_PROYECTOS!$N$5:$N$185,"OK (falta firma)") -> 0 | F23: =COUNTIFS(SEGUIMIENTO_PROYECTOS!$A$5:$A$185,DASHBOARD_KPIs!$E$3,SEGUIMIENTO_PROYECTOS!$N$5:$N$185,"EN PROCESO") -> 0 | G23: =COUNTIFS(SEGUIMIENTO_PROYECTOS!$A$5:$A$185,DASHBOARD_KPIs!$E$3,SEGUIMIENTO_PROYECTOS!$N$5:$N$185,"PENDIENTE") -> 18 | H23: =COUNTIFS(SEGUIMIENTO_PROYECTOS!$A$5:$A$185,DASHBOARD_KPIs!$E$3,SEGUIMIENTO_PROYECTOS!$N$5:$N$185,"NO APLICA") -> 107 | I23: =IFERROR((COUNTIFS(SEGUIMIENTO_PROYECTOS!$A$5:$A$185,DASHBOARD_KPIs!$E$3,SEGUIMIENTO_PROYECTOS!$N$5:$N$185,"OK")+COUNTIFS(SEGUIMIENTO_PROYECTOS!$A$5:$A$185,DASHBOARD_KPIs!$E$3,SEGUIMIENTO_PROYECTOS!$N$5:$N$185,"OK (falta firma)")*0.75+COUNTIFS(SEGUIMIENTO_PROYECTOS!$A$5:$A$185,DASHBOARD_KPIs!$E$3,SEGUIMIENTO_PROYECTOS!$N$5:$N$185,"EN PROCESO")*0.5)/(COUNTIFS(SEGUIMIENTO_PROYECTOS!$A$5:$A$185,DASHBOARD_KPIs!$E$3)-COUNTIFS(SEGUIMIENTO_PROYECTOS!$A$5:$A$185,DASHBOARD_KPIs!$E$3,SEGUIMIENTO_PROYECTOS!$N$5:$N$185,"NO APLICA")-COUNTIFS(SEGUIMIENTO_PROYECTOS!$A$5:$A$185,DASHBOARD_KPIs!$E$3,SEGUIMIENTO_PROYECTOS!$N$5:$N$185,"-")-COUNTIFS(SEGUIMIENTO_PROYECTOS!$A$5:$A$185,DASHBOARD_KPIs!$E$3,SEGUIMIENTO_PROYECTOS!$N$5:$N$185,"")),"") -> 0.66037736 | J23: =IFERROR(IF(I23>=0.9,"CONFORME",IF(I23>=0.5,"ALERTA","CRITICO")),"S/D") -> ALERTA
B24: LECCIONES APRENDIDAS | C24: =COUNTIFS(SEGUIMIENTO_PROYECTOS!$A$5:$A$185,DASHBOARD_KPIs!$E$3)-COUNTIFS(SEGUIMIENTO_PROYECTOS!$A$5:$A$185,DASHBOARD_KPIs!$E$3,SEGUIMIENTO_PROYECTOS!$O$5:$O$185,"NO APLICA")-COUNTIFS(SEGUIMIENTO_PROYECTOS!$A$5:$A$185,DASHBOARD_KPIs!$E$3,SEGUIMIENTO_PROYECTOS!$O$5:$O$185,"-")-COUNTIFS(SEGUIMIENTO_PROYECTOS!$A$5:$A$185,DASHBOARD_KPIs!$E$3,SEGUIMIENTO_PROYECTOS!$O$5:$O$185,"") -> 36 | D24: =COUNTIFS(SEGUIMIENTO_PROYECTOS!$A$5:$A$185,DASHBOARD_KPIs!$E$3,SEGUIMIENTO_PROYECTOS!$O$5:$O$185,"OK") -> 13 | E24: =COUNTIFS(SEGUIMIENTO_PROYECTOS!$A$5:$A$185,DASHBOARD_KPIs!$E$3,SEGUIMIENTO_PROYECTOS!$O$5:$O$185,"OK (falta firma)") -> 0 | F24: =COUNTIFS(SEGUIMIENTO_PROYECTOS!$A$5:$A$185,DASHBOARD_KPIs!$E$3,SEGUIMIENTO_PROYECTOS!$O$5:$O$185,"EN PROCESO") -> 0 | G24: =COUNTIFS(SEGUIMIENTO_PROYECTOS!$A$5:$A$185,DASHBOARD_KPIs!$E$3,SEGUIMIENTO_PROYECTOS!$O$5:$O$185,"PENDIENTE") -> 23 | H24: =COUNTIFS(SEGUIMIENTO_PROYECTOS!$A$5:$A$185,DASHBOARD_KPIs!$E$3,SEGUIMIENTO_PROYECTOS!$O$5:$O$185,"NO APLICA") -> 123 | I24: =IFERROR((COUNTIFS(SEGUIMIENTO_PROYECTOS!$A$5:$A$185,DASHBOARD_KPIs!$E$3,SEGUIMIENTO_PROYECTOS!$O$5:$O$185,"OK")+COUNTIFS(SEGUIMIENTO_PROYECTOS!$A$5:$A$185,DASHBOARD_KPIs!$E$3,SEGUIMIENTO_PROYECTOS!$O$5:$O$185,"OK (falta firma)")*0.75+COUNTIFS(SEGUIMIENTO_PROYECTOS!$A$5:$A$185,DASHBOARD_KPIs!$E$3,SEGUIMIENTO_PROYECTOS!$O$5:$O$185,"EN PROCESO")*0.5)/(COUNTIFS(SEGUIMIENTO_PROYECTOS!$A$5:$A$185,DASHBOARD_KPIs!$E$3)-COUNTIFS(SEGUIMIENTO_PROYECTOS!$A$5:$A$185,DASHBOARD_KPIs!$E$3,SEGUIMIENTO_PROYECTOS!$O$5:$O$185,"NO APLICA")-COUNTIFS(SEGUIMIENTO_PROYECTOS!$A$5:$A$185,DASHBOARD_KPIs!$E$3,SEGUIMIENTO_PROYECTOS!$O$5:$O$185,"-")-COUNTIFS(SEGUIMIENTO_PROYECTOS!$A$5:$A$185,DASHBOARD_KPIs!$E$3,SEGUIMIENTO_PROYECTOS!$O$5:$O$185,"")),"") -> 0.36111111 | J24: =IFERROR(IF(I24>=0.9,"CONFORME",IF(I24>=0.5,"ALERTA","CRITICO")),"S/D") -> CRITICO
B25: REPORTES (RA) | C25: =COUNTIFS(SEGUIMIENTO_PROYECTOS!$A$5:$A$185,DASHBOARD_KPIs!$E$3)-COUNTIFS(SEGUIMIENTO_PROYECTOS!$A$5:$A$185,DASHBOARD_KPIs!$E$3,SEGUIMIENTO_PROYECTOS!$P$5:$P$185,"NO APLICA")-COUNTIFS(SEGUIMIENTO_PROYECTOS!$A$5:$A$185,DASHBOARD_KPIs!$E$3,SEGUIMIENTO_PROYECTOS!$P$5:$P$185,"-")-COUNTIFS(SEGUIMIENTO_PROYECTOS!$A$5:$A$185,DASHBOARD_KPIs!$E$3,SEGUIMIENTO_PROYECTOS!$P$5:$P$185,"") -> 116 | D25: =COUNTIFS(SEGUIMIENTO_PROYECTOS!$A$5:$A$185,DASHBOARD_KPIs!$E$3,SEGUIMIENTO_PROYECTOS!$P$5:$P$185,"OK") -> 92 | E25: =COUNTIFS(SEGUIMIENTO_PROYECTOS!$A$5:$A$185,DASHBOARD_KPIs!$E$3,SEGUIMIENTO_PROYECTOS!$P$5:$P$185,"OK (falta firma)") -> 0 | F25: =COUNTIFS(SEGUIMIENTO_PROYECTOS!$A$5:$A$185,DASHBOARD_KPIs!$E$3,SEGUIMIENTO_PROYECTOS!$P$5:$P$185,"EN PROCESO") -> 0 | G25: =COUNTIFS(SEGUIMIENTO_PROYECTOS!$A$5:$A$185,DASHBOARD_KPIs!$E$3,SEGUIMIENTO_PROYECTOS!$P$5:$P$185,"PENDIENTE") -> 24 | H25: =COUNTIFS(SEGUIMIENTO_PROYECTOS!$A$5:$A$185,DASHBOARD_KPIs!$E$3,SEGUIMIENTO_PROYECTOS!$P$5:$P$185,"NO APLICA") -> 52 | I25: =IFERROR((COUNTIFS(SEGUIMIENTO_PROYECTOS!$A$5:$A$185,DASHBOARD_KPIs!$E$3,SEGUIMIENTO_PROYECTOS!$P$5:$P$185,"OK")+COUNTIFS(SEGUIMIENTO_PROYECTOS!$A$5:$A$185,DASHBOARD_KPIs!$E$3,SEGUIMIENTO_PROYECTOS!$P$5:$P$185,"OK (falta firma)")*0.75+COUNTIFS(SEGUIMIENTO_PROYECTOS!$A$5:$A$185,DASHBOARD_KPIs!$E$3,SEGUIMIENTO_PROYECTOS!$P$5:$P$185,"EN PROCESO")*0.5)/(COUNTIFS(SEGUIMIENTO_PROYECTOS!$A$5:$A$185,DASHBOARD_KPIs!$E$3)-COUNTIFS(SEGUIMIENTO_PROYECTOS!$A$5:$A$185,DASHBOARD_KPIs!$E$3,SEGUIMIENTO_PROYECTOS!$P$5:$P$185,"NO APLICA")-COUNTIFS(SEGUIMIENTO_PROYECTOS!$A$5:$A$185,DASHBOARD_KPIs!$E$3,SEGUIMIENTO_PROYECTOS!$P$5:$P$185,"-")-COUNTIFS(SEGUIMIENTO_PROYECTOS!$A$5:$A$185,DASHBOARD_KPIs!$E$3,SEGUIMIENTO_PROYECTOS!$P$5:$P$185,"")),"") -> 0.79310345 | J25: =IFERROR(IF(I25>=0.9,"CONFORME",IF(I25>=0.5,"ALERTA","CRITICO")),"S/D") -> ALERTA
B26: ACTAS DE REUNIÓN | C26: =COUNTIFS(SEGUIMIENTO_PROYECTOS!$A$5:$A$185,DASHBOARD_KPIs!$E$3)-COUNTIFS(SEGUIMIENTO_PROYECTOS!$A$5:$A$185,DASHBOARD_KPIs!$E$3,SEGUIMIENTO_PROYECTOS!$Q$5:$Q$185,"NO APLICA")-COUNTIFS(SEGUIMIENTO_PROYECTOS!$A$5:$A$185,DASHBOARD_KPIs!$E$3,SEGUIMIENTO_PROYECTOS!$Q$5:$Q$185,"-")-COUNTIFS(SEGUIMIENTO_PROYECTOS!$A$5:$A$185,DASHBOARD_KPIs!$E$3,SEGUIMIENTO_PROYECTOS!$Q$5:$Q$185,"") -> 64 | D26: =COUNTIFS(SEGUIMIENTO_PROYECTOS!$A$5:$A$185,DASHBOARD_KPIs!$E$3,SEGUIMIENTO_PROYECTOS!$Q$5:$Q$185,"OK") -> 51 | E26: =COUNTIFS(SEGUIMIENTO_PROYECTOS!$A$5:$A$185,DASHBOARD_KPIs!$E$3,SEGUIMIENTO_PROYECTOS!$Q$5:$Q$185,"OK (falta firma)") -> 0 | F26: =COUNTIFS(SEGUIMIENTO_PROYECTOS!$A$5:$A$185,DASHBOARD_KPIs!$E$3,SEGUIMIENTO_PROYECTOS!$Q$5:$Q$185,"EN PROCESO") -> 0 | G26: =COUNTIFS(SEGUIMIENTO_PROYECTOS!$A$5:$A$185,DASHBOARD_KPIs!$E$3,SEGUIMIENTO_PROYECTOS!$Q$5:$Q$185,"PENDIENTE") -> 13 | H26: =COUNTIFS(SEGUIMIENTO_PROYECTOS!$A$5:$A$185,DASHBOARD_KPIs!$E$3,SEGUIMIENTO_PROYECTOS!$Q$5:$Q$185,"NO APLICA") -> 105 | I26: =IFERROR((COUNTIFS(SEGUIMIENTO_PROYECTOS!$A$5:$A$185,DASHBOARD_KPIs!$E$3,SEGUIMIENTO_PROYECTOS!$Q$5:$Q$185,"OK")+COUNTIFS(SEGUIMIENTO_PROYECTOS!$A$5:$A$185,DASHBOARD_KPIs!$E$3,SEGUIMIENTO_PROYECTOS!$Q$5:$Q$185,"OK (falta firma)")*0.75+COUNTIFS(SEGUIMIENTO_PROYECTOS!$A$5:$A$185,DASHBOARD_KPIs!$E$3,SEGUIMIENTO_PROYECTOS!$Q$5:$Q$185,"EN PROCESO")*0.5)/(COUNTIFS(SEGUIMIENTO_PROYECTOS!$A$5:$A$185,DASHBOARD_KPIs!$E$3)-COUNTIFS(SEGUIMIENTO_PROYECTOS!$A$5:$A$185,DASHBOARD_KPIs!$E$3,SEGUIMIENTO_PROYECTOS!$Q$5:$Q$185,"NO APLICA")-COUNTIFS(SEGUIMIENTO_PROYECTOS!$A$5:$A$185,DASHBOARD_KPIs!$E$3,SEGUIMIENTO_PROYECTOS!$Q$5:$Q$185,"-")-COUNTIFS(SEGUIMIENTO_PROYECTOS!$A$5:$A$185,DASHBOARD_KPIs!$E$3,SEGUIMIENTO_PROYECTOS!$Q$5:$Q$185,"")),"") -> 0.796875 | J26: =IFERROR(IF(I26>=0.9,"CONFORME",IF(I26>=0.5,"ALERTA","CRITICO")),"S/D") -> ALERTA
B28: 👤 CUMPLIMIENTO POR RESPONSABLE — JEFE DE PROYECTO
B29: RESPONSABLE | C29: ACTIVOS | D29: CONFORME | E29: ALERTA | F29: CRITICO | G29: CERRADOS | H29: STAND BY | I29: % SIG PROM.
B30: A. Ferrer | C30: =COUNTIFS(SEGUIMIENTO_PROYECTOS!$A$5:$A$185,DASHBOARD_KPIs!$E$3,SEGUIMIENTO_PROYECTOS!$H$5:$H$185,"A. Ferrer")-COUNTIFS(SEGUIMIENTO_PROYECTOS!$A$5:$A$185,DASHBOARD_KPIs!$E$3,SEGUIMIENTO_PROYECTOS!$H$5:$H$185,"A. Ferrer",SEGUIMIENTO_PROYECTOS!$F$5:$F$185,"CERRADO")-COUNTIFS(SEGUIMIENTO_PROYECTOS!$A$5:$A$185,DASHBOARD_KPIs!$E$3,SEGUIMIENTO_PROYECTOS!$H$5:$H$185,"A. Ferrer",SEGUIMIENTO_PROYECTOS!$F$5:$F$185,"CANCELADO")-COUNTIFS(SEGUIMIENTO_PROYECTOS!$A$5:$A$185,DASHBOARD_KPIs!$E$3,SEGUIMIENTO_PROYECTOS!$H$5:$H$185,"A. Ferrer",SEGUIMIENTO_PROYECTOS!$F$5:$F$185,"DESCARTADO") -> 6 | D30: =COUNTIFS(SEGUIMIENTO_PROYECTOS!$A$5:$A$185,DASHBOARD_KPIs!$E$3,SEGUIMIENTO_PROYECTOS!$H$5:$H$185,"A. Ferrer",SEGUIMIENTO_PROYECTOS!$W$5:$W$185,"CONFORME") -> 0 | E30: =COUNTIFS(SEGUIMIENTO_PROYECTOS!$A$5:$A$185,DASHBOARD_KPIs!$E$3,SEGUIMIENTO_PROYECTOS!$H$5:$H$185,"A. Ferrer",SEGUIMIENTO_PROYECTOS!$W$5:$W$185,"ALERTA") -> 5 | F30: =COUNTIFS(SEGUIMIENTO_PROYECTOS!$A$5:$A$185,DASHBOARD_KPIs!$E$3,SEGUIMIENTO_PROYECTOS!$H$5:$H$185,"A. Ferrer",SEGUIMIENTO_PROYECTOS!$W$5:$W$185,"CRITICO") -> 7 | G30: =COUNTIFS(SEGUIMIENTO_PROYECTOS!$A$5:$A$185,DASHBOARD_KPIs!$E$3,SEGUIMIENTO_PROYECTOS!$H$5:$H$185,"A. Ferrer",SEGUIMIENTO_PROYECTOS!$F$5:$F$185,"CERRADO") -> 6 | H30: =COUNTIFS(SEGUIMIENTO_PROYECTOS!$A$5:$A$185,DASHBOARD_KPIs!$E$3,SEGUIMIENTO_PROYECTOS!$H$5:$H$185,"A. Ferrer",SEGUIMIENTO_PROYECTOS!$W$5:$W$185,"STAND BY") -> 0 | I30: =IFERROR(SUMIFS(SEGUIMIENTO_PROYECTOS!$Y$5:$Y$185,SEGUIMIENTO_PROYECTOS!$A$5:$A$185,DASHBOARD_KPIs!$E$3,SEGUIMIENTO_PROYECTOS!$H$5:$H$185,"A. Ferrer")/SUMIFS(SEGUIMIENTO_PROYECTOS!$X$5:$X$185,SEGUIMIENTO_PROYECTOS!$A$5:$A$185,DASHBOARD_KPIs!$E$3,SEGUIMIENTO_PROYECTOS!$H$5:$H$185,"A. Ferrer"),"—") -> 0.40769231
B31: B. López | C31: =COUNTIFS(SEGUIMIENTO_PROYECTOS!$A$5:$A$185,DASHBOARD_KPIs!$E$3,SEGUIMIENTO_PROYECTOS!$H$5:$H$185,"B. López")-COUNTIFS(SEGUIMIENTO_PROYECTOS!$A$5:$A$185,DASHBOARD_KPIs!$E$3,SEGUIMIENTO_PROYECTOS!$H$5:$H$185,"B. López",SEGUIMIENTO_PROYECTOS!$F$5:$F$185,"CERRADO")-COUNTIFS(SEGUIMIENTO_PROYECTOS!$A$5:$A$185,DASHBOARD_KPIs!$E$3,SEGUIMIENTO_PROYECTOS!$H$5:$H$185,"B. López",SEGUIMIENTO_PROYECTOS!$F$5:$F$185,"CANCELADO")-COUNTIFS(SEGUIMIENTO_PROYECTOS!$A$5:$A$185,DASHBOARD_KPIs!$E$3,SEGUIMIENTO_PROYECTOS!$H$5:$H$185,"B. López",SEGUIMIENTO_PROYECTOS!$F$5:$F$185,"DESCARTADO") -> 13 | D31: =COUNTIFS(SEGUIMIENTO_PROYECTOS!$A$5:$A$185,DASHBOARD_KPIs!$E$3,SEGUIMIENTO_PROYECTOS!$H$5:$H$185,"B. López",SEGUIMIENTO_PROYECTOS!$W$5:$W$185,"CONFORME") -> 3 | E31: =COUNTIFS(SEGUIMIENTO_PROYECTOS!$A$5:$A$185,DASHBOARD_KPIs!$E$3,SEGUIMIENTO_PROYECTOS!$H$5:$H$185,"B. López",SEGUIMIENTO_PROYECTOS!$W$5:$W$185,"ALERTA") -> 13 | F31: =COUNTIFS(SEGUIMIENTO_PROYECTOS!$A$5:$A$185,DASHBOARD_KPIs!$E$3,SEGUIMIENTO_PROYECTOS!$H$5:$H$185,"B. López",SEGUIMIENTO_PROYECTOS!$W$5:$W$185,"CRITICO") -> 11 | G31: =COUNTIFS(SEGUIMIENTO_PROYECTOS!$A$5:$A$185,DASHBOARD_KPIs!$E$3,SEGUIMIENTO_PROYECTOS!$H$5:$H$185,"B. López",SEGUIMIENTO_PROYECTOS!$F$5:$F$185,"CERRADO") -> 16 | H31: =COUNTIFS(SEGUIMIENTO_PROYECTOS!$A$5:$A$185,DASHBOARD_KPIs!$E$3,SEGUIMIENTO_PROYECTOS!$H$5:$H$185,"B. López",SEGUIMIENTO_PROYECTOS!$W$5:$W$185,"STAND BY") -> 0 | I31: =IFERROR(SUMIFS(SEGUIMIENTO_PROYECTOS!$Y$5:$Y$185,SEGUIMIENTO_PROYECTOS!$A$5:$A$185,DASHBOARD_KPIs!$E$3,SEGUIMIENTO_PROYECTOS!$H$5:$H$185,"B. López")/SUMIFS(SEGUIMIENTO_PROYECTOS!$X$5:$X$185,SEGUIMIENTO_PROYECTOS!$A$5:$A$185,DASHBOARD_KPIs!$E$3,SEGUIMIENTO_PROYECTOS!$H$5:$H$185,"B. López"),"—") -> 0.48275862
B32: C. Castillo | C32: =COUNTIFS(SEGUIMIENTO_PROYECTOS!$A$5:$A$185,DASHBOARD_KPIs!$E$3,SEGUIMIENTO_PROYECTOS!$H$5:$H$185,"C. Castillo")-COUNTIFS(SEGUIMIENTO_PROYECTOS!$A$5:$A$185,DASHBOARD_KPIs!$E$3,SEGUIMIENTO_PROYECTOS!$H$5:$H$185,"C. Castillo",SEGUIMIENTO_PROYECTOS!$F$5:$F$185,"CERRADO")-COUNTIFS(SEGUIMIENTO_PROYECTOS!$A$5:$A$185,DASHBOARD_KPIs!$E$3,SEGUIMIENTO_PROYECTOS!$H$5:$H$185,"C. Castillo",SEGUIMIENTO_PROYECTOS!$F$5:$F$185,"CANCELADO")-COUNTIFS(SEGUIMIENTO_PROYECTOS!$A$5:$A$185,DASHBOARD_KPIs!$E$3,SEGUIMIENTO_PROYECTOS!$H$5:$H$185,"C. Castillo",SEGUIMIENTO_PROYECTOS!$F$5:$F$185,"DESCARTADO") -> 1 | D32: =COUNTIFS(SEGUIMIENTO_PROYECTOS!$A$5:$A$185,DASHBOARD_KPIs!$E$3,SEGUIMIENTO_PROYECTOS!$H$5:$H$185,"C. Castillo",SEGUIMIENTO_PROYECTOS!$W$5:$W$185,"CONFORME") -> 10 | E32: =COUNTIFS(SEGUIMIENTO_PROYECTOS!$A$5:$A$185,DASHBOARD_KPIs!$E$3,SEGUIMIENTO_PROYECTOS!$H$5:$H$185,"C. Castillo",SEGUIMIENTO_PROYECTOS!$W$5:$W$185,"ALERTA") -> 1 | F32: =COUNTIFS(SEGUIMIENTO_PROYECTOS!$A$5:$A$185,DASHBOARD_KPIs!$E$3,SEGUIMIENTO_PROYECTOS!$H$5:$H$185,"C. Castillo",SEGUIMIENTO_PROYECTOS!$W$5:$W$185,"CRITICO") -> 0 | G32: =COUNTIFS(SEGUIMIENTO_PROYECTOS!$A$5:$A$185,DASHBOARD_KPIs!$E$3,SEGUIMIENTO_PROYECTOS!$H$5:$H$185,"C. Castillo",SEGUIMIENTO_PROYECTOS!$F$5:$F$185,"CERRADO") -> 11 | H32: =COUNTIFS(SEGUIMIENTO_PROYECTOS!$A$5:$A$185,DASHBOARD_KPIs!$E$3,SEGUIMIENTO_PROYECTOS!$H$5:$H$185,"C. Castillo",SEGUIMIENTO_PROYECTOS!$W$5:$W$185,"STAND BY") -> 0 | I32: =IFERROR(SUMIFS(SEGUIMIENTO_PROYECTOS!$Y$5:$Y$185,SEGUIMIENTO_PROYECTOS!$A$5:$A$185,DASHBOARD_KPIs!$E$3,SEGUIMIENTO_PROYECTOS!$H$5:$H$185,"C. Castillo")/SUMIFS(SEGUIMIENTO_PROYECTOS!$X$5:$X$185,SEGUIMIENTO_PROYECTOS!$A$5:$A$185,DASHBOARD_KPIs!$E$3,SEGUIMIENTO_PROYECTOS!$H$5:$H$185,"C. Castillo"),"—") -> 0.98333333
B33: C. Castillo / Michael Gómez | C33: =COUNTIFS(SEGUIMIENTO_PROYECTOS!$A$5:$A$185,DASHBOARD_KPIs!$E$3,SEGUIMIENTO_PROYECTOS!$H$5:$H$185,"C. Castillo / Michael Gómez")-COUNTIFS(SEGUIMIENTO_PROYECTOS!$A$5:$A$185,DASHBOARD_KPIs!$E$3,SEGUIMIENTO_PROYECTOS!$H$5:$H$185,"C. Castillo / Michael Gómez",SEGUIMIENTO_PROYECTOS!$F$5:$F$185,"CERRADO")-COUNTIFS(SEGUIMIENTO_PROYECTOS!$A$5:$A$185,DASHBOARD_KPIs!$E$3,SEGUIMIENTO_PROYECTOS!$H$5:$H$185,"C. Castillo / Michael Gómez",SEGUIMIENTO_PROYECTOS!$F$5:$F$185,"CANCELADO")-COUNTIFS(SEGUIMIENTO_PROYECTOS!$A$5:$A$185,DASHBOARD_KPIs!$E$3,SEGUIMIENTO_PROYECTOS!$H$5:$H$185,"C. Castillo / Michael Gómez",SEGUIMIENTO_PROYECTOS!$F$5:$F$185,"DESCARTADO") -> 0 | D33: =COUNTIFS(SEGUIMIENTO_PROYECTOS!$A$5:$A$185,DASHBOARD_KPIs!$E$3,SEGUIMIENTO_PROYECTOS!$H$5:$H$185,"C. Castillo / Michael Gómez",SEGUIMIENTO_PROYECTOS!$W$5:$W$185,"CONFORME") -> 3 | E33: =COUNTIFS(SEGUIMIENTO_PROYECTOS!$A$5:$A$185,DASHBOARD_KPIs!$E$3,SEGUIMIENTO_PROYECTOS!$H$5:$H$185,"C. Castillo / Michael Gómez",SEGUIMIENTO_PROYECTOS!$W$5:$W$185,"ALERTA") -> 3 | F33: =COUNTIFS(SEGUIMIENTO_PROYECTOS!$A$5:$A$185,DASHBOARD_KPIs!$E$3,SEGUIMIENTO_PROYECTOS!$H$5:$H$185,"C. Castillo / Michael Gómez",SEGUIMIENTO_PROYECTOS!$W$5:$W$185,"CRITICO") -> 0 | G33: =COUNTIFS(SEGUIMIENTO_PROYECTOS!$A$5:$A$185,DASHBOARD_KPIs!$E$3,SEGUIMIENTO_PROYECTOS!$H$5:$H$185,"C. Castillo / Michael Gómez",SEGUIMIENTO_PROYECTOS!$F$5:$F$185,"CERRADO") -> 6 | H33: =COUNTIFS(SEGUIMIENTO_PROYECTOS!$A$5:$A$185,DASHBOARD_KPIs!$E$3,SEGUIMIENTO_PROYECTOS!$H$5:$H$185,"C. Castillo / Michael Gómez",SEGUIMIENTO_PROYECTOS!$W$5:$W$185,"STAND BY") -> 0 | I33: =IFERROR(SUMIFS(SEGUIMIENTO_PROYECTOS!$Y$5:$Y$185,SEGUIMIENTO_PROYECTOS!$A$5:$A$185,DASHBOARD_KPIs!$E$3,SEGUIMIENTO_PROYECTOS!$H$5:$H$185,"C. Castillo / Michael Gómez")/SUMIFS(SEGUIMIENTO_PROYECTOS!$X$5:$X$185,SEGUIMIENTO_PROYECTOS!$A$5:$A$185,DASHBOARD_KPIs!$E$3,SEGUIMIENTO_PROYECTOS!$H$5:$H$185,"C. Castillo / Michael Gómez"),"—") -> 0.83333333
B34: C. Valdizán | C34: =COUNTIFS(SEGUIMIENTO_PROYECTOS!$A$5:$A$185,DASHBOARD_KPIs!$E$3,SEGUIMIENTO_PROYECTOS!$H$5:$H$185,"C. Valdizán")-COUNTIFS(SEGUIMIENTO_PROYECTOS!$A$5:$A$185,DASHBOARD_KPIs!$E$3,SEGUIMIENTO_PROYECTOS!$H$5:$H$185,"C. Valdizán",SEGUIMIENTO_PROYECTOS!$F$5:$F$185,"CERRADO")-COUNTIFS(SEGUIMIENTO_PROYECTOS!$A$5:$A$185,DASHBOARD_KPIs!$E$3,SEGUIMIENTO_PROYECTOS!$H$5:$H$185,"C. Valdizán",SEGUIMIENTO_PROYECTOS!$F$5:$F$185,"CANCELADO")-COUNTIFS(SEGUIMIENTO_PROYECTOS!$A$5:$A$185,DASHBOARD_KPIs!$E$3,SEGUIMIENTO_PROYECTOS!$H$5:$H$185,"C. Valdizán",SEGUIMIENTO_PROYECTOS!$F$5:$F$185,"DESCARTADO") -> 0 | D34: =COUNTIFS(SEGUIMIENTO_PROYECTOS!$A$5:$A$185,DASHBOARD_KPIs!$E$3,SEGUIMIENTO_PROYECTOS!$H$5:$H$185,"C. Valdizán",SEGUIMIENTO_PROYECTOS!$W$5:$W$185,"CONFORME") -> 1 | E34: =COUNTIFS(SEGUIMIENTO_PROYECTOS!$A$5:$A$185,DASHBOARD_KPIs!$E$3,SEGUIMIENTO_PROYECTOS!$H$5:$H$185,"C. Valdizán",SEGUIMIENTO_PROYECTOS!$W$5:$W$185,"ALERTA") -> 0 | F34: =COUNTIFS(SEGUIMIENTO_PROYECTOS!$A$5:$A$185,DASHBOARD_KPIs!$E$3,SEGUIMIENTO_PROYECTOS!$H$5:$H$185,"C. Valdizán",SEGUIMIENTO_PROYECTOS!$W$5:$W$185,"CRITICO") -> 1 | G34: =COUNTIFS(SEGUIMIENTO_PROYECTOS!$A$5:$A$185,DASHBOARD_KPIs!$E$3,SEGUIMIENTO_PROYECTOS!$H$5:$H$185,"C. Valdizán",SEGUIMIENTO_PROYECTOS!$F$5:$F$185,"CERRADO") -> 2 | H34: =COUNTIFS(SEGUIMIENTO_PROYECTOS!$A$5:$A$185,DASHBOARD_KPIs!$E$3,SEGUIMIENTO_PROYECTOS!$H$5:$H$185,"C. Valdizán",SEGUIMIENTO_PROYECTOS!$W$5:$W$185,"STAND BY") -> 0 | I34: =IFERROR(SUMIFS(SEGUIMIENTO_PROYECTOS!$Y$5:$Y$185,SEGUIMIENTO_PROYECTOS!$A$5:$A$185,DASHBOARD_KPIs!$E$3,SEGUIMIENTO_PROYECTOS!$H$5:$H$185,"C. Valdizán")/SUMIFS(SEGUIMIENTO_PROYECTOS!$X$5:$X$185,SEGUIMIENTO_PROYECTOS!$A$5:$A$185,DASHBOARD_KPIs!$E$3,SEGUIMIENTO_PROYECTOS!$H$5:$H$185,"C. Valdizán"),"—") -> 0.71428571
B35: F. Choque | C35: =COUNTIFS(SEGUIMIENTO_PROYECTOS!$A$5:$A$185,DASHBOARD_KPIs!$E$3,SEGUIMIENTO_PROYECTOS!$H$5:$H$185,"F. Choque")-COUNTIFS(SEGUIMIENTO_PROYECTOS!$A$5:$A$185,DASHBOARD_KPIs!$E$3,SEGUIMIENTO_PROYECTOS!$H$5:$H$185,"F. Choque",SEGUIMIENTO_PROYECTOS!$F$5:$F$185,"CERRADO")-COUNTIFS(SEGUIMIENTO_PROYECTOS!$A$5:$A$185,DASHBOARD_KPIs!$E$3,SEGUIMIENTO_PROYECTOS!$H$5:$H$185,"F. Choque",SEGUIMIENTO_PROYECTOS!$F$5:$F$185,"CANCELADO")-COUNTIFS(SEGUIMIENTO_PROYECTOS!$A$5:$A$185,DASHBOARD_KPIs!$E$3,SEGUIMIENTO_PROYECTOS!$H$5:$H$185,"F. Choque",SEGUIMIENTO_PROYECTOS!$F$5:$F$185,"DESCARTADO") -> 13 | D35: =COUNTIFS(SEGUIMIENTO_PROYECTOS!$A$5:$A$185,DASHBOARD_KPIs!$E$3,SEGUIMIENTO_PROYECTOS!$H$5:$H$185,"F. Choque",SEGUIMIENTO_PROYECTOS!$W$5:$W$185,"CONFORME") -> 7 | E35: =COUNTIFS(SEGUIMIENTO_PROYECTOS!$A$5:$A$185,DASHBOARD_KPIs!$E$3,SEGUIMIENTO_PROYECTOS!$H$5:$H$185,"F. Choque",SEGUIMIENTO_PROYECTOS!$W$5:$W$185,"ALERTA") -> 28 | F35: =COUNTIFS(SEGUIMIENTO_PROYECTOS!$A$5:$A$185,DASHBOARD_KPIs!$E$3,SEGUIMIENTO_PROYECTOS!$H$5:$H$185,"F. Choque",SEGUIMIENTO_PROYECTOS!$W$5:$W$185,"CRITICO") -> 13 | G35: =COUNTIFS(SEGUIMIENTO_PROYECTOS!$A$5:$A$185,DASHBOARD_KPIs!$E$3,SEGUIMIENTO_PROYECTOS!$H$5:$H$185,"F. Choque",SEGUIMIENTO_PROYECTOS!$F$5:$F$185,"CERRADO") -> 35 | H35: =COUNTIFS(SEGUIMIENTO_PROYECTOS!$A$5:$A$185,DASHBOARD_KPIs!$E$3,SEGUIMIENTO_PROYECTOS!$H$5:$H$185,"F. Choque",SEGUIMIENTO_PROYECTOS!$W$5:$W$185,"STAND BY") -> 0 | I35: =IFERROR(SUMIFS(SEGUIMIENTO_PROYECTOS!$Y$5:$Y$185,SEGUIMIENTO_PROYECTOS!$A$5:$A$185,DASHBOARD_KPIs!$E$3,SEGUIMIENTO_PROYECTOS!$H$5:$H$185,"F. Choque")/SUMIFS(SEGUIMIENTO_PROYECTOS!$X$5:$X$185,SEGUIMIENTO_PROYECTOS!$A$5:$A$185,DASHBOARD_KPIs!$E$3,SEGUIMIENTO_PROYECTOS!$H$5:$H$185,"F. Choque"),"—") -> 0.58809524
B36: F. Corvera | C36: =COUNTIFS(SEGUIMIENTO_PROYECTOS!$A$5:$A$185,DASHBOARD_KPIs!$E$3,SEGUIMIENTO_PROYECTOS!$H$5:$H$185,"F. Corvera")-COUNTIFS(SEGUIMIENTO_PROYECTOS!$A$5:$A$185,DASHBOARD_KPIs!$E$3,SEGUIMIENTO_PROYECTOS!$H$5:$H$185,"F. Corvera",SEGUIMIENTO_PROYECTOS!$F$5:$F$185,"CERRADO")-COUNTIFS(SEGUIMIENTO_PROYECTOS!$A$5:$A$185,DASHBOARD_KPIs!$E$3,SEGUIMIENTO_PROYECTOS!$H$5:$H$185,"F. Corvera",SEGUIMIENTO_PROYECTOS!$F$5:$F$185,"CANCELADO")-COUNTIFS(SEGUIMIENTO_PROYECTOS!$A$5:$A$185,DASHBOARD_KPIs!$E$3,SEGUIMIENTO_PROYECTOS!$H$5:$H$185,"F. Corvera",SEGUIMIENTO_PROYECTOS!$F$5:$F$185,"DESCARTADO") -> 0 | D36: =COUNTIFS(SEGUIMIENTO_PROYECTOS!$A$5:$A$185,DASHBOARD_KPIs!$E$3,SEGUIMIENTO_PROYECTOS!$H$5:$H$185,"F. Corvera",SEGUIMIENTO_PROYECTOS!$W$5:$W$185,"CONFORME") -> 0 | E36: =COUNTIFS(SEGUIMIENTO_PROYECTOS!$A$5:$A$185,DASHBOARD_KPIs!$E$3,SEGUIMIENTO_PROYECTOS!$H$5:$H$185,"F. Corvera",SEGUIMIENTO_PROYECTOS!$W$5:$W$185,"ALERTA") -> 1 | F36: =COUNTIFS(SEGUIMIENTO_PROYECTOS!$A$5:$A$185,DASHBOARD_KPIs!$E$3,SEGUIMIENTO_PROYECTOS!$H$5:$H$185,"F. Corvera",SEGUIMIENTO_PROYECTOS!$W$5:$W$185,"CRITICO") -> 1 | G36: =COUNTIFS(SEGUIMIENTO_PROYECTOS!$A$5:$A$185,DASHBOARD_KPIs!$E$3,SEGUIMIENTO_PROYECTOS!$H$5:$H$185,"F. Corvera",SEGUIMIENTO_PROYECTOS!$F$5:$F$185,"CERRADO") -> 2 | H36: =COUNTIFS(SEGUIMIENTO_PROYECTOS!$A$5:$A$185,DASHBOARD_KPIs!$E$3,SEGUIMIENTO_PROYECTOS!$H$5:$H$185,"F. Corvera",SEGUIMIENTO_PROYECTOS!$W$5:$W$185,"STAND BY") -> 0 | I36: =IFERROR(SUMIFS(SEGUIMIENTO_PROYECTOS!$Y$5:$Y$185,SEGUIMIENTO_PROYECTOS!$A$5:$A$185,DASHBOARD_KPIs!$E$3,SEGUIMIENTO_PROYECTOS!$H$5:$H$185,"F. Corvera")/SUMIFS(SEGUIMIENTO_PROYECTOS!$X$5:$X$185,SEGUIMIENTO_PROYECTOS!$A$5:$A$185,DASHBOARD_KPIs!$E$3,SEGUIMIENTO_PROYECTOS!$H$5:$H$185,"F. Corvera"),"—") -> 0.36363636
B37: F. Corvera / (Revisión) | C37: =COUNTIFS(SEGUIMIENTO_PROYECTOS!$A$5:$A$185,DASHBOARD_KPIs!$E$3,SEGUIMIENTO_PROYECTOS!$H$5:$H$185,"F. Corvera / (Revisión)")-COUNTIFS(SEGUIMIENTO_PROYECTOS!$A$5:$A$185,DASHBOARD_KPIs!$E$3,SEGUIMIENTO_PROYECTOS!$H$5:$H$185,"F. Corvera / (Revisión)",SEGUIMIENTO_PROYECTOS!$F$5:$F$185,"CERRADO")-COUNTIFS(SEGUIMIENTO_PROYECTOS!$A$5:$A$185,DASHBOARD_KPIs!$E$3,SEGUIMIENTO_PROYECTOS!$H$5:$H$185,"F. Corvera / (Revisión)",SEGUIMIENTO_PROYECTOS!$F$5:$F$185,"CANCELADO")-COUNTIFS(SEGUIMIENTO_PROYECTOS!$A$5:$A$185,DASHBOARD_KPIs!$E$3,SEGUIMIENTO_PROYECTOS!$H$5:$H$185,"F. Corvera / (Revisión)",SEGUIMIENTO_PROYECTOS!$F$5:$F$185,"DESCARTADO") -> 0 | D37: =COUNTIFS(SEGUIMIENTO_PROYECTOS!$A$5:$A$185,DASHBOARD_KPIs!$E$3,SEGUIMIENTO_PROYECTOS!$H$5:$H$185,"F. Corvera / (Revisión)",SEGUIMIENTO_PROYECTOS!$W$5:$W$185,"CONFORME") -> 0 | E37: =COUNTIFS(SEGUIMIENTO_PROYECTOS!$A$5:$A$185,DASHBOARD_KPIs!$E$3,SEGUIMIENTO_PROYECTOS!$H$5:$H$185,"F. Corvera / (Revisión)",SEGUIMIENTO_PROYECTOS!$W$5:$W$185,"ALERTA") -> 1 | F37: =COUNTIFS(SEGUIMIENTO_PROYECTOS!$A$5:$A$185,DASHBOARD_KPIs!$E$3,SEGUIMIENTO_PROYECTOS!$H$5:$H$185,"F. Corvera / (Revisión)",SEGUIMIENTO_PROYECTOS!$W$5:$W$185,"CRITICO") -> 1 | G37: =COUNTIFS(SEGUIMIENTO_PROYECTOS!$A$5:$A$185,DASHBOARD_KPIs!$E$3,SEGUIMIENTO_PROYECTOS!$H$5:$H$185,"F. Corvera / (Revisión)",SEGUIMIENTO_PROYECTOS!$F$5:$F$185,"CERRADO") -> 2 | H37: =COUNTIFS(SEGUIMIENTO_PROYECTOS!$A$5:$A$185,DASHBOARD_KPIs!$E$3,SEGUIMIENTO_PROYECTOS!$H$5:$H$185,"F. Corvera / (Revisión)",SEGUIMIENTO_PROYECTOS!$W$5:$W$185,"STAND BY") -> 0 | I37: =IFERROR(SUMIFS(SEGUIMIENTO_PROYECTOS!$Y$5:$Y$185,SEGUIMIENTO_PROYECTOS!$A$5:$A$185,DASHBOARD_KPIs!$E$3,SEGUIMIENTO_PROYECTOS!$H$5:$H$185,"F. Corvera / (Revisión)")/SUMIFS(SEGUIMIENTO_PROYECTOS!$X$5:$X$185,SEGUIMIENTO_PROYECTOS!$A$5:$A$185,DASHBOARD_KPIs!$E$3,SEGUIMIENTO_PROYECTOS!$H$5:$H$185,"F. Corvera / (Revisión)"),"—") -> 0.36363636
B38: Giancarlo G | C38: =COUNTIFS(SEGUIMIENTO_PROYECTOS!$A$5:$A$185,DASHBOARD_KPIs!$E$3,SEGUIMIENTO_PROYECTOS!$H$5:$H$185,"Giancarlo G")-COUNTIFS(SEGUIMIENTO_PROYECTOS!$A$5:$A$185,DASHBOARD_KPIs!$E$3,SEGUIMIENTO_PROYECTOS!$H$5:$H$185,"Giancarlo G",SEGUIMIENTO_PROYECTOS!$F$5:$F$185,"CERRADO")-COUNTIFS(SEGUIMIENTO_PROYECTOS!$A$5:$A$185,DASHBOARD_KPIs!$E$3,SEGUIMIENTO_PROYECTOS!$H$5:$H$185,"Giancarlo G",SEGUIMIENTO_PROYECTOS!$F$5:$F$185,"CANCELADO")-COUNTIFS(SEGUIMIENTO_PROYECTOS!$A$5:$A$185,DASHBOARD_KPIs!$E$3,SEGUIMIENTO_PROYECTOS!$H$5:$H$185,"Giancarlo G",SEGUIMIENTO_PROYECTOS!$F$5:$F$185,"DESCARTADO") -> 0 | D38: =COUNTIFS(SEGUIMIENTO_PROYECTOS!$A$5:$A$185,DASHBOARD_KPIs!$E$3,SEGUIMIENTO_PROYECTOS!$H$5:$H$185,"Giancarlo G",SEGUIMIENTO_PROYECTOS!$W$5:$W$185,"CONFORME") -> 0 | E38: =COUNTIFS(SEGUIMIENTO_PROYECTOS!$A$5:$A$185,DASHBOARD_KPIs!$E$3,SEGUIMIENTO_PROYECTOS!$H$5:$H$185,"Giancarlo G",SEGUIMIENTO_PROYECTOS!$W$5:$W$185,"ALERTA") -> 0 | F38: =COUNTIFS(SEGUIMIENTO_PROYECTOS!$A$5:$A$185,DASHBOARD_KPIs!$E$3,SEGUIMIENTO_PROYECTOS!$H$5:$H$185,"Giancarlo G",SEGUIMIENTO_PROYECTOS!$W$5:$W$185,"CRITICO") -> 2 | G38: =COUNTIFS(SEGUIMIENTO_PROYECTOS!$A$5:$A$185,DASHBOARD_KPIs!$E$3,SEGUIMIENTO_PROYECTOS!$H$5:$H$185,"Giancarlo G",SEGUIMIENTO_PROYECTOS!$F$5:$F$185,"CERRADO") -> 2 | H38: =COUNTIFS(SEGUIMIENTO_PROYECTOS!$A$5:$A$185,DASHBOARD_KPIs!$E$3,SEGUIMIENTO_PROYECTOS!$H$5:$H$185,"Giancarlo G",SEGUIMIENTO_PROYECTOS!$W$5:$W$185,"STAND BY") -> 0 | I38: =IFERROR(SUMIFS(SEGUIMIENTO_PROYECTOS!$Y$5:$Y$185,SEGUIMIENTO_PROYECTOS!$A$5:$A$185,DASHBOARD_KPIs!$E$3,SEGUIMIENTO_PROYECTOS!$H$5:$H$185,"Giancarlo G")/SUMIFS(SEGUIMIENTO_PROYECTOS!$X$5:$X$185,SEGUIMIENTO_PROYECTOS!$A$5:$A$185,DASHBOARD_KPIs!$E$3,SEGUIMIENTO_PROYECTOS!$H$5:$H$185,"Giancarlo G"),"—") -> 0
B39: J. Lara | C39: =COUNTIFS(SEGUIMIENTO_PROYECTOS!$A$5:$A$185,DASHBOARD_KPIs!$E$3,SEGUIMIENTO_PROYECTOS!$H$5:$H$185,"J. Lara")-COUNTIFS(SEGUIMIENTO_PROYECTOS!$A$5:$A$185,DASHBOARD_KPIs!$E$3,SEGUIMIENTO_PROYECTOS!$H$5:$H$185,"J. Lara",SEGUIMIENTO_PROYECTOS!$F$5:$F$185,"CERRADO")-COUNTIFS(SEGUIMIENTO_PROYECTOS!$A$5:$A$185,DASHBOARD_KPIs!$E$3,SEGUIMIENTO_PROYECTOS!$H$5:$H$185,"J. Lara",SEGUIMIENTO_PROYECTOS!$F$5:$F$185,"CANCELADO")-COUNTIFS(SEGUIMIENTO_PROYECTOS!$A$5:$A$185,DASHBOARD_KPIs!$E$3,SEGUIMIENTO_PROYECTOS!$H$5:$H$185,"J. Lara",SEGUIMIENTO_PROYECTOS!$F$5:$F$185,"DESCARTADO") -> 0 | D39: =COUNTIFS(SEGUIMIENTO_PROYECTOS!$A$5:$A$185,DASHBOARD_KPIs!$E$3,SEGUIMIENTO_PROYECTOS!$H$5:$H$185,"J. Lara",SEGUIMIENTO_PROYECTOS!$W$5:$W$185,"CONFORME") -> 5 | E39: =COUNTIFS(SEGUIMIENTO_PROYECTOS!$A$5:$A$185,DASHBOARD_KPIs!$E$3,SEGUIMIENTO_PROYECTOS!$H$5:$H$185,"J. Lara",SEGUIMIENTO_PROYECTOS!$W$5:$W$185,"ALERTA") -> 5 | F39: =COUNTIFS(SEGUIMIENTO_PROYECTOS!$A$5:$A$185,DASHBOARD_KPIs!$E$3,SEGUIMIENTO_PROYECTOS!$H$5:$H$185,"J. Lara",SEGUIMIENTO_PROYECTOS!$W$5:$W$185,"CRITICO") -> 1 | G39: =COUNTIFS(SEGUIMIENTO_PROYECTOS!$A$5:$A$185,DASHBOARD_KPIs!$E$3,SEGUIMIENTO_PROYECTOS!$H$5:$H$185,"J. Lara",SEGUIMIENTO_PROYECTOS!$F$5:$F$185,"CERRADO") -> 11 | H39: =COUNTIFS(SEGUIMIENTO_PROYECTOS!$A$5:$A$185,DASHBOARD_KPIs!$E$3,SEGUIMIENTO_PROYECTOS!$H$5:$H$185,"J. Lara",SEGUIMIENTO_PROYECTOS!$W$5:$W$185,"STAND BY") -> 0 | I39: =IFERROR(SUMIFS(SEGUIMIENTO_PROYECTOS!$Y$5:$Y$185,SEGUIMIENTO_PROYECTOS!$A$5:$A$185,DASHBOARD_KPIs!$E$3,SEGUIMIENTO_PROYECTOS!$H$5:$H$185,"J. Lara")/SUMIFS(SEGUIMIENTO_PROYECTOS!$X$5:$X$185,SEGUIMIENTO_PROYECTOS!$A$5:$A$185,DASHBOARD_KPIs!$E$3,SEGUIMIENTO_PROYECTOS!$H$5:$H$185,"J. Lara"),"—") -> 0.75
B40: M. Becerra | C40: =COUNTIFS(SEGUIMIENTO_PROYECTOS!$A$5:$A$185,DASHBOARD_KPIs!$E$3,SEGUIMIENTO_PROYECTOS!$H$5:$H$185,"M. Becerra")-COUNTIFS(SEGUIMIENTO_PROYECTOS!$A$5:$A$185,DASHBOARD_KPIs!$E$3,SEGUIMIENTO_PROYECTOS!$H$5:$H$185,"M. Becerra",SEGUIMIENTO_PROYECTOS!$F$5:$F$185,"CERRADO")-COUNTIFS(SEGUIMIENTO_PROYECTOS!$A$5:$A$185,DASHBOARD_KPIs!$E$3,SEGUIMIENTO_PROYECTOS!$H$5:$H$185,"M. Becerra",SEGUIMIENTO_PROYECTOS!$F$5:$F$185,"CANCELADO")-COUNTIFS(SEGUIMIENTO_PROYECTOS!$A$5:$A$185,DASHBOARD_KPIs!$E$3,SEGUIMIENTO_PROYECTOS!$H$5:$H$185,"M. Becerra",SEGUIMIENTO_PROYECTOS!$F$5:$F$185,"DESCARTADO") -> 8 | D40: =COUNTIFS(SEGUIMIENTO_PROYECTOS!$A$5:$A$185,DASHBOARD_KPIs!$E$3,SEGUIMIENTO_PROYECTOS!$H$5:$H$185,"M. Becerra",SEGUIMIENTO_PROYECTOS!$W$5:$W$185,"CONFORME") -> 1 | E40: =COUNTIFS(SEGUIMIENTO_PROYECTOS!$A$5:$A$185,DASHBOARD_KPIs!$E$3,SEGUIMIENTO_PROYECTOS!$H$5:$H$185,"M. Becerra",SEGUIMIENTO_PROYECTOS!$W$5:$W$185,"ALERTA") -> 7 | F40: =COUNTIFS(SEGUIMIENTO_PROYECTOS!$A$5:$A$185,DASHBOARD_KPIs!$E$3,SEGUIMIENTO_PROYECTOS!$H$5:$H$185,"M. Becerra",SEGUIMIENTO_PROYECTOS!$W$5:$W$185,"CRITICO") -> 7 | G40: =COUNTIFS(SEGUIMIENTO_PROYECTOS!$A$5:$A$185,DASHBOARD_KPIs!$E$3,SEGUIMIENTO_PROYECTOS!$H$5:$H$185,"M. Becerra",SEGUIMIENTO_PROYECTOS!$F$5:$F$185,"CERRADO") -> 8 | H40: =COUNTIFS(SEGUIMIENTO_PROYECTOS!$A$5:$A$185,DASHBOARD_KPIs!$E$3,SEGUIMIENTO_PROYECTOS!$H$5:$H$185,"M. Becerra",SEGUIMIENTO_PROYECTOS!$W$5:$W$185,"STAND BY") -> 0 | I40: =IFERROR(SUMIFS(SEGUIMIENTO_PROYECTOS!$Y$5:$Y$185,SEGUIMIENTO_PROYECTOS!$A$5:$A$185,DASHBOARD_KPIs!$E$3,SEGUIMIENTO_PROYECTOS!$H$5:$H$185,"M. Becerra")/SUMIFS(SEGUIMIENTO_PROYECTOS!$X$5:$X$185,SEGUIMIENTO_PROYECTOS!$A$5:$A$185,DASHBOARD_KPIs!$E$3,SEGUIMIENTO_PROYECTOS!$H$5:$H$185,"M. Becerra"),"—") -> 0.5
B41: M. Gómez | C41: =COUNTIFS(SEGUIMIENTO_PROYECTOS!$A$5:$A$185,DASHBOARD_KPIs!$E$3,SEGUIMIENTO_PROYECTOS!$H$5:$H$185,"M. Gómez")-COUNTIFS(SEGUIMIENTO_PROYECTOS!$A$5:$A$185,DASHBOARD_KPIs!$E$3,SEGUIMIENTO_PROYECTOS!$H$5:$H$185,"M. Gómez",SEGUIMIENTO_PROYECTOS!$F$5:$F$185,"CERRADO")-COUNTIFS(SEGUIMIENTO_PROYECTOS!$A$5:$A$185,DASHBOARD_KPIs!$E$3,SEGUIMIENTO_PROYECTOS!$H$5:$H$185,"M. Gómez",SEGUIMIENTO_PROYECTOS!$F$5:$F$185,"CANCELADO")-COUNTIFS(SEGUIMIENTO_PROYECTOS!$A$5:$A$185,DASHBOARD_KPIs!$E$3,SEGUIMIENTO_PROYECTOS!$H$5:$H$185,"M. Gómez",SEGUIMIENTO_PROYECTOS!$F$5:$F$185,"DESCARTADO") -> 0 | D41: =COUNTIFS(SEGUIMIENTO_PROYECTOS!$A$5:$A$185,DASHBOARD_KPIs!$E$3,SEGUIMIENTO_PROYECTOS!$H$5:$H$185,"M. Gómez",SEGUIMIENTO_PROYECTOS!$W$5:$W$185,"CONFORME") -> 3 | E41: =COUNTIFS(SEGUIMIENTO_PROYECTOS!$A$5:$A$185,DASHBOARD_KPIs!$E$3,SEGUIMIENTO_PROYECTOS!$H$5:$H$185,"M. Gómez",SEGUIMIENTO_PROYECTOS!$W$5:$W$185,"ALERTA") -> 6 | F41: =COUNTIFS(SEGUIMIENTO_PROYECTOS!$A$5:$A$185,DASHBOARD_KPIs!$E$3,SEGUIMIENTO_PROYECTOS!$H$5:$H$185,"M. Gómez",SEGUIMIENTO_PROYECTOS!$W$5:$W$185,"CRITICO") -> 2 | G41: =COUNTIFS(SEGUIMIENTO_PROYECTOS!$A$5:$A$185,DASHBOARD_KPIs!$E$3,SEGUIMIENTO_PROYECTOS!$H$5:$H$185,"M. Gómez",SEGUIMIENTO_PROYECTOS!$F$5:$F$185,"CERRADO") -> 11 | H41: =COUNTIFS(SEGUIMIENTO_PROYECTOS!$A$5:$A$185,DASHBOARD_KPIs!$E$3,SEGUIMIENTO_PROYECTOS!$H$5:$H$185,"M. Gómez",SEGUIMIENTO_PROYECTOS!$W$5:$W$185,"STAND BY") -> 0 | I41: =IFERROR(SUMIFS(SEGUIMIENTO_PROYECTOS!$Y$5:$Y$185,SEGUIMIENTO_PROYECTOS!$A$5:$A$185,DASHBOARD_KPIs!$E$3,SEGUIMIENTO_PROYECTOS!$H$5:$H$185,"M. Gómez")/SUMIFS(SEGUIMIENTO_PROYECTOS!$X$5:$X$185,SEGUIMIENTO_PROYECTOS!$A$5:$A$185,DASHBOARD_KPIs!$E$3,SEGUIMIENTO_PROYECTOS!$H$5:$H$185,"M. Gómez"),"—") -> 0.66666667
B42: N. Cruz | C42: =COUNTIFS(SEGUIMIENTO_PROYECTOS!$A$5:$A$185,DASHBOARD_KPIs!$E$3,SEGUIMIENTO_PROYECTOS!$H$5:$H$185,"N. Cruz")-COUNTIFS(SEGUIMIENTO_PROYECTOS!$A$5:$A$185,DASHBOARD_KPIs!$E$3,SEGUIMIENTO_PROYECTOS!$H$5:$H$185,"N. Cruz",SEGUIMIENTO_PROYECTOS!$F$5:$F$185,"CERRADO")-COUNTIFS(SEGUIMIENTO_PROYECTOS!$A$5:$A$185,DASHBOARD_KPIs!$E$3,SEGUIMIENTO_PROYECTOS!$H$5:$H$185,"N. Cruz",SEGUIMIENTO_PROYECTOS!$F$5:$F$185,"CANCELADO")-COUNTIFS(SEGUIMIENTO_PROYECTOS!$A$5:$A$185,DASHBOARD_KPIs!$E$3,SEGUIMIENTO_PROYECTOS!$H$5:$H$185,"N. Cruz",SEGUIMIENTO_PROYECTOS!$F$5:$F$185,"DESCARTADO") -> 0 | D42: =COUNTIFS(SEGUIMIENTO_PROYECTOS!$A$5:$A$185,DASHBOARD_KPIs!$E$3,SEGUIMIENTO_PROYECTOS!$H$5:$H$185,"N. Cruz",SEGUIMIENTO_PROYECTOS!$W$5:$W$185,"CONFORME") -> 0 | E42: =COUNTIFS(SEGUIMIENTO_PROYECTOS!$A$5:$A$185,DASHBOARD_KPIs!$E$3,SEGUIMIENTO_PROYECTOS!$H$5:$H$185,"N. Cruz",SEGUIMIENTO_PROYECTOS!$W$5:$W$185,"ALERTA") -> 2 | F42: =COUNTIFS(SEGUIMIENTO_PROYECTOS!$A$5:$A$185,DASHBOARD_KPIs!$E$3,SEGUIMIENTO_PROYECTOS!$H$5:$H$185,"N. Cruz",SEGUIMIENTO_PROYECTOS!$W$5:$W$185,"CRITICO") -> 1 | G42: =COUNTIFS(SEGUIMIENTO_PROYECTOS!$A$5:$A$185,DASHBOARD_KPIs!$E$3,SEGUIMIENTO_PROYECTOS!$H$5:$H$185,"N. Cruz",SEGUIMIENTO_PROYECTOS!$F$5:$F$185,"CERRADO") -> 3 | H42: =COUNTIFS(SEGUIMIENTO_PROYECTOS!$A$5:$A$185,DASHBOARD_KPIs!$E$3,SEGUIMIENTO_PROYECTOS!$H$5:$H$185,"N. Cruz",SEGUIMIENTO_PROYECTOS!$W$5:$W$185,"STAND BY") -> 0 | I42: =IFERROR(SUMIFS(SEGUIMIENTO_PROYECTOS!$Y$5:$Y$185,SEGUIMIENTO_PROYECTOS!$A$5:$A$185,DASHBOARD_KPIs!$E$3,SEGUIMIENTO_PROYECTOS!$H$5:$H$185,"N. Cruz")/SUMIFS(SEGUIMIENTO_PROYECTOS!$X$5:$X$185,SEGUIMIENTO_PROYECTOS!$A$5:$A$185,DASHBOARD_KPIs!$E$3,SEGUIMIENTO_PROYECTOS!$H$5:$H$185,"N. Cruz"),"—") -> 0.47222222
B43: P. Lavado | C43: =COUNTIFS(SEGUIMIENTO_PROYECTOS!$A$5:$A$185,DASHBOARD_KPIs!$E$3,SEGUIMIENTO_PROYECTOS!$H$5:$H$185,"P. Lavado")-COUNTIFS(SEGUIMIENTO_PROYECTOS!$A$5:$A$185,DASHBOARD_KPIs!$E$3,SEGUIMIENTO_PROYECTOS!$H$5:$H$185,"P. Lavado",SEGUIMIENTO_PROYECTOS!$F$5:$F$185,"CERRADO")-COUNTIFS(SEGUIMIENTO_PROYECTOS!$A$5:$A$185,DASHBOARD_KPIs!$E$3,SEGUIMIENTO_PROYECTOS!$H$5:$H$185,"P. Lavado",SEGUIMIENTO_PROYECTOS!$F$5:$F$185,"CANCELADO")-COUNTIFS(SEGUIMIENTO_PROYECTOS!$A$5:$A$185,DASHBOARD_KPIs!$E$3,SEGUIMIENTO_PROYECTOS!$H$5:$H$185,"P. Lavado",SEGUIMIENTO_PROYECTOS!$F$5:$F$185,"DESCARTADO") -> 3 | D43: =COUNTIFS(SEGUIMIENTO_PROYECTOS!$A$5:$A$185,DASHBOARD_KPIs!$E$3,SEGUIMIENTO_PROYECTOS!$H$5:$H$185,"P. Lavado",SEGUIMIENTO_PROYECTOS!$W$5:$W$185,"CONFORME") -> 0 | E43: =COUNTIFS(SEGUIMIENTO_PROYECTOS!$A$5:$A$185,DASHBOARD_KPIs!$E$3,SEGUIMIENTO_PROYECTOS!$H$5:$H$185,"P. Lavado",SEGUIMIENTO_PROYECTOS!$W$5:$W$185,"ALERTA") -> 2 | F43: =COUNTIFS(SEGUIMIENTO_PROYECTOS!$A$5:$A$185,DASHBOARD_KPIs!$E$3,SEGUIMIENTO_PROYECTOS!$H$5:$H$185,"P. Lavado",SEGUIMIENTO_PROYECTOS!$W$5:$W$185,"CRITICO") -> 12 | G43: =COUNTIFS(SEGUIMIENTO_PROYECTOS!$A$5:$A$185,DASHBOARD_KPIs!$E$3,SEGUIMIENTO_PROYECTOS!$H$5:$H$185,"P. Lavado",SEGUIMIENTO_PROYECTOS!$F$5:$F$185,"CERRADO") -> 12 | H43: =COUNTIFS(SEGUIMIENTO_PROYECTOS!$A$5:$A$185,DASHBOARD_KPIs!$E$3,SEGUIMIENTO_PROYECTOS!$H$5:$H$185,"P. Lavado",SEGUIMIENTO_PROYECTOS!$W$5:$W$185,"STAND BY") -> 0 | I43: =IFERROR(SUMIFS(SEGUIMIENTO_PROYECTOS!$Y$5:$Y$185,SEGUIMIENTO_PROYECTOS!$A$5:$A$185,DASHBOARD_KPIs!$E$3,SEGUIMIENTO_PROYECTOS!$H$5:$H$185,"P. Lavado")/SUMIFS(SEGUIMIENTO_PROYECTOS!$X$5:$X$185,SEGUIMIENTO_PROYECTOS!$A$5:$A$185,DASHBOARD_KPIs!$E$3,SEGUIMIENTO_PROYECTOS!$H$5:$H$185,"P. Lavado"),"—") -> 0.30232558
B44: R. Nuñez | C44: =COUNTIFS(SEGUIMIENTO_PROYECTOS!$A$5:$A$185,DASHBOARD_KPIs!$E$3,SEGUIMIENTO_PROYECTOS!$H$5:$H$185,"R. Nuñez")-COUNTIFS(SEGUIMIENTO_PROYECTOS!$A$5:$A$185,DASHBOARD_KPIs!$E$3,SEGUIMIENTO_PROYECTOS!$H$5:$H$185,"R. Nuñez",SEGUIMIENTO_PROYECTOS!$F$5:$F$185,"CERRADO")-COUNTIFS(SEGUIMIENTO_PROYECTOS!$A$5:$A$185,DASHBOARD_KPIs!$E$3,SEGUIMIENTO_PROYECTOS!$H$5:$H$185,"R. Nuñez",SEGUIMIENTO_PROYECTOS!$F$5:$F$185,"CANCELADO")-COUNTIFS(SEGUIMIENTO_PROYECTOS!$A$5:$A$185,DASHBOARD_KPIs!$E$3,SEGUIMIENTO_PROYECTOS!$H$5:$H$185,"R. Nuñez",SEGUIMIENTO_PROYECTOS!$F$5:$F$185,"DESCARTADO") -> 0 | D44: =COUNTIFS(SEGUIMIENTO_PROYECTOS!$A$5:$A$185,DASHBOARD_KPIs!$E$3,SEGUIMIENTO_PROYECTOS!$H$5:$H$185,"R. Nuñez",SEGUIMIENTO_PROYECTOS!$W$5:$W$185,"CONFORME") -> 0 | E44: =COUNTIFS(SEGUIMIENTO_PROYECTOS!$A$5:$A$185,DASHBOARD_KPIs!$E$3,SEGUIMIENTO_PROYECTOS!$H$5:$H$185,"R. Nuñez",SEGUIMIENTO_PROYECTOS!$W$5:$W$185,"ALERTA") -> 0 | F44: =COUNTIFS(SEGUIMIENTO_PROYECTOS!$A$5:$A$185,DASHBOARD_KPIs!$E$3,SEGUIMIENTO_PROYECTOS!$H$5:$H$185,"R. Nuñez",SEGUIMIENTO_PROYECTOS!$W$5:$W$185,"CRITICO") -> 3 | G44: =COUNTIFS(SEGUIMIENTO_PROYECTOS!$A$5:$A$185,DASHBOARD_KPIs!$E$3,SEGUIMIENTO_PROYECTOS!$H$5:$H$185,"R. Nuñez",SEGUIMIENTO_PROYECTOS!$F$5:$F$185,"CERRADO") -> 3 | H44: =COUNTIFS(SEGUIMIENTO_PROYECTOS!$A$5:$A$185,DASHBOARD_KPIs!$E$3,SEGUIMIENTO_PROYECTOS!$H$5:$H$185,"R. Nuñez",SEGUIMIENTO_PROYECTOS!$W$5:$W$185,"STAND BY") -> 0 | I44: =IFERROR(SUMIFS(SEGUIMIENTO_PROYECTOS!$Y$5:$Y$185,SEGUIMIENTO_PROYECTOS!$A$5:$A$185,DASHBOARD_KPIs!$E$3,SEGUIMIENTO_PROYECTOS!$H$5:$H$185,"R. Nuñez")/SUMIFS(SEGUIMIENTO_PROYECTOS!$X$5:$X$185,SEGUIMIENTO_PROYECTOS!$A$5:$A$185,DASHBOARD_KPIs!$E$3,SEGUIMIENTO_PROYECTOS!$H$5:$H$185,"R. Nuñez"),"—") -> 0

Sheet LEYENDA
A1: LEYENDA DE COLORES Y LÓGICA DE ESTADOS
B3: ESTADOS ENTREGABLES (cols J–S) — cambian automáticamente al editar
B4: OK | C4: Entregable completado y conforme
B5: EN PROCESO | C5: En elaboración o levantando observaciones
B6: PENDIENTE | C6: No iniciado — requiere acción inmediata
B7: NO APLICA | C7: El servicio no requiere este entregable
B8: DESCARTADA | C8: Descartado por decisión del cliente
B9: - | C9: Sin información
B11: % SIG (col V) — se recalcula automáticamente
B12: ≥ 90% | C12: → CONFORME
B13: 50–89% | C13: → EN RIESGO
B14: < 50% | C14: → CRÍTICO
B16: ESTADO GENERAL (col W) — se actualiza automáticamente
B17: CONFORME | C17: Activo con % SIG ≥ 90%
B18: EN RIESGO | C18: Activo con % SIG 50–89%
B19: CRITICO | C19: Activo con % SIG < 50%
B20: CERRADO | C20: Etapa = CERRADO
B21: CANCELADO | C21: Etapa = CANCELADO
B22: STAND BY | C22: Etapa = STAND BY
B23: DESCARTADO | C23: Etapa = DESCARTADO
B24: S/D | C24: Sin datos suficientes
B26: DASHBOARD — USO DEL FILTRO DE AÑO
B27: 0 = TODOS | C27: Muestra todos los años (2024+2025+2026)
B28: 2024 / 2025 / 2026 | C28: Filtra solo el año seleccionado en celda D3
B29: % SIG PROM. | C29: Calculado directamente desde columnas J:S (no desde col V)

Sheet CATÁLOGOS
A1: CATÁLOGOS — LISTAS MAESTRAS
A3: ETAPA ACTUAL | C3: TIPO SGC | E3: ESTADO ENTREGABLE | G3: RESPONSABLES
A4: POR INICIAR | C4: A | E4: OK | G4: A. Ferrer
A5: ING | C5: B | E5: EN PROCESO | G5: B. López
A6: LIC | C6: C | E6: PENDIENTE | G6: C. Castillo
A7: RI | C7: D | E7: NO APLICA | G7: C. Castillo / Michael Gómez
A8: CONS | E8: DESCARTADA | G8: C. Valdizán
A9: GP | G9: F. Choque
A10: SUP | G10: F. Corvera
A11: CIERRE | G11: F. Corvera / (Revisión)
A12: CERRADO | G12: Giancarlo G
A13: CANCELADO | G13: J. Lara
A14: STAND BY | G14: M. Becerra
G15: M. Gómez
G16: N. Cruz
G17: P. Lavado
G18: R. Nuñez
